Workbook
Name anchor_src_columns_note: #REF!
Name anchor_src_columns_note: #REF!
Name anchor_src_columns_null: #REF!
Name anchor_src_columns_null: #REF!
Name anchor_src_columns_pk: #REF!
Name anchor_src_columns_pk: #REF!
Name anchor_src_columns_type: #REF!
Name anchor_src_columns_type: #REF!
Name anchor_tgt_columns_def: #REF!
Name anchor_tgt_columns_def: 'Source columns'!#REF!
Name anchor_tgt_columns_def: #REF!
Name anchor_tgt_columns_fk: #REF!
Name anchor_tgt_columns_fk: 'Source columns'!$H$1
Name anchor_tgt_columns_fk: #REF!
Name anchor_tgt_columns_note: #REF!
Name anchor_tgt_columns_note: 'Source columns'!$J$1
Name anchor_tgt_columns_note: #REF!
Name anchor_tgt_columns_null: #REF!
Name anchor_tgt_columns_null: 'Source columns'!$E$1
Name anchor_tgt_columns_null: #REF!
Name anchor_tgt_columns_pk: #REF!
Name anchor_tgt_columns_pk: 'Source columns'!$G$1
Name anchor_tgt_columns_pk: #REF!
Name anchor_tgt_columns_po: #REF!
Name anchor_tgt_columns_po: 'Source columns'!$F$1
Name anchor_tgt_columns_po: #REF!
Name anchor_tgt_columns_type: #REF!
Name anchor_tgt_columns_type: 'Source columns'!$D$1
Name anchor_tgt_columns_type: #REF!
Name anchor_tgt_tables_ntab: #REF!
Name anchor_tgt_tables_ntab: 'Target tables'!$E$1
Name anchor_tgt_tables_ntab: #REF!
Name anchor_tgt_tables_sa: #REF!
Name anchor_tgt_tables_sa: 'Target tables'!$D$1
Name anchor_tgt_tables_sa: #REF!
Name d: '[1]Target columns'!$D$1
Name first_value: Глоссарий!$I$1:$I$3
Name lst_src_columns: #REF!
Name lst_src_columns: #REF!
Name lst_tgt_columns: #REF!
Name lst_tgt_columns: 'Source columns'!$A:$J
Name lst_tgt_columns: #REF!
Name lst_tgt_tables: #REF!
Name lst_tgt_tables: 'Target tables'!$A:$E
Name lst_tgt_tables: #REF!
Name sff: '[1]Target columns'!$H$1
Name target_columns2: #REF!

Sheet Список изменений
A1: Версия | B1: Дата | C1: Измененный объект | D1: Изменение | E1: Автор | F1: Комментарий | G1: Номер патча
A2: 0.5 | B2: 45565 | C2: S2T, Source columns, Target tables, Target columns | D2: Добавлен атрибут в t_registry, добавлена таблица t_registry_type. Изменен тип поля rateSubsidyScheme_agreement | E2: Свиридова
A3: 0.6 | B3: 45573 | C3: S2T, Additional objects | D3: Добавлено условие фильтрации для таблицы t_agr_escrow_int_org. Изменен SQL-запрос для V_B3080000460001_legalEpkId | E3: Свиридова
A4: 0.7 | B4: 45574 | C4: S2T, Additional objects | D4: Добавлено условие фильтрации для таблицы t_agr_escrow_int_org. Изменен SQL-запрос для V_B3080000460001_escrowBranchCode | E4: Свиридова
A5: 0.8 | B5: 45595 | C5: Additional objects | D5: V_B3080000460001_developerLoanAgr | E5: Масальцева
A6: 0.8 | B6: 45595 | C6: Additional objects | D6: V_B3080000460001_externalRegistryId | E6: Масальцева
A7: 0.8 | B7: 45595 | C7: Additional objects | D7: V_B3080000460001_rateSubsidyScheme | E7: Масальцева
A8: 0.8 | B8: 45595 | C8: Additional objects | D8: V_B3080000460001_legalEpkId | E8: Масальцева
A9: 0.8 | B9: 45595 | C9: Additional objects | D9: V_B3080000460001_currency | E9: Масальцева
A10: 0.8 | B10: 45595 | C10: Additional objects | D10: V_B3080000460001_escrowBranchCode | E10: Масальцева
A11: 0.8 | B11: 45595 | C11: Additional objects | D11: V_B3080000460005_tariffs | E11: Масальцева
A12: 0.8 | B12: 45595 | C12: Additional objects | D12: V_B3080000460006_payments | E12: Масальцева
A13: 0.8 | B13: 45595 | C13: S2T | D13: t_agr_escrow (блок 530 ) | E13: Масальцева
... A59: 0.11 | B59: 45685 | C59: S2T | D59: Изменение имени таблицы b3080000460008_general_agreement_actual_limitschedule | E59: Свиридова
A60: 0.11 | B60: 45685 | C60: S2T | D60: t_registry | E60: Свиридова | F60: ГС исключение счетов резерва
A61: 0.11 | B61: 45685 | C61: Source columns | D61: Изменение имени таблицы b3080000460008_general_agreement_actual_limitschedule и названия поля external_id_uid (external_id) | E61: Свиридова
A62: 0.11 | B62: 45685 | C62: Метаданные для hadoop | D62: Изменение имени таблицы general_agreement_actual_limitschedule | E62: Свиридова
A63: 0.12 | B63: 45688 | C63: Метаданные для hadoop | D63: lcl_agreement_actual: новая таблица lcl_registry: новая таблица payments_2_0_posting: добавлены поля postingEvent.accountDebit.number + postingEvent.accountCredit.registerId + postingEvent.accountCredit.number + postingEvent.operationIdKt payments_2_0_posting: изменен json путь к атрибутам operationIdDt -> postingEvent.operationIdDt accountDebit.registerId -> postingEvent.accountDebit.registerId serviceId -> postingEvent.serviceId | E63: Афанасова
A64: 0.12 | B64: 45688 | C64: hadoop ->A | D64: a_000046_lcl_agreement_actual_dto: новая таблица a_000046_lcl_agreement_credit_contracts: новая таблица a_000046_lcl_agreement_supply_contracts: новая таблица a_000046_lcl_agreement_tariffs: новая таблица a_000046_lcl_agreement_applicant_fee_accounts: новая таблица a_000046_lcl_registry_dto: новая таблица | E64: Афанасова
A65: 0.12 | B65: 45688 | C65: А-слой->В-слой | D65: b3080000460009_lcl_agreement_actual_dto: новая таблица b3080000460010_lcl_agreement_credit_contracts: новая таблица b3080000460011_lcl_agreement_supply_contracts: новая таблица b3080000460012_lcl_agreement_tariffs: новая таблица b3080000460013_lcl_agreement_applicant_fee_accounts: новая таблица b3080000460014_lcl_registry_dto: новая таблица | E65: Афанасова
A66: 0.12 | B66: 45688 | C66: Source columns | D66: b3080000460009_lcl_agreement_actual_dto: новая таблица b3080000460010_lcl_agreement_credit_contracts: новая таблица b3080000460011_lcl_agreement_supply_contracts: новая таблица b3080000460012_lcl_agreement_tariffs: новая таблица b3080000460013_lcl_agreement_applicant_fee_accounts: новая таблица b3080000460013_lcl_registry_dto: новая таблица b3080000460006_payments_2_0_posting_dto: добавлены поля postingevent_accountdebit_number + postingevent_accountcredit_registerid + postingevent_accountcredit_number + postingevent_operationidkt | E66: Афанасова
A67: 0.13 | B67: 45692 | C67: Target columns | D67: t_agr_frame, изменено название поля start_dt на open_dt | E67: Свиридова
A68: 0.13 | B68: 45692 | C68: S2T | D68: t_agr_frame, изменено название поля start_dt на open_dt t_cust --добавлено условие deleted='N' для B-таблиц t_int_org --добавлено условие deleted='N' для B-таблиц, поле rn вынесено во внешний подзапрос (иначе были дубли) t_agr_escrow_int_org --при заполнени action_cd учитывается значение deleted='Y' t_optn_type --добавлено условие deleted='N' t_optn --Создана таблица n308000046_optn, заполняемая функцией sp308000046_bn_00840_optn. При заполнени action_cd учитывается значение deleted='Y'. t_optn$gls --Создана таблица n308000046_optn$gls, заполняемая функцией sp308000046_bn_00920_optn$gls. При заполнени action_cd учитывается значение deleted='Y'. t_cust_org_idfn --при заполнени action_cd учитывается значение deleted='Y' T_optn_fee_type --добавлено условие deleted='N' | E68: Свиридова
A69: 0.14 | B69: 45700 | C69: Source columns | D69: b3080000460006_payments_2_0_posting_dto: добавлено поле external_agreement_id | E69: Афанасова
A70: 0.14 | B70: 45700 | C70: s2t | D70: t_agr_accred | E70: Афанасова | F70: новый блок - Аккредитивы ЮЛ
A71: 0.14 | B71: 45700 | C71: s2t | D71: t_agr_accred_fin | E71: Афанасова | F71: новый блок - Аккредитивы ЮЛ
A72: 0.14 | B72: 45700 | C72: s2t | D72: t_accred_cover_type | E72: Афанасова | F72: новый блок - Аккредитивы ЮЛ
A73: 0.14 | B73: 45700 | C73: s2t | D73: t_time_period_type | E73: Афанасова | F73: новый блок - Аккредитивы ЮЛ
A74: 0.14 | B74: 45700 | C74: s2t | D74: t_agr_accred_type | E74: Афанасова | F74: новый блок - Аккредитивы ЮЛ
A75: 0.14 | B75: 45700 | C75: s2t | D75: t_accred_income_scheme | E75: Афанасова | F75: новый блок - Аккредитивы ЮЛ
A76: 0.14 | B76: 45700 | C76: s2t | D76: t_agr_accred_agr_cred | E76: Афанасова | F76: новый блок - Аккредитивы ЮЛ
A77: 0.14 | B77: 45700 | C77: s2t | D77: t_agr_accred_bank | E77: Афанасова | F77: новый блок - Аккредитивы ЮЛ
A78: 0.14 | B78: 45700 | C78: s2t | D78: t_agr_accred_contract | E78: Афанасова | F78: новый блок - Аккредитивы ЮЛ
A79: 0.14 | B79: 45700 | C79: s2t | D79: t_agr_accred_cust | E79: Афанасова | F79: новый блок - Аккредитивы ЮЛ
A80: 0.14 | B80: 45700 | C80: s2t | D80: t_agr_accred_int_org | E80: Афанасова | F80: новый блок - Аккредитивы ЮЛ
A81: 0.14 | B81: 45700 | C81: s2t | D81: t_bank | E81: Афанасова | F81: новый блок - Аккредитивы ЮЛ
... A99: 0.15 | B99: 45705 | C99: s2t | D99: t_agr_frame_int_org | E99: Свиридова | F99: изменено поле источника для agr_frame_id
A100: 0.15 | B100: 45705 | C100: Source columns | D100: b3080000460009_general_agreement_actual_dto: добавлено поле id | E100: Свиридова
A101: 0.15 | B101: 45705 | C101: Source columns | D101: b3080000460008_general_agreement_actual_limitschedule: добавлено поле id | E101: Свиридова
A102: 0.15 | B102: 45705 | C102: Target columns | D102: t_agr_frame: добавлено поле host_ext_id | E102: Свиридова
A103: 0.16 | B103: 45705 | C103: Метаданные для hadoop | D103: lcl_agreement_actual | E103: Афанасова | F103: актуализировано поле для ссылки на ГС generalagreementexternalid -> generalagreementfactoryid
A104: 0.16 | B104: 45705 | C104: Source columns | D104: b3080000460009_lcl_agreement_actual_dto | E104: Афанасова | F104: актуализировано поле для ссылки на ГС generalagreementexternalid -> generalagreementfactoryid
A105: 0.16 | B105: 45705 | C105: s2t | D105: t_agr_accred | E105: Афанасова | F105: добавлено поле agr_frame_id + заполнение поля
A106: 0.17 | B106: 45709 | C106: А-слой->В-слой Source columns s2t | D106: переименование b3080000460009_lcl_agreement_actual_dto -> b3080000460015_lcl_agreement_actual_dto | E106: Афанасова
A107: 0.18 | B107: 45719 | C107: Метаданные для hadoop Source columns | D107: удалено поле isEarlyPayment.lcl_agreement_actual | E107: Афанасова | F107: АЮЛ
A108: 0.18 | B108: 45719 | C108: s2t | D108: t_cust | E108: Афанасова | F108: АЮЛ: актуализирован мэпинг для host_epk_cust_id: beneficiaryindepkid -> beneficiaryindividualepkrbid
A109: 0.18 | B109: 45719 | C109: s2t | D109: t_cust_org_idfn | E109: Афанасова | F109: АЮЛ: добавлен фильтр deleted = 'N'
A110: 0.18 | B110: 45719 | C110: Source columns | D110: добавлены *_uid поля | E110: Афанасова | F110: АЮЛ
A111: 0.19 | B111: 45723 | C111: S2T, Target columns | D111: t_optn_fee_type | E111: Афанасова | F111: снят фильтр на продукты, выбираются все коды комиссий
A112: 0.20 | B112: 45730 | C112: s2t | D112: t_contract | E112: Афанасова | F112: АЮЛ: заменен фильтр *_uid is not null -> НК is not null (конкатенированный НК, *_uid всегда не пустой)
A113: 0.20 | B113: 45730 | C113: s2t | D113: t_agr_accred_contract | E113: Афанасова | F113: АЮЛ: заменен фильтр *_uid is not null -> НК is not null (конкатенированный НК, *_uid всегда не пустой)
A114: 0.20 | B114: 45730 | C114: s2t | D114: t_cust | E114: Афанасова | F114: АЮЛ: заменен фильтр *_uid is not null -> НК is not null (конкатенированный НК, *_uid всегда не пустой)
A115: 0.20 | B115: 45730 | C115: s2t | D115: t_cust_org_idfn | E115: Афанасова | F115: АЮЛ: заменен фильтр *_uid is not null -> НК is not null (конкатенированный НК, *_uid всегда не пустой)
A116: 0.20 | B116: 45730 | C116: s2t | D116: t_cust_ind_idfn | E116: Афанасова | F116: АЮЛ: заменен фильтр *_uid is not null -> НК is not null (конкатенированный НК, *_uid всегда не пустой)
A117: 0.20 | B117: 45730 | C117: s2t | D117: t_cust_coa | E117: Афанасова | F117: АЮЛ: заменен фильтр *_uid is not null -> НК is not null (конкатенированный НК, *_uid всегда не пустой)
A118: 0.20 | B118: 45730 | C118: s2t | D118: t_agr_accred_cust | E118: Афанасова | F118: АЮЛ: заменен фильтр *_uid is not null -> НК is not null (конкатенированный НК, *_uid всегда не пустой)
... A120: 0.20 | B120: 45740 | C120: s2t | D120: t_agr_accred_int_org | E120: Афанасова | F120: АЮЛ: заменен фильтр *_uid is not null -> НК is not null (конкатенированный НК, *_uid всегда не пустой)
A121: 0.21 | B121: 45731 | C121: S2T Target tables Target columns | D121: t_agr_other | E121: Свиридова
A122: 0.21 | B122: 45731 | C122: S2T Target tables Target columns | D122: t_agr_other_cust | E122: Свиридова
A123: 0.21 | B123: 45731 | C123: S2T Target tables Target columns | D123: t_agr_other_int_org | E123: Свиридова
A124: 0.21 | B124: 45731 | C124: Target tables Target columns | D124: t_agr_other_cust_type | E124: Свиридова
A125: 0.21 | B125: 45731 | C125: Target tables Target columns | D125: t_agr_other_categ | E125: Свиридова
A126: 0.21 | B126: 45731 | C126: Target tables Target columns | D126: t_agr_other_int_org_type | E126: Свиридова
A127: 0.21 | B127: 45731 | C127: S2T Target tables Target columns | D127: t_agr_other_bank | E127: Свиридова
A128: 0.21 | B128: 45731 | C128: Target tables Target columns | D128: t_agr_other_bank_type | E128: Свиридова
A129: 0.21 | B129: 45731 | C129: Target tables Target columns | D129: t_agr_other_coa_role | E129: Свиридова
A130: 0.21 | B130: 45731 | C130: S2T Target tables Target columns | D130: t_agr_other_coa | E130: Свиридова
A131: 0.21 | B131: 45731 | C131: А-слой->В-слой Source columns | D131: b3080000460016_inkasso_export_agreement_actual_dto | E131: Свиридова
A132: 0.21 | B132: 45731 | C132: А-слой->В-слой Source columns | D132: b3080000460017_inkasso_import_agreement_actual_dto | E132: Свиридова
... A136: 0.21 | B136: 45731 | C136: Метаданные для hadoop | D136: reimbursement_agreement_actual_dto | E136: Свиридова
A137: 0.21 | B137: 45731 | C137: S2T | D137: t_coa | E137: Свиридова | F137: Добавлены инкассо и рамбурсы
A138: 0.21 | B138: 45731 | C138: S2T | D138: t_bank | E138: Свиридова | F138: Добавлены инкассо и рамбурсы
A139: 0.21 | B139: 45731 | C139: S2T | D139: t_cust | E139: Свиридова | F139: Добавлены инкассо и рамбурсы
A140: 0.21 | B140: 45731 | C140: S2T | D140: t_int_org | E140: Свиридова | F140: Добавлены инкассо и рамбурсы
A141: 0.21 | B141: 45731 | C141: S2T | D141: t_crncy | E141: Свиридова | F141: Добавлены инкассо и рамбурсы
A142: 0.22 | B142: 45742 | C142: S2T | D142: t_registry | E142: Свиридова | F142: Добавлены инкассо и рамбурсы
A143: 0.22 | B143: 45742 | C143: S2T | D143: t_optn | E143: Свиридова | F143: Добавлены инкассо и рамбурсы
A144: 0.22 | B144: 45742 | C144: S2T | D144: t_optn$gls | E144: Свиридова | F144: Добавлены инкассо и рамбурсы
A145: 0.23 | B145: 45744 | C145: s2t | D145: t_contract | E145: Афанасова | F145: АЮЛ: изменено условие фильтрации исходного набора
A146: 0.23 | B146: 45744 | C146: s2t | D146: t_agr_accred_contract | E146: Афанасова | F146: АЮЛ: изменено условие фильтрации исходного набора
A147: 0.23 | B147: 45750 | C147: s2t | D147: t_agr_cred | E147: Масальцева | F147: АЮЛ: добавлен фильтр сортировки в row_number()
A148: 0.23 | B148: 45750 | C148: s2t | D148: t_agr_accred_agr_cred | E148: Масальцева | F148: АЮЛ: добавлен фильтр сортировки в row_number()
... A164: 0.29 | B164: 45897 | C164: А-слой->В-слой->S-слой | D164: s308_0020_lcl_agrmnt_versioned | E164: Масальцева | F164: Добавлена таблица
A165: 0.30 | B165: 45928 | C165: Метаданные для hadoop | D165: lcl_agreement_actual | E165: Масальцева | F165: Добавлены атрибуты | G165: DMLJL-1881
A166: 0.30 | B166: 45928 | C166: Метаданные для hadoop | D166: lcl_agreement_versioned | E166: Масальцева | F166: Добавлены атрибуты | G166: DMLJL-1881
A167: 0.30 | B167: 45928 | C167: hadoop ->A | D167: guarantee_actual_dto | E167: Масальцева | F167: Добавлена таблица | G167: DMLJL-1876
A168: 0.30 | B168: 45928 | C168: А-слой->В-слой->S-слой | D168: b3080000460021_guarantee_actual_dto | E168: Масальцева | F168: Добавлена таблица | G168: DMLJL-1876
A169: 0.30 | B169: 45928 | C169: А-слой->В-слой->S-слой | D169: s308_0020_lcl_agrmnt_versioned | E169: Масальцева | F169: Добавлены атрибуты | G169: DMLJL-1876
A170: 0.30 | B170: 45928 | C170: Source columns | D170: b3080000460015_lcl_agreement_actual_dto | E170: Масальцева | F170: Добавлены атрибуты | G170: DMLJL-1876
A171: 0.30 | B171: 45928 | C171: Source columns | D171: b3080000460020_lcl_agreement_versioned_dto | E171: Масальцева | F171: Добавлены атрибуты | G171: DMLJL-1876
A172: 0.30 | B172: 45928 | C172: Source columns | D172: b3080000460021_guarantee_actual_dto | E172: Масальцева | F172: Добавлена таблица | G172: DMLJL-1876
A173: 0.30 | B173: 45928 | C173: S2T | D173: t_agr_accred_stts | E173: Масальцева | F173: Добавлена таблица | G173: DMLJL-1876
A174: 0.30 | B174: 45928 | C174: S2T | D174: t_agr_accred_stts_type | E174: Масальцева | F174: Добавлена таблица | G174: DMLJL-1876
A175: 0.30 | B175: 45928 | C175: S2T | D175: t_agr_grntee | E175: Масальцева | F175: Добавлена таблица | G175: DMLJL-1876
A176: 0.30 | B176: 45928 | C176: S2T | D176: t_agr_grntee_cust | E176: Масальцева | F176: Добавлена таблица | G176: DMLJL-1876
... A228: 0.39 | B228: 46107 | C228: S2T | D228: t_agr_escrow | E228: Масальцева | F228: Добавлен атрибут depositing_dt | G228: DMLJL-2139

Sheet S2T
A2: № ПП | B2: Предметная область | C2: Описание целевой таблицы | D2: Таблица-приемник | E2: Тип данных поля приемника | F2: Первичный ключ? | G2: Внешний ключ? | H2: NULL? | I2: Описание поля приемника | J2: Поле приемника | K2: Таблица-источник | L2: Тип данных поля источника | M2: Описание поля источника | N2: Трансформация поля источника | O2: Дополнительная таблица-источник | P2: Условия соединения с дополнительной таблицей | Q2: K-таблица | R2: Условия соединения с K-таблицей | S2: Условия фильтрации исходного набора общий фильтр deleted = 'N' | T2: Пояснения к SQL исходного набора данных | U2: SQL исходного набора данных | V2: Название N-таблицы | W2: Роль в истории | X2: Since min date | Y2: Till max date | Z2: Restrict SQL | AA2: Accumulate | AB2: Full snapshot | AC2: Valid from workaround | AD2: Gaps | AE2: First value | AF2: СОД | AG2: Опции проекта | AH2: Кто менял | AI2: Дата | AJ2: Комментарии
A3: 10 | B3: Эскроу | C3: =IFERROR(VLOOKUP(D3,'Target tables'!A:B,2,0),"") -> Договор эскроу | D3: t_agr_escrow | E3: =IFERROR(VLOOKUP(D3&J3,'Target columns'!A:J,4,FALSE),"") -> UUID | F3: =IFERROR(VLOOKUP(D3&J3,'Target columns'!A:J,7,FALSE),"") -> Yes | G3: =IFERROR(VLOOKUP(D3&J3,'Target columns'!A:J,8,FALSE),"") -> No | H3: =IFERROR(VLOOKUP(D3&J3,'Target columns'!A:J,5,FALSE),"") -> NOT NULL | I3: =IFERROR(VLOOKUP(D3&J3,'Target columns'!A:J,10,FALSE),"") -> Идентификатор договора эскроу | J3: agr_escrow_id | K3: b3080000460001_escrow_legal214_agreement_actual_dto | L3: =IFERROR(VLOOKUP(UPPER(K3&N3), source_columns[], 4,0),"") -> uuid | M3: =IFERROR(VLOOKUP(UPPER(K3&N3), source_columns[], 7,0),"") -> Идентификатор договора эскроу | N3: escrowId_agreement_uid | V3: ="n308000046_"&IFERROR(VLOOKUP(D3, target_tables[], 5, 0),"<not found>") -> n308000046_agr_escrow | W3: Ключ | AF3: Снимок-снимок
A4: 20 | B4: Эскроу | C4: =IFERROR(VLOOKUP(D4,'Target tables'!A:B,2,0),"") -> Договор эскроу | D4: t_agr_escrow | E4: =IFERROR(VLOOKUP(D4&J4,'Target columns'!A:J,4,FALSE),"") -> DATE | F4: =IFERROR(VLOOKUP(D4&J4,'Target columns'!A:J,7,FALSE),"") -> No | G4: =IFERROR(VLOOKUP(D4&J4,'Target columns'!A:J,8,FALSE),"") -> No | H4: =IFERROR(VLOOKUP(D4&J4,'Target columns'!A:J,5,FALSE),"") -> NULL | I4: =IFERROR(VLOOKUP(D4&J4,'Target columns'!A:J,10,FALSE),"") -> Дата открытия договора эскроу | J4: open_dt | K4: b3080000460001_escrow_legal214_agreement_actual_dto | L4: =IFERROR(VLOOKUP(UPPER(K4&N5), source_columns[], 4,0),"") -> date | M4: =IFERROR(VLOOKUP(UPPER(K4&N4),source_columns[],7,0),"") -> Дата открытия договора эскроу | N4: openDate_agreement | V4: ="n308000046_"&IFERROR(VLOOKUP(D4,target_tables[],5,0),"<not found>") -> n308000046_agr_escrow | W4: -
A5: 30 | B5: Эскроу | C5: =IFERROR(VLOOKUP(D5,'Target tables'!A:B,2,0),"") -> Договор эскроу | D5: t_agr_escrow | E5: =IFERROR(VLOOKUP(D5&J5,'Target columns'!A:J,4,FALSE),"") -> DATE | F5: =IFERROR(VLOOKUP(D5&J5,'Target columns'!A:J,7,FALSE),"") -> No | G5: =IFERROR(VLOOKUP(D5&J5,'Target columns'!A:J,8,FALSE),"") -> No | H5: =IFERROR(VLOOKUP(D5&J5,'Target columns'!A:J,5,FALSE),"") -> NULL | I5: =IFERROR(VLOOKUP(D5&J5,'Target columns'!A:J,10,FALSE),"") -> Дата подписания договора эскроу | J5: signed_dt | K5: b3080000460001_escrow_legal214_agreement_actual_dto | L5: =IFERROR(VLOOKUP(UPPER(K5&N6),source_columns[],4,0),"") -> date | M5: =IFERROR(VLOOKUP(UPPER(K5&N5),source_columns[],7,0),"") -> Дата открытия договора эскроу | N5: openDate_agreement | V5: ="n308000046_"&IFERROR(VLOOKUP(D5,target_tables[],5,0),"<not found>") -> n308000046_agr_escrow | W5: -
A6: 40 | B6: Эскроу | C6: =IFERROR(VLOOKUP(D6,'Target tables'!A:B,2,0),"") -> Договор эскроу | D6: t_agr_escrow | E6: =IFERROR(VLOOKUP(D6&J6,'Target columns'!A:J,4,FALSE),"") -> DATE | F6: =IFERROR(VLOOKUP(D6&J6,'Target columns'!A:J,7,FALSE),"") -> No | G6: =IFERROR(VLOOKUP(D6&J6,'Target columns'!A:J,8,FALSE),"") -> No | H6: =IFERROR(VLOOKUP(D6&J6,'Target columns'!A:J,5,FALSE),"") -> NULL | I6: =IFERROR(VLOOKUP(D6&J6,'Target columns'!A:J,10,FALSE),"") -> Дата закрытия договора эскроу | J6: close_dt | K6: b3080000460001_escrow_legal214_agreement_actual_dto | L6: =IFERROR(VLOOKUP(UPPER(K6&N7),source_columns[],4,0),"") -> text | M6: =IFERROR(VLOOKUP(UPPER(K6&N6),source_columns[],7,0),"") -> Дата закрытия договора эскроу | N6: closeDate_agreement | V6: ="n308000046_"&IFERROR(VLOOKUP(D6,target_tables[],5,0),"<not found>") -> n308000046_agr_escrow | W6: -
A7: 50 | B7: Эскроу | C7: =IFERROR(VLOOKUP(D7,'Target tables'!A:B,2,0),"") -> Договор эскроу | D7: t_agr_escrow | E7: =IFERROR(VLOOKUP(D7&J7,'Target columns'!A:J,4,FALSE),"") -> TEXT | F7: =IFERROR(VLOOKUP(D7&J7,'Target columns'!A:J,7,FALSE),"") -> No | G7: =IFERROR(VLOOKUP(D7&J7,'Target columns'!A:J,8,FALSE),"") -> No | H7: =IFERROR(VLOOKUP(D7&J7,'Target columns'!A:J,5,FALSE),"") -> NULL | I7: =IFERROR(VLOOKUP(D7&J7,'Target columns'!A:J,10,FALSE),"") -> Номер договора эскроу | J7: agr_escrow_num | K7: b3080000460001_escrow_legal214_agreement_actual_dto | L7: =IFERROR(VLOOKUP(UPPER(K7&N7), source_columns[], 4,0),"") -> text | M7: =IFERROR(VLOOKUP(UPPER(K7&N7),source_columns[],7,0),"") -> Номер договора | N7: reference_agreement | V7: ="n308000046_"&IFERROR(VLOOKUP(D7,target_tables[],5,0),"<not found>") -> n308000046_agr_escrow | W7: -
A8: 60 | B8: Эскроу | C8: =IFERROR(VLOOKUP(D8,'Target tables'!A:B,2,0),"") -> Договор эскроу | D8: t_agr_escrow | E8: =IFERROR(VLOOKUP(D8&J8,'Target columns'!A:J,4,FALSE),"") -> TEXT | F8: =IFERROR(VLOOKUP(D8&J8,'Target columns'!A:J,7,FALSE),"") -> No | G8: =IFERROR(VLOOKUP(D8&J8,'Target columns'!A:J,8,FALSE),"") -> No | H8: =IFERROR(VLOOKUP(D8&J8,'Target columns'!A:J,5,FALSE),"") -> NULL | I8: =IFERROR(VLOOKUP(D8&J8,'Target columns'!A:J,10,FALSE),"") -> Идентификатор договора эскроу в системе-источнике | J8: host_agr_escrow_id | K8: b3080000460001_escrow_legal214_agreement_actual_dto | L8: =IFERROR(VLOOKUP(UPPER(K8&N8),source_columns[],4,0),"") -> text | M8: =IFERROR(VLOOKUP(UPPER(K8&N8),source_columns[],7,0),"") -> Идентификатор договора эскроу | N8: escrowId_agreement | V8: ="n308000046_"&IFERROR(VLOOKUP(D8,target_tables[],5,0),"<not found>") -> n308000046_agr_escrow | W8: -
A9: 70 | B9: Эскроу | C9: =IFERROR(VLOOKUP(D9,'Target tables'!A:B,2,0),"") -> Договор эскроу | D9: t_agr_escrow | E9: =IFERROR(VLOOKUP(D9&J9,'Target columns'!A:J,4,FALSE),"") -> DATE | F9: =IFERROR(VLOOKUP(D9&J9,'Target columns'!A:J,7,FALSE),"") -> No | G9: =IFERROR(VLOOKUP(D9&J9,'Target columns'!A:J,8,FALSE),"") -> No | H9: =IFERROR(VLOOKUP(D9&J9,'Target columns'!A:J,5,FALSE),"") -> NULL | I9: =IFERROR(VLOOKUP(D9&J9,'Target columns'!A:J,10,FALSE),"") -> Плановая дата ввода в эксплуатацию объекта строительства | J9: permission_explotation_plan_dt | K9: b3080000460001_escrow_legal214_agreement_actual_dto | L9: =IFERROR(VLOOKUP(UPPER(K9&N9),source_columns[],4,0),"") -> date | M9: =IFERROR(VLOOKUP(UPPER(K9&N9),source_columns[],7,0),"") -> Плановая дата ввода ОС в эксплуатацию | N9: completeEstimateDate_agreementObject | V9: ="n308000046_"&IFERROR(VLOOKUP(D9,target_tables[],5,0),"<not found>") -> n308000046_agr_escrow | W9: -
A10: 71 | B10: Эскроу | C10: =IFERROR(VLOOKUP(D10,'Target tables'!A:B,2,0),"") -> Договор эскроу | D10: t_agr_escrow | E10: =IFERROR(VLOOKUP(D10&J10,'Target columns'!A:J,4,FALSE),"") -> DATE | F10: =IFERROR(VLOOKUP(D10&J10,'Target columns'!A:J,7,FALSE),"") -> No | G10: =IFERROR(VLOOKUP(D10&J10,'Target columns'!A:J,8,FALSE),"") -> No | H10: =IFERROR(VLOOKUP(D10&J10,'Target columns'!A:J,5,FALSE),"") -> NULL | I10: =IFERROR(VLOOKUP(D10&J10,'Target columns'!A:J,10,FALSE),"") -> Срок депонирования объекта | J10: depositing_object_dt | K10: b3080000460001_escrow_legal214_agreement_actual_dto | L10: =IFERROR(VLOOKUP(UPPER(K10&N10),source_columns[],4,0),"") -> date | M10: =IFERROR(VLOOKUP(UPPER(K10&N10),source_columns[],7,0),"") -> Срок депонирования объекта | N10: estateObject_ExpireDate_agreementObject | V10: ="n308000046_"&IFERROR(VLOOKUP(D10,target_tables[],5,0),"<not found>") -> n308000046_agr_escrow
A11: 80 | B11: Эскроу | C11: =IFERROR(VLOOKUP(D11,'Target tables'!A:B,2,0),"") -> Договор эскроу | D11: t_agr_escrow | E11: =IFERROR(VLOOKUP(D11&J11,'Target columns'!A:J,4,FALSE),"") -> DECIMAL(26,4) | F11: =IFERROR(VLOOKUP(D11&J11,'Target columns'!A:J,7,FALSE),"") -> No | G11: =IFERROR(VLOOKUP(D11&J11,'Target columns'!A:J,8,FALSE),"") -> No | H11: =IFERROR(VLOOKUP(D11&J11,'Target columns'!A:J,5,FALSE),"") -> NULL | I11: =IFERROR(VLOOKUP(D11&J11,'Target columns'!A:J,10,FALSE),"") -> Сумма депонирования эскроу | J11: start_sum_crncy_amt | K11: b3080000460001_escrow_legal214_agreement_actual_dto | L11: =IFERROR(VLOOKUP(UPPER(K11&N11),source_columns[],4,0),"") -> decimal(38 , 16) | M11: =IFERROR(VLOOKUP(UPPER(K11&N11),source_columns[],7,0),"") -> Сумма депонирования | N11: escrowAmount_value_agreement | V11: ="n308000046_"&IFERROR(VLOOKUP(D11, target_tables[], 5, 0),"<not found>") -> n308000046_agr_escrow | W11: - | AJ11: В json максимальное значение - 10 в 15 степени
A12: 90 | B12: Эскроу | C12: =IFERROR(VLOOKUP(D12,'Target tables'!A:B,2,0),"") -> Договор эскроу | D12: t_agr_escrow | E12: =IFERROR(VLOOKUP(D12&J12,'Target columns'!A:J,4,FALSE),"") -> UUID | F12: =IFERROR(VLOOKUP(D12&J12,'Target columns'!A:J,7,FALSE),"") -> No | G12: =IFERROR(VLOOKUP(D12&J12,'Target columns'!A:J,8,FALSE),"") -> Yes | H12: =IFERROR(VLOOKUP(D12&J12,'Target columns'!A:J,5,FALSE),"") -> NULL | I12: =IFERROR(VLOOKUP(D12&J12,'Target columns'!A:J,10,FALSE),"") -> Идентификатор валюты | J12: crncy_id | K12: b3080000460001_escrow_legal214_agreement_actual_dto | L12: =IFERROR(VLOOKUP(UPPER(K12&N12),source_columns[],4,0),"") -> uuid | M12: =IFERROR(VLOOKUP(UPPER(K12&N12),source_columns[],7,0),"") -> Валюта суммы депонирования | N12: escrowAmount_currency_agreement_uid | V12: ="n308000046_"&IFERROR(VLOOKUP(D12,target_tables[],5,0),"<not found>") -> n308000046_agr_escrow | W12: -
A13: 100 | B13: Эскроу | C13: =IFERROR(VLOOKUP(D13,'Target tables'!A:B,2,0),"") -> Договор эскроу | D13: t_agr_escrow | E13: =IFERROR(VLOOKUP(D13&J13,'Target columns'!A:J,4,FALSE),"") -> UUID | F13: =IFERROR(VLOOKUP(D13&J13,'Target columns'!A:J,7,FALSE),"") -> No | G13: =IFERROR(VLOOKUP(D13&J13,'Target columns'!A:J,8,FALSE),"") -> Yes | H13: =IFERROR(VLOOKUP(D13&J13,'Target columns'!A:J,5,FALSE),"") -> NULL | I13: =IFERROR(VLOOKUP(D13&J13,'Target columns'!A:J,10,FALSE),"") -> Идентификатор схемы | J13: escrow_scheme_id | K13: b3080000460001_escrow_legal214_agreement_actual_dto | L13: =IFERROR(VLOOKUP(UPPER(K13&N13),source_columns[],4,0),"") -> uuid | M13: =IFERROR(VLOOKUP(UPPER(K13&N13),source_columns[],7,0),"") -> Схема субсидирования | N13: rateSubsidyScheme_agreement_uid | V13: ="n308000046_"&IFERROR(VLOOKUP(D13,target_tables[],5,0),"<not found>") -> n308000046_agr_escrow | W13: - | AJ13: По эскроу 214 - это схема субсидирования ставки
A14: 110 | B14: Эскроу | C14: =IFERROR(VLOOKUP(D14,'Target tables'!A:B,2,0),"") -> Договор эскроу | D14: t_agr_escrow | E14: =IFERROR(VLOOKUP(D14&J14,'Target columns'!A:J,4,FALSE),"") -> DATE | F14: =IFERROR(VLOOKUP(D14&J14,'Target columns'!A:J,7,FALSE),"") -> No | G14: =IFERROR(VLOOKUP(D14&J14,'Target columns'!A:J,8,FALSE),"") -> No | H14: =IFERROR(VLOOKUP(D14&J14,'Target columns'!A:J,5,FALSE),"") -> NULL | I14: =IFERROR(VLOOKUP(D14&J14,'Target columns'!A:J,10,FALSE),"") -> Плановая дата окончания/Срок условного депонирования договора | J14: expiration_dt | K14: b3080000460001_escrow_legal214_agreement_actual_dto | L14: =IFERROR(VLOOKUP(UPPER(K14&N14),source_columns[],4,0),"") -> date | M14: =IFERROR(VLOOKUP(UPPER(K14&N14),source_columns[],7,0),"") -> Срок депонирования договора | N14: expireDate_agreementObject | V14: ="n308000046_"&IFERROR(VLOOKUP(D14,target_tables[],5,0),"<not found>") -> n308000046_agr_escrow | W14: -
A15: 120 | B15: Эскроу | C15: =IFERROR(VLOOKUP(D15,'Target tables'!A:B,2,0),"") -> Договор эскроу | D15: t_agr_escrow | E15: =IFERROR(VLOOKUP(D15&J15,'Target columns'!A:J,4,FALSE),"") -> TEXT | F15: =IFERROR(VLOOKUP(D15&J15,'Target columns'!A:J,7,FALSE),"") -> No | G15: =IFERROR(VLOOKUP(D15&J15,'Target columns'!A:J,8,FALSE),"") -> No | H15: =IFERROR(VLOOKUP(D15&J15,'Target columns'!A:J,5,FALSE),"") -> NULL | I15: =IFERROR(VLOOKUP(D15&J15,'Target columns'!A:J,10,FALSE),"") -> Признак работы в рамках 214-ФЗ | J15: agr_214_fed_flag | K15: b3080000460001_escrow_legal214_agreement_actual_dto | L15: =IFERROR(VLOOKUP(UPPER(K15&N15),source_columns[],4,0),"") | M15: =IFERROR(VLOOKUP(UPPER(K15&N15),source_columns[],7,0),"") | N15: 'Y' | V15: ="n308000046_"&IFERROR(VLOOKUP(D15,target_tables[],5,0),"<not found>") -> n308000046_agr_escrow | W15: -
A16: 130 | B16: Эскроу | C16: =IFERROR(VLOOKUP(D16,'Target tables'!A:B,2,0),"") -> Кредитный договор | D16: t_agr_cred | E16: =IFERROR(VLOOKUP(D16&J16,'Target columns'!A:J,4,FALSE),"") -> UUID | F16: =IFERROR(VLOOKUP(D16&J16,'Target columns'!A:J,7,FALSE),"") -> Yes | G16: =IFERROR(VLOOKUP(D16&J16,'Target columns'!A:J,8,FALSE),"") -> No | H16: =IFERROR(VLOOKUP(D16&J16,'Target columns'!A:J,5,FALSE),"") -> NOT NULL | I16: =IFERROR(VLOOKUP(D16&J16,'Target columns'!A:J,10,FALSE),"") -> ИД кредитного договора с застройщиком | J16: agr_cred_id | K16: ETL | L16: uuid | M16: Номер кредитного договора | N16: developerLoanAgrNumber_cred_agreement_uid | S16: SELECT sub_2.agr_cred_id, sub_2.signed_dt, sub_2.agr_cred_num, sub_2.host_eks_agrmnt_id, sub_2.host_agr_cred_id, sub_2.input_file_id, sub_2.info_system_id, CASE WHEN sub_2.deleted_flag = 'Y'::text THEN 'D'::text ELSE sub_2.action_cd END AS action_cd, sub_2.deleted_flag, sub_2.workflow_run_id, '-103500130'::integer AS session_inst_id FROM ( SELECT sub_1.agr_cred_id, sub_1.signed_dt, sub_1.agr_cred_num, sub_1.host_eks_agrmnt_id, sub_1.host_agr_cred_id, sub_1.input_file_id, sub_1.info_system_id, sub_1.ctl_action AS action_cd, sub_1.deleted_flag, sub_1.workflow_run_id, row_number() OVER (PARTITION BY sub_1.agr_cred_id ORDER BY sub_1.signed_dt DESC, COALESCE(sub_1.host_agr_cred_id, '0'::text) DESC, COALESCE(sub_1.host_eks_agrmnt_id, '0'::text) DESC, sub_1.sys_date_create_or_update desc, sub_1.st ) AS rn FROM ( SELECT COALESCE(b3080000460001_escrow_legal214_agreement_actual_dto.devloanagrkulid_agreement_uid, b3080000460001_escrow_legal214_agreement_actual_dto.developerloanagrnumber_cred_agreement_uid) AS agr_cred_id, b3080000460001_escrow_legal214_agreement_actual_dto.developerloanagrdate_cred_agreement AS signed_dt, b3080000460001_escrow_legal214_agreement_actual_dto.developerloanagrnumber_cred_agreement AS agr_cred_num, b3080000460001_escrow_legal214_agreement_actual_dto.devloanagr_eksid_agreement AS host_eks_agrmnt_id, b3080000460001_escrow_legal214_agreement_actual_dto.devloanagrkulid_agreement AS host_agr_cred_id, 2 AS st, b3080000460001_escrow_legal214_agreement_actual_dto.sys_date_create_or_update, b3080000460001_escrow_legal214_agreement_actual_dto.input_file_id, b3080000460001_escrow_legal214_agreement_actual_dto.info_system_id, b3080000460001_escrow_legal214_agreement_actual_dto.ctl_action, b3080000460001_escrow_legal214_agreement_actual_dto.deleted_flag, b3080000460001_escrow_legal214_agreement_actual_dto.workflow_run_id FROM s_grnplm_as_t_didsd_308_db_stg.b3080000460001_escrow_legal214_agreement_actual_dto WHERE (b3080000460001_escrow_legal214_agreement_actual_dto.developerloanagrnumber_cred_agreement IS NOT NULL OR b3080000460001_escrow_legal214_agreement_actual_dto.devloanagrkulid_agreement IS NOT NULL) AND b3080000460001_escrow_legal214_agreement_actual_dto.deleted = 'N'::text UNION ALL SELECT COALESCE(b3080000460002_escrow_legalgk_agreement_actual_dto.depositorlegal_creditcontract_kulid_uid, b3080000460002_escrow_legalgk_agreement_actual_dto.depositorlegal_creditcontract_number_uid) AS agr_cred_id, b3080000460002_escrow_legalgk_agreement_actual_dto.depositorlegal_creditcontract_date AS signed_dt, b3080000460002_escrow_legalgk_agreement_actual_dto.depositorlegal_creditcontract_number AS agr_cred_num, b3080000460002_escrow_legalgk_agreement_actual_dto.depositorlegal_creditcontract_eks AS host_eks_agrmnt_id, b3080000460002_escrow_legalgk_agreement_actual_dto.depositorlegal_creditcontract_kulid AS host_agr_cred_id, 2 AS st, b3080000460002_escrow_legalgk_agreement_actual_dto.sys_date_create_or_update, b3080000460002_escrow_legalgk_agreement_actual_dto.input_file_id, b3080000460002_escrow_legalgk_agreement_actual_dto.info_system_id, b3080000460002_escrow_legalgk_agreement_actual_dto.ctl_action, b3080000460002_escrow_legalgk_agreement_actual_dto.deleted_flag, b3080000460002_escrow_legalgk_agreement_actual_dto.workflow_run_id FROM s_grnplm_as_t_didsd_308_db_stg.b3080000460002_escrow_legalgk_agreement_actual_dto WHERE (b3080000460002_escrow_legalgk_agreement_actual_dto.depositorlegal_creditcontract_number IS NOT NULL OR b3080000460002_escrow_legalgk_agreement_actual_dto.depositorlegal_creditcontract_kulid IS NOT NULL) AND b3080000460002_escrow_legalgk_agreement_actual_dto.deleted = 'N'::text UNION ALL SELECT COALESCE(b3080000460004_escrow_legalgk_beneficiarieslegal.creditcontract_l_kulid_uid, b3080000460004_escrow_legalgk_beneficiarieslegal.creditcontract_d_l_uid) AS agr_cred_id, b3080000460004_escrow_legalgk_beneficiarieslegal.creditcontract_l AS signed_dt, b3080000460004_escrow_legalgk_beneficiarieslegal.creditcontract_d_l AS agr_cred_num, b3080000460004_escrow_legalgk_beneficiarieslegal.creditcontract_l_eksid AS host_eks_agrmnt_id, b3080000460004_escrow_legalgk_beneficiarieslegal.creditcontract_l_kulid AS host_agr_cred_id, 2 AS st, b3080000460004_escrow_legalgk_beneficiarieslegal.sys_date_create_or_update, b3080000460004_escrow_legalgk_beneficiarieslegal.input_file_id, b3080000460004_escrow_legalgk_beneficiarieslegal.info_system_id, b3080000460004_escrow_legalgk_beneficiarieslegal.ctl_action, b3080000460004_escrow_legalgk_beneficiarieslegal.deleted_flag, b3080000460004_escrow_legalgk_beneficiarieslegal.workflow_run_id FROM s_grnplm_as_t_didsd_308_db_stg.b3080000460004_escrow_legalgk_beneficiarieslegal WHERE (b3080000460004_escrow_legalgk_beneficiarieslegal.creditcontract_d_l IS NOT NULL OR b3080000460004_escrow_legalgk_beneficiarieslegal.creditcontract_l_kulid IS NOT NULL) AND b3080000460004_escrow_legalgk_beneficiarieslegal.deleted = 'N'::text UNION ALL SELECT CASE WHEN COALESCE(btrim(b10.creditcontracts_idpprbkul), '-1'::text) = '-1'::text THEN b10.creditcontracts_number_uid ELSE b10.creditcontracts_idpprbkul_uid END AS agr_cred_id, b10.creditcontracts_date AS signed_dt, b10.creditcontracts_number AS agr_cred_num, b10.creditcontracts_eksid AS host_eks_agrmnt_id, b10.creditcontracts_idpprbkul AS host_agr_cred_id, CASE WHEN upper(b10.status) = 'INACTIVE'::text THEN 1 WHEN upper(b10.status) = 'CLOSED'::text THEN 10 ELSE 2 END AS st, b10.sys_date_create_or_update, b10.input_file_id, b10.info_system_id, 'I'::text AS ctl_action, 'N'::text AS deleted_flag, b10.workflow_run_id FROM s_grnplm_as_t_didsd_308_db_stg.b3080000460010_lcl_agreement_credit_contracts b10 WHERE (b10.creditcontracts_number_uid IS NOT NULL OR b10.creditcontracts_idpprbkul IS NOT NULL) AND b10.deleted = 'N'::text) sub_1) sub_2 WHERE sub_2.rn = 1 | V16: ="n308000046_"&IFERROR(VLOOKUP(D16,target_tables[],5,0),"<not found>") -> n308000046_agr_cred | W16: Ключ | AF16: Снимок-снимок | AJ16: это не ссылка на схему 700, на нее выйти технически невозможно
A17: 140 | B17: Эскроу | C17: =IFERROR(VLOOKUP(D17,'Target tables'!A:B,2,0),"") -> Кредитный договор | D17: t_agr_cred | E17: =IFERROR(VLOOKUP(D17&J17,'Target columns'!A:J,4,FALSE),"") -> DATE | F17: =IFERROR(VLOOKUP(D17&J17,'Target columns'!A:J,7,FALSE),"") -> No | G17: =IFERROR(VLOOKUP(D17&J17,'Target columns'!A:J,8,FALSE),"") -> No | H17: =IFERROR(VLOOKUP(D17&J17,'Target columns'!A:J,5,FALSE),"") -> NULL | I17: =IFERROR(VLOOKUP(D17&J17,'Target columns'!A:J,10,FALSE),"") -> Дата подписания договора | J17: signed_dt | K17: ETL | L17: date | M17: Дата кредитного договора | N17: developerLoanAgrDate_cred_agreement | V17: ="n308000046_"&IFERROR(VLOOKUP(D17,target_tables[],5,0),"<not found>") -> n308000046_agr_cred | W17: -
A18: 150 | B18: Эскроу | C18: =IFERROR(VLOOKUP(D18,'Target tables'!A:B,2,0),"") -> Кредитный договор | D18: t_agr_cred | E18: =IFERROR(VLOOKUP(D18&J18,'Target columns'!A:J,4,FALSE),"") -> TEXT | F18: =IFERROR(VLOOKUP(D18&J18,'Target columns'!A:J,7,FALSE),"") -> No | G18: =IFERROR(VLOOKUP(D18&J18,'Target columns'!A:J,8,FALSE),"") -> No | H18: =IFERROR(VLOOKUP(D18&J18,'Target columns'!A:J,5,FALSE),"") -> NULL | I18: =IFERROR(VLOOKUP(D18&J18,'Target columns'!A:J,10,FALSE),"") -> Номер договора | J18: agr_cred_num | K18: ETL | L18: text | M18: Номер кредитного договора | N18: developerLoanAgrNumber_cred_agreement | V18: ="n308000046_"&IFERROR(VLOOKUP(D18,target_tables[],5,0),"<not found>") -> n308000046_agr_cred | W18: -
A19: 160 | B19: Эскроу | C19: =IFERROR(VLOOKUP(D19,'Target tables'!A:B,2,0),"") -> Кредитный договор | D19: t_agr_cred | E19: =IFERROR(VLOOKUP(D19&J19,'Target columns'!A:J,4,FALSE),"") -> TEXT | F19: =IFERROR(VLOOKUP(D19&J19,'Target columns'!A:J,7,FALSE),"") -> No | G19: =IFERROR(VLOOKUP(D19&J19,'Target columns'!A:J,8,FALSE),"") -> No | H19: =IFERROR(VLOOKUP(D19&J19,'Target columns'!A:J,5,FALSE),"") -> NULL | I19: =IFERROR(VLOOKUP(D19&J19,'Target columns'!A:J,10,FALSE),"") -> ID договора в ЕКС | J19: host_eks_agrmnt_id | K19: ETL | L19: text | M19: ID договора в ЕКС | N19: devLoanAgr_EksId_agreement | V19: ="n308000046_"&IFERROR(VLOOKUP(D19,target_tables[],5,0),"<not found>") -> n308000046_agr_cred | W19: -
A20: 170 | B20: Эскроу | C20: =IFERROR(VLOOKUP(D20,'Target tables'!A:B,2,0),"") -> Кредитный договор | D20: t_agr_cred | E20: =IFERROR(VLOOKUP(D20&J20,'Target columns'!A:J,4,FALSE),"") -> TEXT | F20: =IFERROR(VLOOKUP(D20&J20,'Target columns'!A:J,7,FALSE),"") -> No | G20: =IFERROR(VLOOKUP(D20&J20,'Target columns'!A:J,8,FALSE),"") -> No | H20: =IFERROR(VLOOKUP(D20&J20,'Target columns'!A:J,5,FALSE),"") -> NULL | I20: =IFERROR(VLOOKUP(D20&J20,'Target columns'!A:J,10,FALSE),"") -> ИД договора в системе-источнике ППРБ.КЮЛ | J20: host_agr_cred_id | K20: ETL | L20: text | M20: ИД договора в системе-источнике ППРБ.КЮЛ | N20: devLoanAgrKulId_agreement | V20: ="n308000046_"&IFERROR(VLOOKUP(D20,target_tables[],5,0),"<not found>") -> n308000046_agr_cred | W20: -
A21: 180 | B21: Эскроу, ГС, Аккредитив, УПФ | C21: =IFERROR(VLOOKUP(D21,'Target tables'!A:B,2,0),"") -> Таблица регистров | D21: t_registry | E21: =IFERROR(VLOOKUP(D21&J21,'Target columns'!A:J,4,FALSE),"") -> UUID | F21: =IFERROR(VLOOKUP(D21&J21,'Target columns'!A:J,7,FALSE),"") -> Yes | G21: =IFERROR(VLOOKUP(D21&J21,'Target columns'!A:J,8,FALSE),"") -> No | H21: =IFERROR(VLOOKUP(D21&J21,'Target columns'!A:J,5,FALSE),"") -> NOT NULL | I21: =IFERROR(VLOOKUP(D21&J21,'Target columns'!A:J,10,FALSE),"") -> Идентификатор регистра | J21: registry_id | K21: ETL | L21: uuid | M21: ID регистра счёта | N21: registry_id | S21: select * from ( -- Эскроу 214 select externalRegistryId_escrow_accountDetails_uid as registry_id, externalRegistryId_escrow_accountDetails as host_registry_id, escrowId_agreement_uid as agr_escrow_id, null as agr_id, number_escrow_accountDetails, '00000000-0000-0000-0000-0000fffffc14' as registry_type_id, cast(sys_date_create_or_update as date) as start_dt, cast('9999-12-31' as date) as end_dt, row_number() over (partition by externalregistryid_escrow_accountdetails order by sys_date_create_or_update desc) as rn from s_grnplm_as_t_didsd_308_db_stg.b3080000460001_escrow_legal214_agreement_actual_dto where externalRegistryId_escrow_accountDetails is not null ) a where a.rn = 1 union all select * from ( -- Эскроу ГК select externalregistryid_uid as registry_id, externalregistryid as host_registry_id, escrowid_uid as agr_escrow_id, null as agr_id, null as number_escrow_accountDetails, '00000000-0000-0000-0000-0000fffffc13' as registry_type_id, cast(sys_date_create_or_update as date) as start_dt, cast('9999-12-31' as date) as end_dt, row_number() over (partition by externalregistryid order by sys_date_create_or_update desc) as rn from s_grnplm_as_t_didsd_308_db_stg.b3080000460002_escrow_legalgk_agreement_actual_dto where externalregistryid is not null ) a where a.rn = 1 union all -- Аккредитивы ЮЛ select o.registerid_uid as registry_id , o.registerid as host_registry_id , null::uuid as agr_escrow_id , o.agreementreference_uid as agr_id , o.accountevent_number as coa_num , '00000000-0000-0000-0000-0000fffffc11' as registry_type_id -- accred^Аккредитивы ЮЛ , cast(sys_date_create_or_update as date) as start_dt , cast('9999-12-31' as date) as end_dt from s_grnplm_as_t_didsd_308_db_stg.b3080000460007_payments_2_0_account_dto as o inner join s_grnplm_as_t_didsd_308_db_stg.b3080000460015_lcl_agreement_actual_dto as b on o.agreementreference = b.reference where 1 = 1 and o.registerid_uid is not null and coalesce(upper(o.systemid), '') <> upper('reserve-factory') union all select o.registerid_uid as registry_id , o.registerid as host_registry_id , null::uuid as agr_escrow_id , o.agreementreference_uid as agr_id , o.accountevent_number as coa_num , '00000000-0000-0000-0000-0000fffffc12' as registry_type_id -- reserve^Резервы , cast(sys_date_create_or_update as date) as start_dt , cast('9999-12-31' as date) as end_dt from s_grnplm_as_t_didsd_308_db_stg.b3080000460007_payments_2_0_account_dto as o inner join s_grnplm_as_t_didsd_308_db_stg.b3080000460015_lcl_agreement_actual_dto as b on o.agreementreference = b.reference where 1 = 1 and o.registerid_uid is not null and coalesce(upper(o.systemid), '') = upper('reserve-factory') --инкассо экспортное union all select o.registerid_uid as registry_id , o.registerid as host_registry_id , null::uuid as agr_escrow_id , o.agreementreference_uid as agr_id , o.accountevent_number as coa_num , '00000000-0000-0000-0000-0000fffffc0f' as registry_type_id -- -1009^exportinkasso^Эксп. Инкассо , cast(sys_date_create_or_update as date) as start_dt , cast('9999-12-31' as date) as end_dt from s_grnplm_as_t_didsd_308_db_stg.b3080000460007_payments_2_0_account_dto as o inner join s_grnplm_as_t_didsd_308_db_stg.b3080000460016_inkasso_export_agreement_actual_dto as b on o.agreementreference = b.reference where 1 = 1 and o.registerid_uid is not null and coalesce(upper(o.systemid), '') <> upper('reserve-factory') union all select o.registerid_uid as registry_id , o.registerid as host_registry_id , null::uuid as agr_escrow_id , o.agreementreference_uid as agr_id , o.accountevent_number as coa_num , '00000000-0000-0000-0000-0000fffffc12' as registry_type_id -- reserve^Резервы , cast(sys_date_create_or_update as date) as start_dt , cast('9999-12-31' as date) as end_dt from s_grnplm_as_t_didsd_308_db_stg.b3080000460007_payments_2_0_account_dto as o inner join s_grnplm_as_t_didsd_308_db_stg.b3080000460016_inkasso_export_agreement_actual_dto as b on o.agreementreference = b.reference where 1 = 1 and o.registerid_uid is not null and coalesce(upper(o.systemid), '') = upper('reserve-factory') --инкассо импортное union all select o.registerid_uid as registry_id , o.registerid as host_registry_id , null::uuid as agr_escrow_id , o.agreementreference_uid as agr_id , o.accountevent_number as coa_num , '00000000-0000-0000-0000-0000fffffc10' as registry_type_id -- -1008^importinkasso^Имп. Инкассо , cast(sys_date_create_or_update as date) as start_dt , cast('9999-12-31' as date) as end_dt from s_grnplm_as_t_didsd_308_db_stg.b3080000460007_payments_2_0_account_dto as o inner join s_grnplm_as_t_didsd_308_db_stg.b3080000460017_inkasso_import_agreement_actual_dto as b on o.agreementreference = b.reference where 1 = 1 and o.registerid_uid is not null and coalesce(upper(o.systemid), '') <> upper('reserve-factory') union all select o.registerid_uid as registry_id , o.registerid as host_registry_id , null::uuid as agr_escrow_id , o.agreementreference_uid as agr_id , o.accountevent_number as coa_num , '00000000-0000-0000-0000-0000fffffc12' as registry_type_id -- reserve^Резервы , cast(sys_date_create_or_update as date) as start_dt , cast('9999-12-31' as date) as as end_dt from s_grnplm_as_t_didsd_308_db_stg.b3080000460007_payments_2_0_account_dto as o inner join s_grnplm_as_t_didsd_308_db_stg.b3080000460017_inkasso_import_agreement_actual_dto as b on o.agreementreference = b.reference where 1 = 1 and o.registerid_uid is not null and coalesce(upper(o.systemid), '') = upper('reserve-factory') --рамбурсы union all select o.registerid_uid as registry_id , o.registerid as host_registry_id , null::uuid as agr_escrow_id , o.agreementreference_uid as agr_id , o.accountevent_number as coa_num , '00000000-0000-0000-0000-0000fffffc0e' as registry_type_id -- -1010^reimburs^Рамбурс , cast(sys_date_create_or_update as date) as start_dt , cast('9999-12-31' as date) as as end_dt from s_grnplm_as_t_didsd_308_db_stg.b3080000460007_payments_2_0_account_dto as o inner join s_grnplm_as_t_didsd_308_db_stg.b3080000460018_reimbursement_agreement_actual_dto as b on o.agreementreference = b.reference where 1 = 1 and o.registerid_uid is not null and coalesce(upper(o.systemid), '') <> upper('reserve-factory') union all select o.registerid_uid as registry_id , o.registerid as host_registry_id , null::uuid as agr_escrow_id , o.agreementreference_uid as agr_id , o.accountevent_number as coa_num , '00000000-0000-0000-0000-0000fffffc12' as registry_type_id -- reserve^Резервы , cast(sys_date_create_or_update as date) as start_dt , cast('9999-12-31' as date) as as end_dt from s_grnplm_as_t_didsd_308_db_stg.b3080000460007_payments_2_0_account_dto as o inner join s_grnplm_as_t_didsd_308_db_stg.b3080000460018_reimbursement_agreement_actual_dto as b on o.agreementreference = b.reference where 1 = 1 and o.registerid_uid is not null and coalesce(upper(o.systemid), '') = upper('reserve-factory') -- ГС union all select o.registerid_uid as registry_id , o.registerid as host_registry_id , null::uuid as agr_escrow_id , b.id_uid as agr_id , o.accountevent_number as coa_num , '00000000-0000-0000-0000-0000fffffc17' as registry_type_id -- '-1001^Генеральное соглашение ^ gs , cast(o.sys_date_create_or_update as date) as start_dt , cast('9999-12-31' as date) as end_dt from s_grnplm_as_t_didsd_308_db_stg.b3080000460007_payments_2_0_account_dto as o inner join s_grnplm_as_t_didsd_308_db_stg.b3080000460009_general_agreement_actual_dto as b on o.external_agreement_id = b.external_id where 1 = 1 and o.registerid_uid is not null and coalesce(upper(o.systemid), '') <> upper('reserve-factory') -- ГОДС union all select *, ROW_NUMBER() OVER (PARTITION BY a.registry_id ORDER BY a.start_dt DESC, st ) as rn from ( select 2 as st, recipientaccount_externalregistryid_uid as registry_id , recipientaccount_externalregistryid as host_registry_id , null::uuid as agr_escrow_id , externalid_uid as agr_id , null as coa_num , '00000000-0000-0000-0000-0000fffffc0c' as registry_type_id -- '-1001^ГОДС ^ gods , cast(sys_date_create_or_update as date) as start_dt , cast('9999-12-31' as date) as end_dt from s_grnplm_as_t_didsd_308_db_stg.b3080000460022_escrow_legalgk_gods_actual_dto where recipientaccount_externalregistryid is not null union all select 1 as st, o.registerid_uid as registry_id , o.registerid as host_registry_id , null::uuid as agr_escrow_id , b.externalid_uid as agr_id , o.accountevent_number as coa_num , '00000000-0000-0000-0000-0000fffffc0c' as registry_type_id -- '-1001^ГОДС ^ gods , cast(o.sys_date_create_or_update as date) as start_dt , cast('9999-12-31' as date) as end_dt from s_grnplm_as_t_didsd_308_db_stg.b3080000460007_payments_2_0_account_dto as o inner join s_grnplm_as_t_didsd_308_db_stg.b3080000460022_escrow_legalgk_gods_actual_dto as b on o.external_agreement_id = b.externalid where 1 = 1 and o.registerid_uid is not null and coalesce(upper(o.systemid), '') <> upper('reserve-factory') ) a where a.rn = 1 | V21: ="n308000046_"&IFERROR(VLOOKUP(D21,target_tables[],5,0),"<not found>") -> n308000046_registry | W21: Ключ | AF21: Снимок-снимок
A22: 190 | B22: Эскроу, ГС, Аккредитив, УПФ | C22: =IFERROR(VLOOKUP(D22,'Target tables'!A:B,2,0),"") -> Таблица регистров | D22: t_registry | E22: =IFERROR(VLOOKUP(D22&J22,'Target columns'!A:J,4,FALSE),"") -> TEXT | F22: =IFERROR(VLOOKUP(D22&J22,'Target columns'!A:J,7,FALSE),"") -> No | G22: =IFERROR(VLOOKUP(D22&J22,'Target columns'!A:J,8,FALSE),"") -> No | H22: =IFERROR(VLOOKUP(D22&J22,'Target columns'!A:J,5,FALSE),"") -> NULL | I22: =IFERROR(VLOOKUP(D22&J22,'Target columns'!A:J,10,FALSE),"") -> Идентификатор регистра в системе-источнике | J22: host_registry_id | K22: ETL | L22: text | M22: ID регистра счёта | N22: host_registry_id | V22: ="n308000046_"&IFERROR(VLOOKUP(D22,target_tables[],5,0),"<not found>") -> n308000046_registry | W22: -
A23: 195 | B23: Эскроу, ГС, Аккредитив, УПФ | C23: =IFERROR(VLOOKUP(D23,'Target tables'!A:B,2,0),"") -> Таблица регистров | D23: t_registry | E23: =IFERROR(VLOOKUP(D23&J23,'Target columns'!A:J,4,FALSE),"") -> UUID | F23: =IFERROR(VLOOKUP(D23&J23,'Target columns'!A:J,7,FALSE),"") -> No | G23: =IFERROR(VLOOKUP(D23&J23,'Target columns'!A:J,8,FALSE),"") -> Yes | H23: =IFERROR(VLOOKUP(D23&J23,'Target columns'!A:J,5,FALSE),"") -> NOT NULL | I23: =IFERROR(VLOOKUP(D23&J23,'Target columns'!A:J,10,FALSE),"") -> Тип регистра счета | J23: registry_type_id | K23: ETL | L23: uuid | M23: Тип регистра счета | N23: registry_type_id | V23: ="n308000046_"&IFERROR(VLOOKUP(D23,target_tables[],5,0),"<not found>") -> n308000046_registry | W23: -
A24: 200 | B24: Эскроу, ГС, Аккредитив, УПФ | C24: =IFERROR(VLOOKUP(D24,'Target tables'!A:B,2,0),"") -> Таблица регистров | D24: t_registry | E24: =IFERROR(VLOOKUP(D24&J24,'Target columns'!A:J,4,FALSE),"") -> UUID | F24: =IFERROR(VLOOKUP(D24&J24,'Target columns'!A:J,7,FALSE),"") -> No | G24: =IFERROR(VLOOKUP(D24&J24,'Target columns'!A:J,8,FALSE),"") -> Yes | H24: =IFERROR(VLOOKUP(D24&J24,'Target columns'!A:J,5,FALSE),"") -> NULL | I24: =IFERROR(VLOOKUP(D24&J24,'Target columns'!A:J,10,FALSE),"") -> Идентификатор договора эскроу | J24: agr_escrow_id | K24: ETL | L24: uuid | M24: Идентификатор договора эскроу | N24: agr_escrow_id | V24: ="n308000046_"&IFERROR(VLOOKUP(D24,target_tables[],5,0),"<not found>") -> n308000046_registry | W24: -
A25: 205 | B25: Эскроу, ГС, Аккредитив, УПФ | C25: =IFERROR(VLOOKUP(D25,'Target tables'!A:B,2,0),"") -> Таблица регистров | D25: t_registry | E25: =IFERROR(VLOOKUP(D25&J25,'Target columns'!A:J,4,FALSE),"") -> UUID | F25: =IFERROR(VLOOKUP(D25&J25,'Target columns'!A:J,7,FALSE),"") -> No | G25: =IFERROR(VLOOKUP(D25&J25,'Target columns'!A:J,8,FALSE),"") -> Yes | H25: =IFERROR(VLOOKUP(D25&J25,'Target columns'!A:J,5,FALSE),"") -> NULL | I25: =IFERROR(VLOOKUP(D25&J25,'Target columns'!A:J,10,FALSE),"") -> Идентификатор договора | J25: agr_id | K25: ETL | L25: uuid | M25: Идентификатор договора | N25: agr_id | V25: ="n308000046_"&IFERROR(VLOOKUP(D25,target_tables[],5,0),"<not found>") -> n308000046_registry | W25: - | AJ25: связь со счетом регистра по референсу
A26: 210 | B26: Эскроу, ГС, Аккредитив, УПФ | C26: =IFERROR(VLOOKUP(D26,'Target tables'!A:B,2,0),"") -> Таблица регистров | D26: t_registry | E26: =IFERROR(VLOOKUP(D26&J26,'Target columns'!A:J,4,FALSE),"") -> TEXT | F26: =IFERROR(VLOOKUP(D26&J26,'Target columns'!A:J,7,FALSE),"") -> No | G26: =IFERROR(VLOOKUP(D26&J26,'Target columns'!A:J,8,FALSE),"") -> No | H26: =IFERROR(VLOOKUP(D26&J26,'Target columns'!A:J,5,FALSE),"") -> NULL | I26: =IFERROR(VLOOKUP(D26&J26,'Target columns'!A:J,10,FALSE),"") -> Номер счета | J26: coa_num | K26: ETL | L26: text | M26: Номер счёта | N26: coa_num | V26: ="n308000046_"&IFERROR(VLOOKUP(D26,target_tables[],5,0),"<not found>") -> n308000046_registry | W26: -
A27: 220 | B27: Эскроу, ГС, Аккредитив, УПФ | C27: =IFERROR(VLOOKUP(D27,'Target tables'!A:B,2,0),"") -> Таблица регистров | D27: t_registry | E27: =IFERROR(VLOOKUP(D27&J27,'Target columns'!A:J,4,FALSE),"") -> DATE | F27: =IFERROR(VLOOKUP(D27&J27,'Target columns'!A:J,7,FALSE),"") -> No | G27: =IFERROR(VLOOKUP(D27&J27,'Target columns'!A:J,8,FALSE),"") -> No | H27: =IFERROR(VLOOKUP(D27&J27,'Target columns'!A:J,5,FALSE),"") -> NULL | I27: =IFERROR(VLOOKUP(D27&J27,'Target columns'!A:J,10,FALSE),"") -> Дата начала действия регистра | J27: start_dt | K27: ETL | N27: start_dt | V27: ="n308000046_"&IFERROR(VLOOKUP(D27,target_tables[],5,0),"<not found>") -> n308000046_registry | W27: Начало
A28: 230 | B28: Эскроу, ГС, Аккредитив, УПФ | C28: =IFERROR(VLOOKUP(D28,'Target tables'!A:B,2,0),"") -> Таблица регистров | D28: t_registry | E28: =IFERROR(VLOOKUP(D28&J28,'Target columns'!A:J,4,FALSE),"") -> DATE | F28: =IFERROR(VLOOKUP(D28&J28,'Target columns'!A:J,7,FALSE),"") -> No | G28: =IFERROR(VLOOKUP(D28&J28,'Target columns'!A:J,8,FALSE),"") -> No | H28: =IFERROR(VLOOKUP(D28&J28,'Target columns'!A:J,5,FALSE),"") -> NULL | I28: =IFERROR(VLOOKUP(D28&J28,'Target columns'!A:J,10,FALSE),"") -> Дата окончания действия регистра | J28: end_dt | K28: ETL | N28: end_dt | V28: ="n308000046_"&IFERROR(VLOOKUP(D28,target_tables[],5,0),"<not found>") -> n308000046_registry | W28: Конец
A29: 240 | B29: Эскроу | C29: =IFERROR(VLOOKUP(D29,'Target tables'!A:B,2,0),"") -> Справочник схем субсидирования | D29: t_escrow_scheme | E29: =IFERROR(VLOOKUP(D29&J29,'Target columns'!A:J,4,FALSE),"") -> UUID | F29: =IFERROR(VLOOKUP(D29&J29,'Target columns'!A:J,7,FALSE),"") -> Yes | G29: =IFERROR(VLOOKUP(D29&J29,'Target columns'!A:J,8,FALSE),"") -> No | H29: =IFERROR(VLOOKUP(D29&J29,'Target columns'!A:J,5,FALSE),"") -> NOT NULL | I29: =IFERROR(VLOOKUP(D29&J29,'Target columns'!A:J,10,FALSE),"") -> Идентификатор схемы субсидирования ставки | J29: escrow_scheme_id | K29: ETL | L29: uuid | M29: Схема субсидирования | N29: rateSubsidyScheme_agreement_uid | S29: select * from ( -- Эскроу 214 Схема субсидирования ставки select rateSubsidyScheme_agreement_uid, rateSubsidyScheme_agreement, case when rateSubsidyScheme_agreement = '1' then 'Схема 1' when rateSubsidyScheme_agreement = '2' then 'Схема 2' when rateSubsidyScheme_agreement = '0' then 'Схема 0' else 'Схема 00' end as rateSubsidyScheme_agreement_name, row_number() OVER (PARTITION BY rateSubsidyScheme_agreement ORDER BY sys_date_create_or_update DESC) AS rn from s_grnplm_as_t_didsd_308_db_stg.b3080000460001_escrow_legal214_agreement_actual_dto where rateSubsidyScheme_agreement is not null ) a where a.rn = 1 union ALL select * from ( select -- Эскроу ГКсхема распределения дохода profitscheme_uid as rateSubsidyScheme_agreement_uid, profitscheme as rateSubsidyScheme_agreement, case when profitscheme = 'DEPONENT' then 'Схема 0 – 100% депонент' when profitscheme = 'BENEFICIARY' then 'Схема 2 – 100% бенефициар' when profitscheme = 'EQUALLY' then 'Схема 1 – 50%/50% депонент/бенефициар' end as rateSubsidyScheme_agreement_name, row_number() OVER (PARTITION BY profitscheme ORDER BY sys_date_create_or_update DESC) AS rn from s_grnplm_as_t_didsd_308_db_stg.b3080000460002_escrow_legalgk_agreement_actual_dto where profitscheme is not null ) a where a.rn = 1 | V29: ="n308000046_"&IFERROR(VLOOKUP(D29,target_tables[],5,0),"<not found>") -> n308000046_escrow_scheme | W29: Ключ | AF29: Снимок-снимок
A30: 250 | B30: Эскроу | C30: =IFERROR(VLOOKUP(D30,'Target tables'!A:B,2,0),"") -> Справочник схем субсидирования | D30: t_escrow_scheme | E30: =IFERROR(VLOOKUP(D30&J30,'Target columns'!A:J,4,FALSE),"") -> TEXT | F30: =IFERROR(VLOOKUP(D30&J30,'Target columns'!A:J,7,FALSE),"") -> No | G30: =IFERROR(VLOOKUP(D30&J30,'Target columns'!A:J,8,FALSE),"") -> No | H30: =IFERROR(VLOOKUP(D30&J30,'Target columns'!A:J,5,FALSE),"") -> NULL | I30: =IFERROR(VLOOKUP(D30&J30,'Target columns'!A:J,10,FALSE),"") -> Код схемы субсидирования | J30: escrow_scheme_cd | K30: ETL | L30: text | M30: Схема субсидирования | N30: rateSubsidyScheme_agreement | V30: ="n308000046_"&IFERROR(VLOOKUP(D30,target_tables[],5,0),"<not found>") -> n308000046_escrow_scheme | W30: -
A31: 260 | B31: Эскроу | C31: =IFERROR(VLOOKUP(D31,'Target tables'!A:B,2,0),"") -> Справочник схем субсидирования | D31: t_escrow_scheme | E31: =IFERROR(VLOOKUP(D31&J31,'Target columns'!A:J,4,FALSE),"") -> TEXT | F31: =IFERROR(VLOOKUP(D31&J31,'Target columns'!A:J,7,FALSE),"") -> No | G31: =IFERROR(VLOOKUP(D31&J31,'Target columns'!A:J,8,FALSE),"") -> No | H31: =IFERROR(VLOOKUP(D31&J31,'Target columns'!A:J,5,FALSE),"") -> NULL | I31: =IFERROR(VLOOKUP(D31&J31,'Target columns'!A:J,10,FALSE),"") -> Наименование схемы субсидирования | J31: escrow_scheme_name | K31: ETL | L31: text | M31: Название схемы субсидирования | N31: rateSubsidyScheme_agreement_name | V31: ="n308000046_"&IFERROR(VLOOKUP(D31,target_tables[],5,0),"<not found>") -> n308000046_escrow_scheme | W31: -
A32: 270 | B32: Эскроу | C32: =IFERROR(VLOOKUP(D32,'Target tables'!A:B,2,0),"") -> Таблица связей кредитного договора с договором эскроу | D32: t_agr_escrow_agr_cred | E32: =IFERROR(VLOOKUP(D32&J32,'Target columns'!A:J,4,FALSE),"") -> UUID | F32: =IFERROR(VLOOKUP(D32&J32,'Target columns'!A:J,7,FALSE),"") -> Yes | G32: =IFERROR(VLOOKUP(D32&J32,'Target columns'!A:J,8,FALSE),"") -> Yes | H32: =IFERROR(VLOOKUP(D32&J32,'Target columns'!A:J,5,FALSE),"") -> NOT NULL | I32: =IFERROR(VLOOKUP(D32&J32,'Target columns'!A:J,10,FALSE),"") -> ИД договора эскроу | J32: agr_escrow_id | K32: b3080000460001_escrow_legal214_agreement_actual_dto | L32: =IFERROR(VLOOKUP(UPPER(K32&N32),source_columns[],4,0),"") | M32: =IFERROR(VLOOKUP(UPPER(K32&N32),source_columns[],7,0),"") | N32: escrowId_agreement_uid | S32: developerLoanAgrNumber_cred_agreement is not null or devLoanAgrKulId_agreement is not null | V32: ="n308000046_"&IFERROR(VLOOKUP(D32,target_tables[],5,0),"<not found>") -> n308000046_agr_escrow_agr_cred | W32: Ключ | AF32: Снимок-история
A33: 280 | B33: Эскроу | C33: =IFERROR(VLOOKUP(D33,'Target tables'!A:B,2,0),"") -> Таблица связей кредитного договора с договором эскроу | D33: t_agr_escrow_agr_cred | E33: =IFERROR(VLOOKUP(D33&J33,'Target columns'!A:J,4,FALSE),"") -> UUID | F33: =IFERROR(VLOOKUP(D33&J33,'Target columns'!A:J,7,FALSE),"") -> No | G33: =IFERROR(VLOOKUP(D33&J33,'Target columns'!A:J,8,FALSE),"") -> Yes | H33: =IFERROR(VLOOKUP(D33&J33,'Target columns'!A:J,5,FALSE),"") -> NULL | I33: =IFERROR(VLOOKUP(D33&J33,'Target columns'!A:J,10,FALSE),"") -> ИД кредитного договора с застройщиком | J33: agr_cred_id | K33: b3080000460001_escrow_legal214_agreement_actual_dto | L33: =IFERROR(VLOOKUP(UPPER(K33&N33),source_columns[],4,0),"") | M33: =IFERROR(VLOOKUP(UPPER(K33&N33),source_columns[],7,0),"") | N33: COALESCE (devLoanAgrKulId_agreement_uid, developerLoanAgrNumber_cred_agreement_uid) | V33: ="n308000046_"&IFERROR(VLOOKUP(D33,target_tables[],5,0),"<not found>") -> n308000046_agr_escrow_agr_cred | W33: -
A34: 290 | B34: Эскроу | C34: =IFERROR(VLOOKUP(D34,'Target tables'!A:B,2,0),"") -> Таблица связей кредитного договора с договором эскроу | D34: t_agr_escrow_agr_cred | E34: =IFERROR(VLOOKUP(D34&J34,'Target columns'!A:J,4,FALSE),"") -> DATE | F34: =IFERROR(VLOOKUP(D34&J34,'Target columns'!A:J,7,FALSE),"") -> Yes | G34: =IFERROR(VLOOKUP(D34&J34,'Target columns'!A:J,8,FALSE),"") -> No | H34: =IFERROR(VLOOKUP(D34&J34,'Target columns'!A:J,5,FALSE),"") -> NOT NULL | I34: =IFERROR(VLOOKUP(D34&J34,'Target columns'!A:J,10,FALSE),"") -> Дата начала действия связи между кредитным договором и договором эскроу | J34: start_dt | K34: b3080000460001_escrow_legal214_agreement_actual_dto | L34: =IFERROR(VLOOKUP(UPPER(K34&N34),source_columns[],4,0),"") | M34: =IFERROR(VLOOKUP(UPPER(K34&N34),source_columns[],7,0),"") | N34: cast(sys_date_create_or_update as date) | V34: ="n308000046_"&IFERROR(VLOOKUP(D34,target_tables[],5,0),"<not found>") -> n308000046_agr_escrow_agr_cred | W34: Начало
A35: 300 | B35: Эскроу | C35: =IFERROR(VLOOKUP(D35,'Target tables'!A:B,2,0),"") -> Таблица связей кредитного договора с договором эскроу | D35: t_agr_escrow_agr_cred | E35: =IFERROR(VLOOKUP(D35&J35,'Target columns'!A:J,4,FALSE),"") -> DATE | F35: =IFERROR(VLOOKUP(D35&J35,'Target columns'!A:J,7,FALSE),"") -> No | G35: =IFERROR(VLOOKUP(D35&J35,'Target columns'!A:J,8,FALSE),"") -> No | H35: =IFERROR(VLOOKUP(D35&J35,'Target columns'!A:J,5,FALSE),"") -> NULL | I35: =IFERROR(VLOOKUP(D35&J35,'Target columns'!A:J,10,FALSE),"") -> Дата окончания действия связи между кредитным договором и договором эскроу | J35: end_dt | K35: b3080000460001_escrow_legal214_agreement_actual_dto | L35: =IFERROR(VLOOKUP(UPPER(K35&N35),source_columns[],4,0),"") | M35: =IFERROR(VLOOKUP(UPPER(K35&N35),source_columns[],7,0),"") | N35: cast('9999-12-31' as date) | V35: ="n308000046_"&IFERROR(VLOOKUP(D35,target_tables[],5,0),"<not found>") -> n308000046_agr_escrow_agr_cred | W35: Конец
A36: 310 | B36: Эскроу | C36: =IFERROR(VLOOKUP(D36,'Target tables'!A:B,2,0),"") -> Таблица связей контрагентов с договором эскроу | D36: t_agr_escrow_cust | E36: =IFERROR(VLOOKUP(D36&J36,'Target columns'!A:J,4,FALSE),"") -> UUID | F36: =IFERROR(VLOOKUP(D36&J36,'Target columns'!A:J,7,FALSE),"") -> Yes | G36: =IFERROR(VLOOKUP(D36&J36,'Target columns'!A:J,8,FALSE),"") -> Yes | H36: =IFERROR(VLOOKUP(D36&J36,'Target columns'!A:J,5,FALSE),"") -> NOT NULL | I36: =IFERROR(VLOOKUP(D36&J36,'Target columns'!A:J,10,FALSE),"") -> Идентификатор договора эскроу | J36: agr_escrow_id | K36: b3080000460001_escrow_legal214_agreement_actual_dto | L36: =IFERROR(VLOOKUP(UPPER(K36&N36),source_columns[],4,0),"") -> uuid | M36: =IFERROR(VLOOKUP(UPPER(K36&N36),source_columns[],7,0),"") -> Идентификатор договора эскроу | N36: escrowId_agreement_uid | S36: legalEpkId_deponent is not null | V36: ="n308000046_"&IFERROR(VLOOKUP(D36,target_tables[],5,0),"<not found>") -> n308000046_agr_escrow_cust | W36: Ключ | AF36: Снимок-история
A37: 320 | B37: Эскроу | C37: =IFERROR(VLOOKUP(D37,'Target tables'!A:B,2,0),"") -> Таблица связей контрагентов с договором эскроу | D37: t_agr_escrow_cust | E37: =IFERROR(VLOOKUP(D37&J37,'Target columns'!A:J,4,FALSE),"") -> UUID | F37: =IFERROR(VLOOKUP(D37&J37,'Target columns'!A:J,7,FALSE),"") -> Yes | G37: =IFERROR(VLOOKUP(D37&J37,'Target columns'!A:J,8,FALSE),"") -> Yes | H37: =IFERROR(VLOOKUP(D37&J37,'Target columns'!A:J,5,FALSE),"") -> NOT NULL | I37: =IFERROR(VLOOKUP(D37&J37,'Target columns'!A:J,10,FALSE),"") -> Идентификатор контрагента | J37: cust_id | K37: b3080000460001_escrow_legal214_agreement_actual_dto | L37: =IFERROR(VLOOKUP(UPPER(K37&N37),source_columns[],4,0),"") -> uuid | M37: =IFERROR(VLOOKUP(UPPER(K37&N37),source_columns[],7,0),"") -> ЕПК id юр.лица депонента | N37: legalEpkId_deponent_uid | V37: ="n308000046_"&IFERROR(VLOOKUP(D37,target_tables[],5,0),"<not found>") -> n308000046_agr_escrow_cust | W37: -
A38: 330 | B38: Эскроу | C38: =IFERROR(VLOOKUP(D38,'Target tables'!A:B,2,0),"") -> Таблица связей контрагентов с договором эскроу | D38: t_agr_escrow_cust | E38: =IFERROR(VLOOKUP(D38&J38,'Target columns'!A:J,4,FALSE),"") -> DATE | F38: =IFERROR(VLOOKUP(D38&J38,'Target columns'!A:J,7,FALSE),"") -> Yes | G38: =IFERROR(VLOOKUP(D38&J38,'Target columns'!A:J,8,FALSE),"") -> No | H38: =IFERROR(VLOOKUP(D38&J38,'Target columns'!A:J,5,FALSE),"") -> NOT NULL | I38: =IFERROR(VLOOKUP(D38&J38,'Target columns'!A:J,10,FALSE),"") -> Дата начала действия | J38: start_dt | K38: b3080000460001_escrow_legal214_agreement_actual_dto | L38: =IFERROR(VLOOKUP(UPPER(K38&N38),source_columns[],4,0),"") | M38: =IFERROR(VLOOKUP(UPPER(K38&N38),source_columns[],7,0),"") | N38: cast(sys_date_create_or_update as date) | V38: ="n308000046_"&IFERROR(VLOOKUP(D38,target_tables[],5,0),"<not found>") -> n308000046_agr_escrow_cust | W38: Начало | AJ38: select agr_escrow_cust_type_id from s_grnplm_as_t_didsd_308_db_dwh.t_agr_escrow_cust_type where agr_escrow_cust_type_cd = 'deponent'
A39: 340 | B39: Эскроу | C39: =IFERROR(VLOOKUP(D39,'Target tables'!A:B,2,0),"") -> Таблица связей контрагентов с договором эскроу | D39: t_agr_escrow_cust | E39: =IFERROR(VLOOKUP(D39&J39,'Target columns'!A:J,4,FALSE),"") -> DATE | F39: =IFERROR(VLOOKUP(D39&J39,'Target columns'!A:J,7,FALSE),"") -> No | G39: =IFERROR(VLOOKUP(D39&J39,'Target columns'!A:J,8,FALSE),"") -> No | H39: =IFERROR(VLOOKUP(D39&J39,'Target columns'!A:J,5,FALSE),"") -> NULL | I39: =IFERROR(VLOOKUP(D39&J39,'Target columns'!A:J,10,FALSE),"") -> Дата окончания действия | J39: end_dt | K39: b3080000460001_escrow_legal214_agreement_actual_dto | L39: =IFERROR(VLOOKUP(UPPER(K39&N39),source_columns[],4,0),"") | M39: =IFERROR(VLOOKUP(UPPER(K39&N39),source_columns[],7,0),"") | N39: cast('9999-12-31' as date) | V39: ="n308000046_"&IFERROR(VLOOKUP(D39,target_tables[],5,0),"<not found>") -> n308000046_agr_escrow_cust | W39: Конец
A40: 350 | B40: Эскроу | C40: =IFERROR(VLOOKUP(D40,'Target tables'!A:B,2,0),"") -> Таблица связей контрагентов с договором эскроу | D40: t_agr_escrow_cust | E40: =IFERROR(VLOOKUP(D40&J40,'Target columns'!A:J,4,FALSE),"") -> UUID | F40: =IFERROR(VLOOKUP(D40&J40,'Target columns'!A:J,7,FALSE),"") -> Yes | G40: =IFERROR(VLOOKUP(D40&J40,'Target columns'!A:J,8,FALSE),"") -> Yes | H40: =IFERROR(VLOOKUP(D40&J40,'Target columns'!A:J,5,FALSE),"") -> NOT NULL | I40: =IFERROR(VLOOKUP(D40&J40,'Target columns'!A:J,10,FALSE),"") -> Роль клиента в договоре - ID | J40: agr_escrow_cust_type_id | K40: b3080000460001_escrow_legal214_agreement_actual_dto | L40: =IFERROR(VLOOKUP(UPPER(K40&N40),source_columns[],4,0),"") | M40: =IFERROR(VLOOKUP(UPPER(K40&N40),source_columns[],7,0),"") | N40: 00000000-0000-0000-0000-0000fffffc16 -- Депонент | V40: ="n308000046_"&IFERROR(VLOOKUP(D40,target_tables[],5,0),"<not found>") -> n308000046_agr_escrow_cust | W40: Ключ
A41: 360 | B41: Эскроу | C41: =IFERROR(VLOOKUP(D41,'Target tables'!A:B,2,0),"") -> Таблица связей контрагентов с договором эскроу | D41: t_agr_escrow_cust | E41: =IFERROR(VLOOKUP(D41&J41,'Target columns'!A:J,4,FALSE),"") -> UUID | F41: =IFERROR(VLOOKUP(D41&J41,'Target columns'!A:J,7,FALSE),"") -> Yes | G41: =IFERROR(VLOOKUP(D41&J41,'Target columns'!A:J,8,FALSE),"") -> Yes | H41: =IFERROR(VLOOKUP(D41&J41,'Target columns'!A:J,5,FALSE),"") -> NOT NULL | I41: =IFERROR(VLOOKUP(D41&J41,'Target columns'!A:J,10,FALSE),"") -> Идентификатор договора эскроу | J41: agr_escrow_id | K41: b3080000460001_escrow_legal214_agreement_actual_dto | L41: =IFERROR(VLOOKUP(UPPER(K41&N41),source_columns[],4,0),"") -> uuid | M41: =IFERROR(VLOOKUP(UPPER(K41&N41),source_columns[],7,0),"") -> Идентификатор договора эскроу | N41: escrowId_agreement_uid | S41: legalEpkId_beneficiary is not null | V41: ="n308000046_"&IFERROR(VLOOKUP(D41,target_tables[],5,0),"<not found>") -> n308000046_agr_escrow_cust | W41: Ключ | AF41: Снимок-история
A42: 370 | B42: Эскроу | C42: =IFERROR(VLOOKUP(D42,'Target tables'!A:B,2,0),"") -> Таблица связей контрагентов с договором эскроу | D42: t_agr_escrow_cust | E42: =IFERROR(VLOOKUP(D42&J42,'Target columns'!A:J,4,FALSE),"") -> UUID | F42: =IFERROR(VLOOKUP(D42&J42,'Target columns'!A:J,7,FALSE),"") -> Yes | G42: =IFERROR(VLOOKUP(D42&J42,'Target columns'!A:J,8,FALSE),"") -> Yes | H42: =IFERROR(VLOOKUP(D42&J42,'Target columns'!A:J,5,FALSE),"") -> NOT NULL | I42: =IFERROR(VLOOKUP(D42&J42,'Target columns'!A:J,10,FALSE),"") -> Идентификатор контрагента | J42: cust_id | K42: b3080000460001_escrow_legal214_agreement_actual_dto | L42: =IFERROR(VLOOKUP(UPPER(K42&N42),source_columns[],4,0),"") -> uuid | M42: =IFERROR(VLOOKUP(UPPER(K42&N42),source_columns[],7,0),"") -> ЕПК id юр.лица бенефициара | N42: legalEpkId_beneficiary_uid | V42: ="n308000046_"&IFERROR(VLOOKUP(D42,target_tables[],5,0),"<not found>") -> n308000046_agr_escrow_cust | W42: -
A43: 380 | B43: Эскроу | C43: =IFERROR(VLOOKUP(D43,'Target tables'!A:B,2,0),"") -> Таблица связей контрагентов с договором эскроу | D43: t_agr_escrow_cust | E43: =IFERROR(VLOOKUP(D43&J43,'Target columns'!A:J,4,FALSE),"") -> DATE | F43: =IFERROR(VLOOKUP(D43&J43,'Target columns'!A:J,7,FALSE),"") -> Yes | G43: =IFERROR(VLOOKUP(D43&J43,'Target columns'!A:J,8,FALSE),"") -> No | H43: =IFERROR(VLOOKUP(D43&J43,'Target columns'!A:J,5,FALSE),"") -> NOT NULL | I43: =IFERROR(VLOOKUP(D43&J43,'Target columns'!A:J,10,FALSE),"") -> Дата начала действия | J43: start_dt | K43: b3080000460001_escrow_legal214_agreement_actual_dto | L43: =IFERROR(VLOOKUP(UPPER(K43&N43),source_columns[],4,0),"") | M43: =IFERROR(VLOOKUP(UPPER(K43&N43),source_columns[],7,0),"") | N43: cast(sys_date_create_or_update as date) | V43: ="n308000046_"&IFERROR(VLOOKUP(D43,target_tables[],5,0),"<not found>") -> n308000046_agr_escrow_cust | W43: Начало
A44: 390 | B44: Эскроу | C44: =IFERROR(VLOOKUP(D44,'Target tables'!A:B,2,0),"") -> Таблица связей контрагентов с договором эскроу | D44: t_agr_escrow_cust | E44: =IFERROR(VLOOKUP(D44&J44,'Target columns'!A:J,4,FALSE),"") -> DATE | F44: =IFERROR(VLOOKUP(D44&J44,'Target columns'!A:J,7,FALSE),"") -> No | G44: =IFERROR(VLOOKUP(D44&J44,'Target columns'!A:J,8,FALSE),"") -> No | H44: =IFERROR(VLOOKUP(D44&J44,'Target columns'!A:J,5,FALSE),"") -> NULL | I44: =IFERROR(VLOOKUP(D44&J44,'Target columns'!A:J,10,FALSE),"") -> Дата окончания действия | J44: end_dt | K44: b3080000460001_escrow_legal214_agreement_actual_dto | L44: =IFERROR(VLOOKUP(UPPER(K44&N44),source_columns[],4,0),"") | M44: =IFERROR(VLOOKUP(UPPER(K44&N44),source_columns[],7,0),"") | N44: cast('9999-12-31' as date) | V44: ="n308000046_"&IFERROR(VLOOKUP(D44,target_tables[],5,0),"<not found>") -> n308000046_agr_escrow_cust | W44: Конец | AJ44: select agr_escrow_cust_type_id from s_grnplm_as_t_didsd_308_db_dwh.t_agr_escrow_cust_type where agr_escrow_cust_type_cd = 'beneficiary'
A45: 400 | B45: Эскроу | C45: =IFERROR(VLOOKUP(D45,'Target tables'!A:B,2,0),"") -> Таблица связей контрагентов с договором эскроу | D45: t_agr_escrow_cust | E45: =IFERROR(VLOOKUP(D45&J45,'Target columns'!A:J,4,FALSE),"") -> UUID | F45: =IFERROR(VLOOKUP(D45&J45,'Target columns'!A:J,7,FALSE),"") -> Yes | G45: =IFERROR(VLOOKUP(D45&J45,'Target columns'!A:J,8,FALSE),"") -> Yes | H45: =IFERROR(VLOOKUP(D45&J45,'Target columns'!A:J,5,FALSE),"") -> NOT NULL | I45: =IFERROR(VLOOKUP(D45&J45,'Target columns'!A:J,10,FALSE),"") -> Роль клиента в договоре - ID | J45: agr_escrow_cust_type_id | K45: b3080000460001_escrow_legal214_agreement_actual_dto | L45: =IFERROR(VLOOKUP(UPPER(K45&N45),source_columns[],4,0),"") | M45: =IFERROR(VLOOKUP(UPPER(K45&N45),source_columns[],7,0),"") | N45: 00000000-0000-0000-0000-0000fffffc17 -- Бенефициар | V45: ="n308000046_"&IFERROR(VLOOKUP(D45,target_tables[],5,0),"<not found>") -> n308000046_agr_escrow_cust | W45: Ключ
A46: 410 | B46: Эскроу, ГС, Аккредитив, УПФ | C46: =IFERROR(VLOOKUP(D46,'Target tables'!A:B,2,0),"") -> Контрагенты | D46: t_cust | E46: =IFERROR(VLOOKUP(D46&J46,'Target columns'!A:J,4,FALSE),"") -> UUID | F46: =IFERROR(VLOOKUP(D46&J46,'Target columns'!A:J,7,FALSE),"") -> Yes | G46: =IFERROR(VLOOKUP(D46&J46,'Target columns'!A:J,8,FALSE),"") -> No | H46: =IFERROR(VLOOKUP(D46&J46,'Target columns'!A:J,5,FALSE),"") -> NOT NULL | I46: =IFERROR(VLOOKUP(D46&J46,'Target columns'!A:J,10,FALSE),"") -> Идентификатор контрагента | J46: cust_id | K46: ETL | L46: =IFERROR(VLOOKUP(UPPER(K46&N46),source_columns[],4,0),"") | M46: id клиента | N46: cust_uid | S46: select v.cust_id , v.cust_epk as host_epk_cust_id , v.ind_flag , v.workflow_run_id , v.input_file_id , v.info_system_id , 'I' as action_cd , 'N' as deleted_flag , -103500410::integer as session_inst_id from ( select q.cust_id , q.cust_epk , q.ind_flag , row_number() over (partition by q.cust_id order by q.ind_flag, q.sys_date_create_or_update desc) as rn from ( --гарантии select b.beneficiary_epkId_uid as cust_id , b.beneficiary_epkId as cust_epk , case when beneficiary_type = 'INDIVIDUAL_ENTREPRENEUR' then 'Y' when beneficiary_type = 'LEGAL' then 'N' else null end as ind_flag from s_grnplm_as_t_didsd_308_db_stg.b3080000460021_guarantee_actual_dto b where b.beneficiary_epkId_uid is not null and b.deleted = 'N' union all select b.applicant_epkId_uid as cust_id , b.applicant_epkId as cust_epk , case when applicant_type = 'INDIVIDUAL_ENTREPRENEUR' then 'Y' when applicant_type = 'LEGAL' then 'N' else null end as ind_flag from s_grnplm_as_t_didsd_308_db_stg.b3080000460021_guarantee_actual_dto b where b.applicant_epkId_uid is not null and b.deleted = 'N' -- не клиенты банка union all select b.applicant_taxId_uid , null::text as host_epk_cust_id , case when applicant_type = 'INDIVIDUAL_ENTREPRENEUR' then 'Y' when applicant_type = 'LEGAL' then 'N' else null end as ind_flag from s_grnplm_as_t_didsd_308_db_stg.b3080000460021_guarantee_actual_dto b where b.applicant_epkId is null and b.deleted = 'N' and (b.applicant_taxId is not null or applicant_fullName is not null) union all select b.beneficiary_taxId_uid as cust_id , null::text as cust_epk , case when beneficiary_type = 'INDIVIDUAL_ENTREPRENEUR' then 'Y' when beneficiary_type = 'LEGAL' then 'N' else null end as ind_flag from s_grnplm_as_t_didsd_308_db_stg.b3080000460021_guarantee_actual_dto b where b.beneficiary_epkId is null and b.deleted = 'N' and (b.beneficiary_taxId is not null or beneficiary_fullName is not null) union all --214 select b1_1.legalepkid_beneficiary_uid as cust_id , b1_1.legalepkid_beneficiary as cust_epk , 'N' as ind_flag from s_grnplm_as_t_didsd_308_db_stg.b3080000460001_escrow_legal214_agreement_actual_dto b1_1 where b1_1.legalepkid_beneficiary is not null and b1_1.deleted = 'N' union all select b1_2.legalepkid_deponent_uid as cust_id , b1_2.legalepkid_deponent as cust_epk , 'N' as ind_flag from s_grnplm_as_t_didsd_308_db_stg.b3080000460001_escrow_legal214_agreement_actual_dto b1_2 where b1_2.legalepkid_deponent is not null and b1_2.deleted = 'N' union all --гк --клиенты select b2.depositorlegal_epkid_uid as cust_id , b2.depositorlegal_epkid as cust_epk , 'N' as ind_flag from s_grnplm_as_t_didsd_308_db_stg.b3080000460002_escrow_legalgk_agreement_actual_dto b2 where b2.depositorlegal_epkid is not null and b2.deleted = 'N' union all select b3_1.epkid_i_uid as cust_id , b3_1.epkid_i as cust_epk , 'Y' as ind_flag from s_grnplm_as_t_didsd_308_db_stg.b3080000460003_escrow_legalgk_beneficiariesindividual b3_1 where b3_1.epkid_i is not null and b3_1.deleted = 'N' union all select b4_1.epkid_l_uid as cust_id , b4_1.epkid_l as cust_epk , 'N' as ind_flag from s_grnplm_as_t_didsd_308_db_stg.b3080000460004_escrow_legalgk_beneficiarieslegal b4_1 where b4_1.epkid_l is not null and b4_1.deleted = 'N' union all select b5.comissionerid_uid as cust_id , b5.comissionerid as cust_epk , null as ind_flag from s_grnplm_as_t_didsd_308_db_stg.b3080000460005_escrow_legalgk_tariffs b5 where b5.comissionerid_uid is not null and b5.deleted = 'N' --не клиенты банка union all select b3_2.beneficiariesindividual_uid as cust_id , null as cust_epk , 'Y' as ind_flag from s_grnplm_as_t_didsd_308_db_stg.b3080000460003_escrow_legalgk_beneficiariesindividual b3_2 where b3_2.epkid_i is null and b3_2.deleted = 'N' union all select b4_2.beneficiarieslegal_uid as cust_id , null as cust_epk , 'N' as ind_flag from s_grnplm_as_t_didsd_308_db_stg.b3080000460004_escrow_legalgk_beneficiarieslegal b4_2 where b4_2.epkid_l is null and b4_2.deleted = 'N' union all --гс select b.epkid_client_uid as cust_id , b.epkid_client as cust_epk , null as ind_flag from s_grnplm_as_t_didsd_308_db_stg.b3080000460009_general_agreement_actual_dto b where b.epkid_client_uid is not null and b.deleted = 'N' union all --эксп.инкассо select b.beneficiaryepkid_versionedattr_uid as cust_id , b.beneficiaryepkid_versionedattr as cust_epk , null as ind_flag from s_grnplm_as_t_didsd_308_db_stg.b3080000460016_inkasso_export_agreement_actual_dto b where b.beneficiaryepkid_versionedattr_uid is not null and b.deleted = 'N' union all select b.applicantepkid_versionedattr_uid as cust_id , b.applicantepkid_versionedattr as cust_epk , null as ind_flag from s_grnplm_as_t_didsd_308_db_stg.b3080000460016_inkasso_export_agreement_actual_dto b where b.applicantepkid_versionedattr_uid is not null and b.deleted = 'N' -- не клиенты банка union all select b.beneficiaryname_taxid_versionedattr_uid as cust_id , null::text as cust_epk , null as ind_flag from s_grnplm_as_t_didsd_308_db_stg.b3080000460016_inkasso_export_agreement_actual_dto b where b.beneficiaryepkid_versionedattr is null and b.deleted = 'N' and (b.beneficiaryname_versionedattr is not null or beneficiarytaxid_versionedattr is not null) union all select b.applicantname_taxid_versionedattr_uid as cust_id , null::text as cust_epk , null as ind_flag from s_grnplm_as_t_didsd_308_db_stg.b3080000460016_inkasso_export_agreement_actual_dto b where b.applicantepkid_versionedattr is null and b.deleted = 'N' and (b.applicantname_versionedattr is not null or applicanttaxid_versionedattr is not null) union all --имп.инкассо select b.beneficiaryepkid_versionedattr_uid as cust_id , b.beneficiaryepkid_versionedattr as cust_epk , null as ind_flag from s_grnplm_as_t_didsd_308_db_stg.b3080000460017_inkasso_import_agreement_actual_dto b where b.beneficiaryepkid_versionedattr_uid is not null and b.deleted = 'N' union all select b.applicantepkid_versionedattr_uid as cust_id , b.applicantepkid_versionedattr as cust_epk , null as ind_flag from s_grnplm_as_t_didsd_308_db_stg.b3080000460017_inkasso_import_agreement_actual_dto b where b.applicantepkid_versionedattr_uid is not null and b.deleted = 'N' -- не клиенты банка union all select b.beneficiaryname_taxid_versionedattr_uid , null::text as host_epk_cust_id , null as ind_flag from s_grnplm_as_t_didsd_308_db_stg.b3080000460017_inkasso_import_agreement_actual_dto b where b.beneficiaryepkid_versionedattr is null and b.deleted = 'N' and (b.beneficiaryname_versionedattr is not null or beneficiarytaxid_versionedattr is not null) union all select b.applicantname_taxid_versionedattr_uid as cust_id , null::text as cust_epk , null as ind_flag from s_grnplm_as_t_didsd_308_db_stg.b3080000460017_inkasso_import_agreement_actual_dto b where b.applicantepkid_versionedattr is null and b.deleted = 'N' and (b.applicantname_versionedattr is not null or applicanttaxid_versionedattr is not null) union all -- Аккредитивы ЮЛ select b15_1.applicantepkid_uid as cust_id , b15_1.applicantepkid as host_epk_cust_id , 'N' as ind_flag from s_grnplm_as_t_didsd_308_db_stg.b3080000460015_lcl_agreement_actual_dto as b15_1 where b15_1.applicantepkid_uid is not null and b15_1.deleted = 'N' union all select b15_2.applicantlegalname_tax_uid as cust_id , null::text as host_epk_cust_id , 'N' as ind_flag from s_grnplm_as_t_didsd_308_db_stg.b3080000460015_lcl_agreement_actual_dto as b15_2 where b15_2.applicantepkid_uid is null -- нет ЕПК, только по наименованию и ИНН and coalesce(b15_2.applicantlegalname, '')||coalesce(b15_2.applicanttaxid, '') <> '' -- конкатенированный НК, *_uid всегда не пустой and b15_2.deleted = 'N' union all select b15_3.beneficiarylegalepkid_uid as cust_id , b15_3.beneficiarylegalepkid as host_epk_cust_id , 'N' as ind_flag from s_grnplm_as_t_didsd_308_db_stg.b3080000460015_lcl_agreement_actual_dto as b15_3 where b15_3.beneficiarylegalepkid_uid is not null and b15_3.deleted = 'N' union all select b15_4.beneficiarylegalname_tax_uid as cust_id , null::text as host_epk_cust_id , 'N' as ind_flag from s_grnplm_as_t_didsd_308_db_stg.b3080000460015_lcl_agreement_actual_dto as b15_4 where b15_4.beneficiarylegalepkid_uid is null -- нет ЕПК, только по наименованию и ИНН and coalesce(b15_4.beneficiarylegalname, '')||coalesce(b15_4.beneficiarylegaltaxid, '') <> '' -- конкатенированный НК, *_uid всегда не пустой and b15_4.deleted = 'N' union all select b15_5.beneficiaryindepkid_uid as cust_id , null::text as host_epk_cust_id , 'Y' as ind_flag from s_grnplm_as_t_didsd_308_db_stg.b3080000460015_lcl_agreement_actual_dto as b15_5 where b15_5.beneficiaryindepkid_uid is not null and b15_5.deleted = 'N' union all select b15_6.beneficiaryindname_tax_uid as cust_id , null::text as host_epk_cust_id , 'Y' as ind_flag from s_grnplm_as_t_didsd_308_db_stg.b3080000460015_lcl_agreement_actual_dto as b15_6 where b15_6.beneficiaryindepkid_uid is null -- нет ЕПК, только по наименованию и ИНН and coalesce(b15_6.beneficiaryindividualname, '')||coalesce(b15_6.beneficiaryindividualtaxid, '') <> '' -- конкатенированный НК, *_uid всегда не пустой and b15_6.deleted = 'N' ) q ) v where v.rn = 1; | V46: ="n308000046_"&IFERROR(VLOOKUP(D46,target_tables[],5,0),"<not found>") -> n308000046_cust | W46: Ключ | AF46: Снимок-снимок
A47: 420 | B47: Эскроу, ГС, Аккредитив, УПФ | C47: =IFERROR(VLOOKUP(D47,'Target tables'!A:B,2,0),"") -> Контрагенты | D47: t_cust | E47: =IFERROR(VLOOKUP(D47&J47,'Target columns'!A:J,4,FALSE),"") -> TEXT | F47: =IFERROR(VLOOKUP(D47&J47,'Target columns'!A:J,7,FALSE),"") -> No | G47: =IFERROR(VLOOKUP(D47&J47,'Target columns'!A:J,8,FALSE),"") -> No | H47: =IFERROR(VLOOKUP(D47&J47,'Target columns'!A:J,5,FALSE),"") -> NULL | I47: =IFERROR(VLOOKUP(D47&J47,'Target columns'!A:J,10,FALSE),"") -> Идентификатор контрагента в ЕПК | J47: host_epk_cust_id | K47: ETL | L47: text | M47: ЕПК id юр.лица | N47: cust_epk | V47: ="n308000046_"&IFERROR(VLOOKUP(D47,target_tables[],5,0),"<not found>") -> n308000046_cust | W47: -
A48: 420 | B48: Эскроу, ГС, Аккредитив, УПФ | C48: =IFERROR(VLOOKUP(D48,'Target tables'!A:B,2,0),"") -> Контрагенты | D48: t_cust | E48: =IFERROR(VLOOKUP(D48&J48,'Target columns'!A:J,4,FALSE),"") -> TEXT | F48: =IFERROR(VLOOKUP(D48&J48,'Target columns'!A:J,7,FALSE),"") -> No | G48: =IFERROR(VLOOKUP(D48&J48,'Target columns'!A:J,8,FALSE),"") -> No | H48: =IFERROR(VLOOKUP(D48&J48,'Target columns'!A:J,5,FALSE),"") -> NULL | I48: =IFERROR(VLOOKUP(D48&J48,'Target columns'!A:J,10,FALSE),"") -> Физическое лицо | J48: ind_flag | K48: ETL | L48: text | M48: Физическое лицо | N48: ind_flag | V48: ="n308000046_"&IFERROR(VLOOKUP(D48,target_tables[],5,0),"<not found>") -> n308000046_cust | W48: -
A49: 430 | B49: Эскроу, ГС, Аккредитив, УПФ | C49: =IFERROR(VLOOKUP(D49,'Target tables'!A:B,2,0),"") -> Справочник оргструктуры | D49: t_int_org | E49: =IFERROR(VLOOKUP(D49&J49,'Target columns'!A:J,4,FALSE),"") -> UUID | F49: =IFERROR(VLOOKUP(D49&J49,'Target columns'!A:J,7,FALSE),"") -> Yes | G49: =IFERROR(VLOOKUP(D49&J49,'Target columns'!A:J,8,FALSE),"") -> No | H49: =IFERROR(VLOOKUP(D49&J49,'Target columns'!A:J,5,FALSE),"") -> NOT NULL | I49: =IFERROR(VLOOKUP(D49&J49,'Target columns'!A:J,10,FALSE),"") -> Идентификатор оргструктуры | J49: int_org_id | K49: ETL | L49: uuid | M49: Идентификатор оргструктуры | N49: int_org_id | S49: select v2.int_org_id , v2.int_org_num , v2.bic_num , v2.int_org_name from ( select v.int_org_id , v.int_org_num , row_number() over (partition by v.int_org_id order by v.sys_date_create_or_update desc) as rn from ( -- Гарантии select b2_2.bankBranchOsbCode_uid as int_org_id , concat(b2_2.bankBranch, b2_2.osbCode) as int_org_num , null::text as bic_num , null::text as int_org_name , b2_2.sys_date_create_or_update from s_grnplm_as_t_didsd_308_db_stg.b3080000460021_guarantee_actual_dto b2_2 where bankBranchOsbCode_uid is not null and b2_2.deleted = 'N' union all select b2_2.beneficiaryBankBranchOsbCode_uid as int_org_id , concat(b2_2.beneficiaryBankOsbCode, b2_2.beneficiaryBankOsbCode) as int_org_num , null::text as bic_num , null::text as int_org_name , b2_2.sys_date_create_or_update from s_grnplm_as_t_didsd_308_db_stg.b3080000460021_guarantee_actual_dto b2_2 where beneficiaryBankBranchOsbCode_uid is not null and b2_2.deleted = 'N' union all --214 -- депонент / счет / сопровождение договора select b1_1.escrowbranchcode_agreement_uid as int_org_id , b1_1.escrowbranchcode_agreement as int_org_num , null::text as bic_num , null::text as int_org_name , b1_1.sys_date_create_or_update from s_grnplm_as_t_didsd_308_db_stg.b3080000460001_escrow_legal214_agreement_actual_dto b1_1 where b1_1.escrowbranchcode_agreement is not null and b1_1.deleted = 'N' union all -- бенефициар select b1_2.bankunitcode_beneficiary_uid as int_org_id , b1_2.bankunitcode_beneficiary as int_org_num , null::text as bic_num , null::text as int_org_name , b1_2.sys_date_create_or_update from s_grnplm_as_t_didsd_308_db_stg.b3080000460001_escrow_legal214_agreement_actual_dto b1_2 where b1_2.bankunitcode_beneficiary is not null and b1_2.deleted = 'N' --гк -- сопровождение договора / значение по балансу union all select b2_1.escrowbankregionaloffice_uid as int_org_id , b2_1.escrowbankregionaloffice as int_org_num , null::text as bic_num , null::text as int_org_name , b2_1.sys_date_create_or_update from s_grnplm_as_t_didsd_308_db_stg.b3080000460002_escrow_legalgk_agreement_actual_dto b2_1 where b2_1.escrowbankregionaloffice is not null and b2_1.deleted = 'N' -- по схеме распределения дохода депонент union all select b2_2.deponentbank_uid as int_org_id , concat(b2_2.deponentbankbranch, b2_2.deponentbankregionalunit) as int_org_num , null::text as bic_num , null::text as int_org_name , b2_2.sys_date_create_or_update from s_grnplm_as_t_didsd_308_db_stg.b3080000460002_escrow_legalgk_agreement_actual_dto b2_2 where b2_2.deponentbankbranch is not null and b2_2.deleted = 'N' -- по схеме распределения дохода бенефициар union all select b2_3.beneficiarybank_uid as int_org_id , concat(b2_3.beneficiarybankbranch, b2_3.beneficiarybankregionalunit) as int_org_num , null::text as bic_num , null::text as int_org_name , b2_3.sys_date_create_or_update from s_grnplm_as_t_didsd_308_db_stg.b3080000460002_escrow_legalgk_agreement_actual_dto b2_3 where b2_3.beneficiarybankbranch is not null and b2_3.deleted = 'N' --гс union all select b9.bankbranchosb_uid as int_org_id , b9.bankbranchosb as int_org_num , null::text as bic_num , null::text as int_org_name , b9.sys_date_create_or_update from s_grnplm_as_t_didsd_308_db_stg.b3080000460009_general_agreement_actual_dto b9 where b9.bankbranchosb is not null and b9.deleted = 'N' union all -- Аккредитивы ЮЛ select b.applicant_tbosb_uid as int_org_id , coalesce(b.applicantterritorybankbranchcode,'')||coalesce(b.applicantterritoryosbcode,'') as int_org_num , b.applicantterritorybic as bic_num , b.applicantterritoryname as int_org_name , b.sys_date_create_or_update from s_grnplm_as_t_didsd_308_db_stg.b3080000460015_lcl_agreement_actual_dto as b where 1 = 1 and coalesce(b.applicantterritorybankbranchcode,'')||coalesce(b.applicantterritoryosbcode,'') <> '' -- конкатенированный НК, *_uid всегда не пустой and upper(b.deleted) = 'N' union all select b.beneficiary_tbosb_uid as int_org_id , coalesce(b.beneficiaryterritorybankbranchcode,'')||coalesce(b.beneficiaryterritoryosbcode,'') as int_org_num , b.beneficiaryterritorybic as bic_num , b.beneficiaryterritoryname as int_org_name , b.sys_date_create_or_update from s_grnplm_as_t_didsd_308_db_stg.b3080000460015_lcl_agreement_actual_dto as b where 1 = 1 and coalesce(b.beneficiaryterritorybankbranchcode,'')||coalesce(b.beneficiaryterritoryosbcode,'') <> '' -- конкатенированный НК, *_uid всегда не пустой and upper(b.deleted) = 'N' union all select b.regionalunit_tbosb_uid as int_org_id , coalesce(b.bankregionalunitbankbranchcode,'')||coalesce(b.bankregionalunitosbcode,'') as int_org_num , b.bankregionalunitbic as bic_num , b.bankregionalunitname as int_org_name , b.sys_date_create_or_update from s_grnplm_as_t_didsd_308_db_stg.b3080000460015_lcl_agreement_actual_dto as b where 1 = 1 and coalesce(b.bankregionalunitbankbranchcode,'')||coalesce(b.bankregionalunitosbcode,'') <> '' -- конкатенированный НК, *_uid всегда не пустой and upper(b.deleted) = 'N' union all -- Эксп.инкассо select b.bankregionalunitcode_versionedattr_uid as int_org_id , b.bankregionalunitcode_versionedattr as int_org_num , null::text as bic_num , bankregionalunitname_versionedattr::text as int_org_name , b.sys_date_create_or_update from s_grnplm_as_t_didsd_308_db_stg.b3080000460016_inkasso_export_agreement_actual_dto b where b.bankregionalunitcode_versionedattr is not null and b.deleted = 'N' union all select b.beneficiarybankunitcode_versionedattr_uid as int_org_id , b.beneficiarybankunitcode_versionedattr as int_org_num , null::text as bic_num , bankregionalunitname_versionedattr::text as int_org_name , b.sys_date_create_or_update from s_grnplm_as_t_didsd_308_db_stg.b3080000460016_inkasso_export_agreement_actual_dto b where b.beneficiarybankunitcode_versionedattr is not null and b.deleted = 'N' union all -- Имп.инкассо select b.bankregionalunitcode_versionedattr_uid as int_org_id , b.bankregionalunitcode_versionedattr as int_org_num , null::text as bic_num , bankregionalunitname_versionedattr::text as int_org_name , b.sys_date_create_or_update from s_grnplm_as_t_didsd_308_db_stg.b3080000460017_inkasso_import_agreement_actual_dto b where b.bankregionalunitcode_versionedattr is not null and b.deleted = 'N' union all select b.applicantbankunitcode_versionedattr_uid as int_org_id , b.applicantbankunitcode_versionedattr as int_org_num , null::text as bic_num , bankregionalunitname_versionedattr::text as int_org_name , b.sys_date_create_or_update from s_grnplm_as_t_didsd_308_db_stg.b3080000460017_inkasso_import_agreement_actual_dto b where b.applicantbankunitcode_versionedattr is not null and b.deleted = 'N' union all -- Рамбурс select b.bankregionalunitcode_uid as int_org_id , b.bankregionalunitcode as int_org_num , null::text as bic_num , null::text as int_org_name , b.sys_date_create_or_update from s_grnplm_as_t_didsd_308_db_stg.b3080000460018_reimbursement_agreement_actual_dto b where b.bankregionalunitcode is not null and b.deleted = 'N' ) v ) v2 where v2.rn = 1 | V49: ="n308000046_"&IFERROR(VLOOKUP(D49,target_tables[],5,0),"<not found>") -> n308000046_int_org | W49: Ключ | AF49: Снимок-снимок
A50: 440 | B50: Эскроу, ГС, Аккредитив, УПФ | C50: =IFERROR(VLOOKUP(D50,'Target tables'!A:B,2,0),"") -> Справочник оргструктуры | D50: t_int_org | E50: =IFERROR(VLOOKUP(D50&J50,'Target columns'!A:J,4,FALSE),"") -> TEXT | F50: =IFERROR(VLOOKUP(D50&J50,'Target columns'!A:J,7,FALSE),"") -> No | G50: =IFERROR(VLOOKUP(D50&J50,'Target columns'!A:J,8,FALSE),"") -> No | H50: =IFERROR(VLOOKUP(D50&J50,'Target columns'!A:J,5,FALSE),"") -> NULL | I50: =IFERROR(VLOOKUP(D50&J50,'Target columns'!A:J,10,FALSE),"") -> Номер внутреннего подразделения | J50: int_org_num | K50: ETL | L50: text | M50: Номер внутреннего подразделения | N50: int_org_num | V50: ="n308000046_"&IFERROR(VLOOKUP(D50,target_tables[],5,0),"<not found>") -> n308000046_int_org | W50: -
A51: 441 | B51: Эскроу, ГС, Аккредитив, УПФ | C51: =IFERROR(VLOOKUP(D51,'Target tables'!A:B,2,0),"") -> Справочник оргструктуры | D51: t_int_org | E51: =IFERROR(VLOOKUP(D51&J51,'Target columns'!A:J,4,FALSE),"") -> text | F51: =IFERROR(VLOOKUP(D51&J51,'Target columns'!A:J,7,FALSE),"") -> No | G51: =IFERROR(VLOOKUP(D51&J51,'Target columns'!A:J,8,FALSE),"") -> No | H51: =IFERROR(VLOOKUP(D51&J51,'Target columns'!A:J,5,FALSE),"") -> NULL | I51: =IFERROR(VLOOKUP(D51&J51,'Target columns'!A:J,10,FALSE),"") -> БИК | J51: bic_num | K51: ETL | L51: text | M51: БИК | N51: bic_num | V51: ="n308000046_"&IFERROR(VLOOKUP(D51,target_tables[],5,0),"<not found>") -> n308000046_int_org | W51: -
A52: 442 | B52: Эскроу, ГС, Аккредитив, УПФ | C52: =IFERROR(VLOOKUP(D52,'Target tables'!A:B,2,0),"") -> Справочник оргструктуры | D52: t_int_org | E52: =IFERROR(VLOOKUP(D52&J52,'Target columns'!A:J,4,FALSE),"") -> text | F52: =IFERROR(VLOOKUP(D52&J52,'Target columns'!A:J,7,FALSE),"") -> No | G52: =IFERROR(VLOOKUP(D52&J52,'Target columns'!A:J,8,FALSE),"") -> No | H52: =IFERROR(VLOOKUP(D52&J52,'Target columns'!A:J,5,FALSE),"") -> NULL | I52: =IFERROR(VLOOKUP(D52&J52,'Target columns'!A:J,10,FALSE),"") -> Наименование подразделения | J52: int_org_name | K52: ETL | L52: text | M52: Наименование | N52: int_org_name | V52: ="n308000046_"&IFERROR(VLOOKUP(D52,target_tables[],5,0),"<not found>") -> n308000046_int_org | W52: -
A53: 450 | B53: Эскроу | C53: =IFERROR(VLOOKUP(D53,'Target tables'!A:B,2,0),"") -> Таблица связей договора эскроу со справочником оргструктуры | D53: t_agr_escrow_int_org | E53: =IFERROR(VLOOKUP(D53&J53,'Target columns'!A:J,4,FALSE),"") -> UUID | F53: =IFERROR(VLOOKUP(D53&J53,'Target columns'!A:J,7,FALSE),"") -> Yes | G53: =IFERROR(VLOOKUP(D53&J53,'Target columns'!A:J,8,FALSE),"") -> Yes | H53: =IFERROR(VLOOKUP(D53&J53,'Target columns'!A:J,5,FALSE),"") -> NOT NULL | I53: =IFERROR(VLOOKUP(D53&J53,'Target columns'!A:J,10,FALSE),"") -> Идентификатор договора | J53: agr_escrow_id | K53: b3080000460001_escrow_legal214_agreement_actual_dto | L53: =IFERROR(VLOOKUP(UPPER(K53&N53),source_columns[],4,0),"") -> uuid | M53: =IFERROR(VLOOKUP(UPPER(K53&N53),source_columns[],7,0),"") -> Идентификатор договора эскроу | N53: escrowId_agreement_uid | S53: bankunitcode_beneficiary is not null or escrowBranchCode_agreement is not null | V53: ="n308000046_"&IFERROR(VLOOKUP(D53,target_tables[],5,0),"<not found>") -> n308000046_agr_escrow_int_org | W53: Ключ | AF53: Снимок-история
A54: 460 | B54: Эскроу | C54: =IFERROR(VLOOKUP(D54,'Target tables'!A:B,2,0),"") -> Таблица связей договора эскроу со справочником оргструктуры | D54: t_agr_escrow_int_org | E54: =IFERROR(VLOOKUP(D54&J54,'Target columns'!A:J,4,FALSE),"") -> UUID | F54: =IFERROR(VLOOKUP(D54&J54,'Target columns'!A:J,7,FALSE),"") -> No | G54: =IFERROR(VLOOKUP(D54&J54,'Target columns'!A:J,8,FALSE),"") -> Yes | H54: =IFERROR(VLOOKUP(D54&J54,'Target columns'!A:J,5,FALSE),"") -> NULL | I54: =IFERROR(VLOOKUP(D54&J54,'Target columns'!A:J,10,FALSE),"") -> Код ВСП ведения договора | J54: int_org_id | K54: b3080000460001_escrow_legal214_agreement_actual_dto | N54: null | V54: ="n308000046_"&IFERROR(VLOOKUP(D54,target_tables[],5,0),"<not found>") -> n308000046_agr_escrow_int_org | W54: -
A55: 470 | B55: Эскроу | C55: =IFERROR(VLOOKUP(D55,'Target tables'!A:B,2,0),"") -> Таблица связей договора эскроу со справочником оргструктуры | D55: t_agr_escrow_int_org | E55: =IFERROR(VLOOKUP(D55&J55,'Target columns'!A:J,4,FALSE),"") -> UUID | F55: =IFERROR(VLOOKUP(D55&J55,'Target columns'!A:J,7,FALSE),"") -> No | G55: =IFERROR(VLOOKUP(D55&J55,'Target columns'!A:J,8,FALSE),"") -> Yes | H55: =IFERROR(VLOOKUP(D55&J55,'Target columns'!A:J,5,FALSE),"") -> NULL | I55: =IFERROR(VLOOKUP(D55&J55,'Target columns'!A:J,10,FALSE),"") -> Код ВСП открытия счета бенефициара | J55: ben_int_org_id | K55: b3080000460001_escrow_legal214_agreement_actual_dto | L55: =IFERROR(VLOOKUP(UPPER(K55&N55),source_columns[],4,0),"") -> uuid | M55: Код ВСП бенефициара | N55: bankunitcode_beneficiary_uid | V55: ="n308000046_"&IFERROR(VLOOKUP(D55,target_tables[],5,0),"<not found>") -> n308000046_agr_escrow_int_org | W55: -
A56: 480 | B56: Эскроу | C56: =IFERROR(VLOOKUP(D56,'Target tables'!A:B,2,0),"") -> Таблица связей договора эскроу со справочником оргструктуры | D56: t_agr_escrow_int_org | E56: =IFERROR(VLOOKUP(D56&J56,'Target columns'!A:J,4,FALSE),"") -> UUID | F56: =IFERROR(VLOOKUP(D56&J56,'Target columns'!A:J,7,FALSE),"") -> No | G56: =IFERROR(VLOOKUP(D56&J56,'Target columns'!A:J,8,FALSE),"") -> Yes | H56: =IFERROR(VLOOKUP(D56&J56,'Target columns'!A:J,5,FALSE),"") -> NULL | I56: =IFERROR(VLOOKUP(D56&J56,'Target columns'!A:J,10,FALSE),"") -> Код ВСП открытия счета депонента | J56: dep_int_org_id | K56: b3080000460001_escrow_legal214_agreement_actual_dto | L56: =IFERROR(VLOOKUP(UPPER(K56&N56),source_columns[],4,0),"") -> uuid | M56: =IFERROR(VLOOKUP(UPPER(K56&N56),source_columns[],7,0),"") -> Терр структура ведения договора | N56: escrowBranchCode_agreement_uid | V56: ="n308000046_"&IFERROR(VLOOKUP(D56,target_tables[],5,0),"<not found>") -> n308000046_agr_escrow_int_org | W56: -
A57: 490 | B57: Эскроу | C57: =IFERROR(VLOOKUP(D57,'Target tables'!A:B,2,0),"") -> Таблица связей договора эскроу со справочником оргструктуры | D57: t_agr_escrow_int_org | E57: =IFERROR(VLOOKUP(D57&J57,'Target columns'!A:J,4,FALSE),"") -> DATE | F57: =IFERROR(VLOOKUP(D57&J57,'Target columns'!A:J,7,FALSE),"") -> Yes | G57: =IFERROR(VLOOKUP(D57&J57,'Target columns'!A:J,8,FALSE),"") -> No | H57: =IFERROR(VLOOKUP(D57&J57,'Target columns'!A:J,5,FALSE),"") -> NOT NULL | I57: =IFERROR(VLOOKUP(D57&J57,'Target columns'!A:J,10,FALSE),"") -> Дата начала действия связи | J57: start_dt | K57: b3080000460001_escrow_legal214_agreement_actual_dto | L57: =IFERROR(VLOOKUP(UPPER(K57&N57),source_columns[],4,0),"") | M57: =IFERROR(VLOOKUP(UPPER(K57&N57),source_columns[],7,0),"") | N57: cast(sys_date_create_or_update as date) | V57: ="n308000046_"&IFERROR(VLOOKUP(D57,target_tables[],5,0),"<not found>") -> n308000046_agr_escrow_int_org | W57: Начало
A58: 500 | B58: Эскроу | C58: =IFERROR(VLOOKUP(D58,'Target tables'!A:B,2,0),"") -> Таблица связей договора эскроу со справочником оргструктуры | D58: t_agr_escrow_int_org | E58: =IFERROR(VLOOKUP(D58&J58,'Target columns'!A:J,4,FALSE),"") -> DATE | F58: =IFERROR(VLOOKUP(D58&J58,'Target columns'!A:J,7,FALSE),"") -> No | G58: =IFERROR(VLOOKUP(D58&J58,'Target columns'!A:J,8,FALSE),"") -> No | H58: =IFERROR(VLOOKUP(D58&J58,'Target columns'!A:J,5,FALSE),"") -> NULL | I58: =IFERROR(VLOOKUP(D58&J58,'Target columns'!A:J,10,FALSE),"") -> Дата окончания действия связи | J58: end_dt | K58: b3080000460001_escrow_legal214_agreement_actual_dto | L58: =IFERROR(VLOOKUP(UPPER(K58&N58),source_columns[],4,0),"") | M58: =IFERROR(VLOOKUP(UPPER(K58&N58),source_columns[],7,0),"") | N58: cast('9999-12-31' as date) | V58: ="n308000046_"&IFERROR(VLOOKUP(D58,target_tables[],5,0),"<not found>") -> n308000046_agr_escrow_int_org | W58: Конец
A59: 510 | B59: Эскроу, ГС, Аккредитив, УПФ | C59: =IFERROR(VLOOKUP(D59,'Target tables'!A:B,2,0),"") -> Справочник валюты | D59: t_crncy | E59: =IFERROR(VLOOKUP(D59&J59,'Target columns'!A:J,4,FALSE),"") -> UUID | F59: =IFERROR(VLOOKUP(D59&J59,'Target columns'!A:J,7,FALSE),"") -> Yes | G59: =IFERROR(VLOOKUP(D59&J59,'Target columns'!A:J,8,FALSE),"") -> No | H59: =IFERROR(VLOOKUP(D59&J59,'Target columns'!A:J,5,FALSE),"") -> NOT NULL | I59: =IFERROR(VLOOKUP(D59&J59,'Target columns'!A:J,10,FALSE),"") -> Идентификатор валюты | J59: crncy_id | K59: ETL | L59: uuid | M59: Валюта суммы депонирования | N59: crncy_id | S59: from ( select sub_1.crncy_id , sub_1.iso_crncy_cd , row_number() over (partition by sub_1.crncy_id order by sub_1.sys_date_create_or_update desc) as rn from ( select b1.escrowAmount_currency_agreement_uid as crncy_id , b1.escrowAmount_currency_agreement as iso_crncy_cd from s_grnplm_as_t_didsd_308_db_stg.b3080000460001_escrow_legal214_agreement_actual_dto b1 where b1.escrowAmount_currency_agreement is not null and b1.deleted = 'N' union all select b2.escrowamount_currency_uid as crncy_id , b2.escrowamount_currency as iso_crncy_cd from s_grnplm_as_t_didsd_308_db_stg.b3080000460002_escrow_legalgk_agreement_actual_dto b2 where b2.escrowamount_currency is not null and b2.deleted = 'N' union all select b6.currency_uid as crncy_id , b6.currency as iso_crncy_cd from s_grnplm_as_t_didsd_308_db_stg.b3080000460006_payments_2_0_posting_dto b6 where b6.currency is not null and b6.deleted = 'N' union all select b8.currency_amnt_limitschedule_uid as crncy_id , b8.currency_amnt_limitschedule as iso_crncy_cd from s_grnplm_as_t_didsd_308_db_stg.b3080000460008_general_agreement_actual_limitschedule b8 where b8.currency_amnt_limitschedule is not null and b8.deleted = 'N' union all -- Аккредитивы ЮЛ select b15.amountcurrencycode_uid as crncy_id , b15.amountcurrencycode as iso_crncy_cd from s_grnplm_as_t_didsd_308_db_stg.b3080000460015_lcl_agreement_actual_dto as b15 where b15.amountcurrencycode_uid is not null and b15.deleted = 'N' --Имп.инкассо select b17.currencycode_versionedattr_uid as crncy_id , b17.currencycode_versionedattr as iso_crncy_cd from s_grnplm_as_t_didsd_308_db_stg.b3080000460017_inkasso_import_agreement_actual_dto as b17 where b17.currencycode_versionedattr_uid is not null and b17.deleted = 'N' union all --Эксп.инкассо select b16.currencycode_versionedattr_uid as crncy_id , b16.currencycode_versionedattr as iso_crncy_cd from s_grnplm_as_t_didsd_308_db_stg.b3080000460016_inkasso_export_agreement_actual_dto as b16 where b16.currencycode_versionedattr_uid is not null and b16.deleted = 'N' union all --Рамбурс select b18.currencycode_uid as crncy_id , b18.currencycode as iso_crncy_cd from s_grnplm_as_t_didsd_308_db_stg.b3080000460018_reimbursement_agreement_actual_dto as b18 where b18.currencycode_uid is not null and b18.deleted = 'N' union all --Гарантии select b19.amount_currency_uid as crncy_id , b19.amount_currency as iso_crncy_cd from s_grnplm_as_t_didsd_308_db_stg.b3080000460021_guarantee_actual_dto as b19 where b19.amount_currency is not null and b19.deleted = 'N' union all --ГОДС select b19.conventionAmount_currency_uid as crncy_id , b19.conventionAmount_currency as iso_crncy_cd from s_grnplm_as_t_didsd_308_db_stg.b3080000460022_escrow_legalgk_gods_actual_dto as b19 where b19.conventionAmount_currency is not null and b19.deleted = 'N' ) sub_1 | V59: ="n308000046_"&IFERROR(VLOOKUP(D59,target_tables[],5,0),"<not found>") -> n308000046_crncy | W59: Ключ | AF59: Снимок-снимок
A60: 520 | B60: Эскроу, ГС, Аккредитив, УПФ | C60: =IFERROR(VLOOKUP(D60,'Target tables'!A:B,2,0),"") -> Справочник валюты | D60: t_crncy | E60: =IFERROR(VLOOKUP(D60&J60,'Target columns'!A:J,4,FALSE),"") -> TEXT | F60: =IFERROR(VLOOKUP(D60&J60,'Target columns'!A:J,7,FALSE),"") -> No | G60: =IFERROR(VLOOKUP(D60&J60,'Target columns'!A:J,8,FALSE),"") -> No | H60: =IFERROR(VLOOKUP(D60&J60,'Target columns'!A:J,5,FALSE),"") -> NULL | I60: =IFERROR(VLOOKUP(D60&J60,'Target columns'!A:J,10,FALSE),"") -> Буквенный код валюты | J60: iso_crncy_cd | K60: ETL | L60: text | M60: Валюта суммы депонирования | N60: iso_crncy_cd | V60: ="n308000046_"&IFERROR(VLOOKUP(D60,target_tables[],5,0),"<not found>") -> n308000046_crncy | W60: -
A61: 530 | B61: Эскроу | C61: =IFERROR(VLOOKUP(D61,'Target tables'!A:B,2,0),"") -> Договор эскроу | D61: t_agr_escrow | E61: =IFERROR(VLOOKUP(D61&J61,'Target columns'!A:J,4,FALSE),"") -> UUID | F61: =IFERROR(VLOOKUP(D61&J61,'Target columns'!A:J,7,FALSE),"") -> Yes | G61: =IFERROR(VLOOKUP(D61&J61,'Target columns'!A:J,8,FALSE),"") -> No | H61: =IFERROR(VLOOKUP(D61&J61,'Target columns'!A:J,5,FALSE),"") -> NOT NULL | I61: =IFERROR(VLOOKUP(D61&J61,'Target columns'!A:J,10,FALSE),"") -> Идентификатор договора эскроу | J61: agr_escrow_id | K61: b3080000460002_escrow_legalgk_agreement_actual_dto | L61: =IFERROR(VLOOKUP(UPPER(K61&N61), source_columns[], 4,0),"") -> uuid | M61: =IFERROR(VLOOKUP(UPPER(K61&N61), source_columns[], 7,0),"") -> Идентификатор договора эскроу | N61: escrowid_uid | V61: ="n308000046_"&IFERROR(VLOOKUP(D61,target_tables[],5,0),"<not found>") -> n308000046_agr_escrow | W61: Ключ | AF61: Снимок-снимок
A62: 540 | B62: Эскроу | C62: =IFERROR(VLOOKUP(D62,'Target tables'!A:B,2,0),"") -> Договор эскроу | D62: t_agr_escrow | E62: =IFERROR(VLOOKUP(D62&J62,'Target columns'!A:J,4,FALSE),"") -> DATE | F62: =IFERROR(VLOOKUP(D62&J62,'Target columns'!A:J,7,FALSE),"") -> No | G62: =IFERROR(VLOOKUP(D62&J62,'Target columns'!A:J,8,FALSE),"") -> No | H62: =IFERROR(VLOOKUP(D62&J62,'Target columns'!A:J,5,FALSE),"") -> NULL | I62: =IFERROR(VLOOKUP(D62&J62,'Target columns'!A:J,10,FALSE),"") -> Дата открытия договора эскроу | J62: open_dt | K62: b3080000460002_escrow_legalgk_agreement_actual_dto | L62: =IFERROR(VLOOKUP(UPPER(K62&N62),source_columns[],4,0),"") -> date | M62: =IFERROR(VLOOKUP(UPPER(K62&N62),source_columns[],7,0),"") -> Дата открытия договора эскроу | N62: conclusiondate | V62: ="n308000046_"&IFERROR(VLOOKUP(D62,target_tables[],5,0),"<not found>") -> n308000046_agr_escrow | W62: -
A63: 550 | B63: Эскроу | C63: =IFERROR(VLOOKUP(D63,'Target tables'!A:B,2,0),"") -> Договор эскроу | D63: t_agr_escrow | E63: =IFERROR(VLOOKUP(D63&J63,'Target columns'!A:J,4,FALSE),"") -> DATE | F63: =IFERROR(VLOOKUP(D63&J63,'Target columns'!A:J,7,FALSE),"") -> No | G63: =IFERROR(VLOOKUP(D63&J63,'Target columns'!A:J,8,FALSE),"") -> No | H63: =IFERROR(VLOOKUP(D63&J63,'Target columns'!A:J,5,FALSE),"") -> NULL | I63: =IFERROR(VLOOKUP(D63&J63,'Target columns'!A:J,10,FALSE),"") -> Дата подписания договора эскроу | J63: signed_dt | K63: b3080000460002_escrow_legalgk_agreement_actual_dto | L63: =IFERROR(VLOOKUP(UPPER(K63&N63),source_columns[],4,0),"") | M63: =IFERROR(VLOOKUP(UPPER(K63&N63),source_columns[],7,0),"") | N63: Null | V63: ="n308000046_"&IFERROR(VLOOKUP(D63,target_tables[],5,0),"<not found>") -> n308000046_agr_escrow | W63: -
A64: 560 | B64: Эскроу | C64: =IFERROR(VLOOKUP(D64,'Target tables'!A:B,2,0),"") -> Договор эскроу | D64: t_agr_escrow | E64: =IFERROR(VLOOKUP(D64&J64,'Target columns'!A:J,4,FALSE),"") -> DATE | F64: =IFERROR(VLOOKUP(D64&J64,'Target columns'!A:J,7,FALSE),"") -> No | G64: =IFERROR(VLOOKUP(D64&J64,'Target columns'!A:J,8,FALSE),"") -> No | H64: =IFERROR(VLOOKUP(D64&J64,'Target columns'!A:J,5,FALSE),"") -> NULL | I64: =IFERROR(VLOOKUP(D64&J64,'Target columns'!A:J,10,FALSE),"") -> Дата закрытия договора эскроу | J64: close_dt | K64: b3080000460002_escrow_legalgk_agreement_actual_dto | L64: =IFERROR(VLOOKUP(UPPER(K64&N64),source_columns[],4,0),"") -> date | M64: =IFERROR(VLOOKUP(UPPER(K64&N64),source_columns[],7,0),"") -> Дата закрытия договора эскроу | N64: closedate | V64: ="n308000046_"&IFERROR(VLOOKUP(D64,target_tables[],5,0),"<not found>") -> n308000046_agr_escrow | W64: -
A65: 561 | B65: Эскроу | C65: =IFERROR(VLOOKUP(D65,'Target tables'!A:B,2,0),"") -> Договор эскроу | D65: t_agr_escrow | E65: =IFERROR(VLOOKUP(D65&J65,'Target columns'!A:J,4,FALSE),"") -> DATE | F65: =IFERROR(VLOOKUP(D65&J65,'Target columns'!A:J,7,FALSE),"") -> No | G65: =IFERROR(VLOOKUP(D65&J65,'Target columns'!A:J,8,FALSE),"") -> No | H65: =IFERROR(VLOOKUP(D65&J65,'Target columns'!A:J,5,FALSE),"") -> NULL | I65: =IFERROR(VLOOKUP(D65&J65,'Target columns'!A:J,10,FALSE),"") -> Срок депонирования суммы | J65: depositing_dt | K65: b3080000460002_escrow_legalgk_agreement_actual_dto | L65: =IFERROR(VLOOKUP(UPPER(K65&N65),source_columns[],4,0),"") -> date | M65: =IFERROR(VLOOKUP(UPPER(K65&N65),source_columns[],7,0),"") -> Срок депонированной суммы | N65: depositWithdrawalDate | V65: ="n308000046_"&IFERROR(VLOOKUP(D65,target_tables[],5,0),"<not found>") -> n308000046_agr_escrow | W65: -
A66: 570 | B66: Эскроу | C66: =IFERROR(VLOOKUP(D66,'Target tables'!A:B,2,0),"") -> Договор эскроу | D66: t_agr_escrow | E66: =IFERROR(VLOOKUP(D66&J66,'Target columns'!A:J,4,FALSE),"") -> TEXT | F66: =IFERROR(VLOOKUP(D66&J66,'Target columns'!A:J,7,FALSE),"") -> No | G66: =IFERROR(VLOOKUP(D66&J66,'Target columns'!A:J,8,FALSE),"") -> No | H66: =IFERROR(VLOOKUP(D66&J66,'Target columns'!A:J,5,FALSE),"") -> NULL | I66: =IFERROR(VLOOKUP(D66&J66,'Target columns'!A:J,10,FALSE),"") -> Номер договора эскроу | J66: agr_escrow_num | K66: b3080000460002_escrow_legalgk_agreement_actual_dto | L66: =IFERROR(VLOOKUP(UPPER(K66&N66),source_columns[],4,0),"") -> text | M66: =IFERROR(VLOOKUP(UPPER(K66&N66),source_columns[],7,0),"") -> Номер договора | N66: reference | V66: ="n308000046_"&IFERROR(VLOOKUP(D66,target_tables[],5,0),"<not found>") -> n308000046_agr_escrow | W66: -
A67: 571 | B67: Эскроу | C67: =IFERROR(VLOOKUP(D67,'Target tables'!A:B,2,0),"") -> Договор эскроу | D67: t_agr_escrow | E67: =IFERROR(VLOOKUP(D67&J67,'Target columns'!A:J,4,FALSE),"") -> UUID | F67: =IFERROR(VLOOKUP(D67&J67,'Target columns'!A:J,7,FALSE),"") -> No | G67: =IFERROR(VLOOKUP(D67&J67,'Target columns'!A:J,8,FALSE),"") -> Yes | H67: =IFERROR(VLOOKUP(D67&J67,'Target columns'!A:J,5,FALSE),"") -> NULL | I67: =IFERROR(VLOOKUP(D67&J67,'Target columns'!A:J,10,FALSE),"") -> Идентификатор типа договора эскроу | J67: agr_escrow_type_id | K67: b3080000460002_escrow_legalgk_agreement_actual_dto | L67: =IFERROR(VLOOKUP(UPPER(K67&N67),source_columns[],4,0),"") -> uuid | M67: =IFERROR(VLOOKUP(UPPER(K67&N67),source_columns[],7,0),"") -> Тип договора эскроу ГК | N67: escrowType_code_uid | V67: ="n308000046_"&IFERROR(VLOOKUP(D67,target_tables[],5,0),"<not found>") -> n308000046_agr_escrow | W67: -
A68: 580 | B68: Эскроу | C68: =IFERROR(VLOOKUP(D68,'Target tables'!A:B,2,0),"") -> Договор эскроу | D68: t_agr_escrow | E68: =IFERROR(VLOOKUP(D68&J68,'Target columns'!A:J,4,FALSE),"") -> TEXT | F68: =IFERROR(VLOOKUP(D68&J68,'Target columns'!A:J,7,FALSE),"") -> No | G68: =IFERROR(VLOOKUP(D68&J68,'Target columns'!A:J,8,FALSE),"") -> No | H68: =IFERROR(VLOOKUP(D68&J68,'Target columns'!A:J,5,FALSE),"") -> NULL | I68: =IFERROR(VLOOKUP(D68&J68,'Target columns'!A:J,10,FALSE),"") -> Идентификатор договора эскроу в системе-источнике | J68: host_agr_escrow_id | K68: b3080000460002_escrow_legalgk_agreement_actual_dto | L68: =IFERROR(VLOOKUP(UPPER(K68&N68),source_columns[],4,0),"") -> text | M68: =IFERROR(VLOOKUP(UPPER(K68&N68),source_columns[],7,0),"") -> Идентификатор договора эскроу | N68: escrowid | V68: ="n308000046_"&IFERROR(VLOOKUP(D68,target_tables[],5,0),"<not found>") -> n308000046_agr_escrow | W68: -
A69: 590 | B69: Эскроу | C69: =IFERROR(VLOOKUP(D69,'Target tables'!A:B,2,0),"") -> Договор эскроу | D69: t_agr_escrow | E69: =IFERROR(VLOOKUP(D69&J69,'Target columns'!A:J,4,FALSE),"") -> DATE | F69: =IFERROR(VLOOKUP(D69&J69,'Target columns'!A:J,7,FALSE),"") -> No | G69: =IFERROR(VLOOKUP(D69&J69,'Target columns'!A:J,8,FALSE),"") -> No | H69: =IFERROR(VLOOKUP(D69&J69,'Target columns'!A:J,5,FALSE),"") -> NULL | I69: =IFERROR(VLOOKUP(D69&J69,'Target columns'!A:J,10,FALSE),"") -> Плановая дата ввода в эксплуатацию объекта строительства | J69: permission_explotation_plan_dt | K69: b3080000460002_escrow_legalgk_agreement_actual_dto | L69: =IFERROR(VLOOKUP(UPPER(K69&N69),source_columns[],4,0),"") | M69: =IFERROR(VLOOKUP(UPPER(K69&N69),source_columns[],7,0),"") | N69: Null | V69: ="n308000046_"&IFERROR(VLOOKUP(D69,target_tables[],5,0),"<not found>") -> n308000046_agr_escrow | W69: -
A70: 600 | B70: Эскроу | C70: =IFERROR(VLOOKUP(D70,'Target tables'!A:B,2,0),"") -> Договор эскроу | D70: t_agr_escrow | E70: =IFERROR(VLOOKUP(D70&J70,'Target columns'!A:J,4,FALSE),"") -> DECIMAL(26,4) | F70: =IFERROR(VLOOKUP(D70&J70,'Target columns'!A:J,7,FALSE),"") -> No | G70: =IFERROR(VLOOKUP(D70&J70,'Target columns'!A:J,8,FALSE),"") -> No | H70: =IFERROR(VLOOKUP(D70&J70,'Target columns'!A:J,5,FALSE),"") -> NULL | I70: =IFERROR(VLOOKUP(D70&J70,'Target columns'!A:J,10,FALSE),"") -> Сумма депонирования эскроу | J70: start_sum_crncy_amt | K70: b3080000460002_escrow_legalgk_agreement_actual_dto | L70: =IFERROR(VLOOKUP(UPPER(K70&N70),source_columns[],4,0),"") -> numeric(38 , 16) | M70: =IFERROR(VLOOKUP(UPPER(K70&N70),source_columns[],7,0),"") -> Сумма договора | N70: escrowamount_value | V70: ="n308000046_"&IFERROR(VLOOKUP(D70,target_tables[],5,0),"<not found>") -> n308000046_agr_escrow | W70: - | AJ70: В json максимальное значение - 10 в 15 степени
A71: 610 | B71: Эскроу | C71: =IFERROR(VLOOKUP(D71,'Target tables'!A:B,2,0),"") -> Договор эскроу | D71: t_agr_escrow | E71: =IFERROR(VLOOKUP(D71&J71,'Target columns'!A:J,4,FALSE),"") -> UUID | F71: =IFERROR(VLOOKUP(D71&J71,'Target columns'!A:J,7,FALSE),"") -> No | G71: =IFERROR(VLOOKUP(D71&J71,'Target columns'!A:J,8,FALSE),"") -> Yes | H71: =IFERROR(VLOOKUP(D71&J71,'Target columns'!A:J,5,FALSE),"") -> NULL | I71: =IFERROR(VLOOKUP(D71&J71,'Target columns'!A:J,10,FALSE),"") -> Идентификатор валюты | J71: crncy_id | K71: b3080000460002_escrow_legalgk_agreement_actual_dto | L71: =IFERROR(VLOOKUP(UPPER(K71&N71),source_columns[],4,0),"") -> uuid | M71: =IFERROR(VLOOKUP(UPPER(K71&N71),source_columns[],7,0),"") -> Валюта договора | N71: escrowamount_currency_uid | V71: ="n308000046_"&IFERROR(VLOOKUP(D71,target_tables[],5,0),"<not found>") -> n308000046_agr_escrow | W71: -
A72: 620 | B72: Эскроу | C72: =IFERROR(VLOOKUP(D72,'Target tables'!A:B,2,0),"") -> Договор эскроу | D72: t_agr_escrow | E72: =IFERROR(VLOOKUP(D72&J72,'Target columns'!A:J,4,FALSE),"") -> UUID | F72: =IFERROR(VLOOKUP(D72&J72,'Target columns'!A:J,7,FALSE),"") -> No | G72: =IFERROR(VLOOKUP(D72&J72,'Target columns'!A:J,8,FALSE),"") -> Yes | H72: =IFERROR(VLOOKUP(D72&J72,'Target columns'!A:J,5,FALSE),"") -> NULL | I72: =IFERROR(VLOOKUP(D72&J72,'Target columns'!A:J,10,FALSE),"") -> Идентификатор схемы | J72: escrow_scheme_id | K72: b3080000460002_escrow_legalgk_agreement_actual_dto | L72: =IFERROR(VLOOKUP(UPPER(K72&N72),source_columns[],4,0),"") -> uuid | M72: =IFERROR(VLOOKUP(UPPER(K72&N72),source_columns[],7,0),"") -> Код схемы распределения дохода | N72: profitscheme_uid | V72: ="n308000046_"&IFERROR(VLOOKUP(D72,target_tables[],5,0),"<not found>") -> n308000046_agr_escrow | W72: - | AJ72: Для эскроу ГК - это схема распределения дохода
A73: 630 | B73: Эскроу | C73: =IFERROR(VLOOKUP(D73,'Target tables'!A:B,2,0),"") -> Договор эскроу | D73: t_agr_escrow | E73: =IFERROR(VLOOKUP(D73&J73,'Target columns'!A:J,4,FALSE),"") -> DATE | F73: =IFERROR(VLOOKUP(D73&J73,'Target columns'!A:J,7,FALSE),"") -> No | G73: =IFERROR(VLOOKUP(D73&J73,'Target columns'!A:J,8,FALSE),"") -> No | H73: =IFERROR(VLOOKUP(D73&J73,'Target columns'!A:J,5,FALSE),"") -> NULL | I73: =IFERROR(VLOOKUP(D73&J73,'Target columns'!A:J,10,FALSE),"") -> Плановая дата окончания/Срок условного депонирования договора | J73: expiration_dt | K73: b3080000460002_escrow_legalgk_agreement_actual_dto | L73: =IFERROR(VLOOKUP(UPPER(K73&N73),source_columns[],4,0),"") -> date | M73: =IFERROR(VLOOKUP(UPPER(K73&N73),source_columns[],7,0),"") -> Дата истечения срока действия сделки эскроу | N73: expiredate | V73: ="n308000046_"&IFERROR(VLOOKUP(D73,target_tables[],5,0),"<not found>") -> n308000046_agr_escrow | W73: -
A74: 640 | B74: Эскроу | C74: =IFERROR(VLOOKUP(D74,'Target tables'!A:B,2,0),"") -> Договор эскроу | D74: t_agr_escrow | E74: =IFERROR(VLOOKUP(D74&J74,'Target columns'!A:J,4,FALSE),"") -> TEXT | F74: =IFERROR(VLOOKUP(D74&J74,'Target columns'!A:J,7,FALSE),"") -> No | G74: =IFERROR(VLOOKUP(D74&J74,'Target columns'!A:J,8,FALSE),"") -> No | H74: =IFERROR(VLOOKUP(D74&J74,'Target columns'!A:J,5,FALSE),"") -> NULL | I74: =IFERROR(VLOOKUP(D74&J74,'Target columns'!A:J,10,FALSE),"") -> Признак работы в рамках 214-ФЗ | J74: agr_214_fed_flag | K74: b3080000460002_escrow_legalgk_agreement_actual_dto | L74: =IFERROR(VLOOKUP(UPPER(K74&N74),source_columns[],4,0),"") | M74: =IFERROR(VLOOKUP(UPPER(K74&N74),source_columns[],7,0),"") | N74: N' | V74: ="n308000046_"&IFERROR(VLOOKUP(D74,target_tables[],5,0),"<not found>") -> n308000046_agr_escrow | W74: -
A75: 650 | B75: Эскроу | C75: =IFERROR(VLOOKUP(D75,'Target tables'!A:B,2,0),"") -> Таблица связей кредитного договора с договором эскроу | D75: t_agr_escrow_agr_cred | E75: =IFERROR(VLOOKUP(D75&J75,'Target columns'!A:J,4,FALSE),"") -> UUID | F75: =IFERROR(VLOOKUP(D75&J75,'Target columns'!A:J,7,FALSE),"") -> Yes | G75: =IFERROR(VLOOKUP(D75&J75,'Target columns'!A:J,8,FALSE),"") -> Yes | H75: =IFERROR(VLOOKUP(D75&J75,'Target columns'!A:J,5,FALSE),"") -> NOT NULL | I75: =IFERROR(VLOOKUP(D75&J75,'Target columns'!A:J,10,FALSE),"") -> ИД договора эскроу | J75: agr_escrow_id | K75: b3080000460002_escrow_legalgk_agreement_actual_dto | L75: =IFERROR(VLOOKUP(UPPER(K75&N75),source_columns[],4,0),"") -> uuid | M75: =IFERROR(VLOOKUP(UPPER(K75&N75),source_columns[],7,0),"") -> Идентификатор договора эскроу | N75: escrowid_uid | S75: depositorlegal_creditcontract_number is not null or depositorlegal_creditcontract_kulid is not null | V75: ="n308000046_"&IFERROR(VLOOKUP(D75,target_tables[],5,0),"<not found>") -> n308000046_agr_escrow_agr_cred | W75: Ключ | AF75: Снимок-история
A76: 660 | B76: Эскроу | C76: =IFERROR(VLOOKUP(D76,'Target tables'!A:B,2,0),"") -> Таблица связей кредитного договора с договором эскроу | D76: t_agr_escrow_agr_cred | E76: =IFERROR(VLOOKUP(D76&J76,'Target columns'!A:J,4,FALSE),"") -> UUID | F76: =IFERROR(VLOOKUP(D76&J76,'Target columns'!A:J,7,FALSE),"") -> No | G76: =IFERROR(VLOOKUP(D76&J76,'Target columns'!A:J,8,FALSE),"") -> Yes | H76: =IFERROR(VLOOKUP(D76&J76,'Target columns'!A:J,5,FALSE),"") -> NULL | I76: =IFERROR(VLOOKUP(D76&J76,'Target columns'!A:J,10,FALSE),"") -> ИД кредитного договора с застройщиком | J76: agr_cred_id | K76: b3080000460002_escrow_legalgk_agreement_actual_dto | L76: =IFERROR(VLOOKUP(UPPER(K76&N76),source_columns[],4,0),"") | M76: =IFERROR(VLOOKUP(UPPER(K76&N76),source_columns[],7,0),"") | N76: COALESCE( depositorlegal_creditcontract_kulid_uid ,depositorlegal_creditcontract_number_uid) | V76: ="n308000046_"&IFERROR(VLOOKUP(D76,target_tables[],5,0),"<not found>") -> n308000046_agr_escrow_agr_cred | W76: -
A77: 670 | B77: Эскроу | C77: =IFERROR(VLOOKUP(D77,'Target tables'!A:B,2,0),"") -> Таблица связей кредитного договора с договором эскроу | D77: t_agr_escrow_agr_cred | E77: =IFERROR(VLOOKUP(D77&J77,'Target columns'!A:J,4,FALSE),"") -> DATE | F77: =IFERROR(VLOOKUP(D77&J77,'Target columns'!A:J,7,FALSE),"") -> Yes | G77: =IFERROR(VLOOKUP(D77&J77,'Target columns'!A:J,8,FALSE),"") -> No | H77: =IFERROR(VLOOKUP(D77&J77,'Target columns'!A:J,5,FALSE),"") -> NOT NULL | I77: =IFERROR(VLOOKUP(D77&J77,'Target columns'!A:J,10,FALSE),"") -> Дата начала действия связи между кредитным договором и договором эскроу | J77: start_dt | K77: b3080000460002_escrow_legalgk_agreement_actual_dto | L77: =IFERROR(VLOOKUP(UPPER(K77&N77),source_columns[],4,0),"") | M77: =IFERROR(VLOOKUP(UPPER(K77&N77),source_columns[],7,0),"") | N77: cast(sys_date_create_or_update as date) | V77: ="n308000046_"&IFERROR(VLOOKUP(D77,target_tables[],5,0),"<not found>") -> n308000046_agr_escrow_agr_cred | W77: Начало
A78: 680 | B78: Эскроу | C78: =IFERROR(VLOOKUP(D78,'Target tables'!A:B,2,0),"") -> Таблица связей кредитного договора с договором эскроу | D78: t_agr_escrow_agr_cred | E78: =IFERROR(VLOOKUP(D78&J78,'Target columns'!A:J,4,FALSE),"") -> DATE | F78: =IFERROR(VLOOKUP(D78&J78,'Target columns'!A:J,7,FALSE),"") -> No | G78: =IFERROR(VLOOKUP(D78&J78,'Target columns'!A:J,8,FALSE),"") -> No | H78: =IFERROR(VLOOKUP(D78&J78,'Target columns'!A:J,5,FALSE),"") -> NULL | I78: =IFERROR(VLOOKUP(D78&J78,'Target columns'!A:J,10,FALSE),"") -> Дата окончания действия связи между кредитным договором и договором эскроу | J78: end_dt | K78: b3080000460002_escrow_legalgk_agreement_actual_dto | L78: =IFERROR(VLOOKUP(UPPER(K78&N78),source_columns[],4,0),"") | M78: =IFERROR(VLOOKUP(UPPER(K78&N78),source_columns[],7,0),"") | N78: cast('9999-12-31' as date) | V78: ="n308000046_"&IFERROR(VLOOKUP(D78,target_tables[],5,0),"<not found>") -> n308000046_agr_escrow_agr_cred | W78: Конец
A79: 690 | B79: Эскроу | C79: =IFERROR(VLOOKUP(D79,'Target tables'!A:B,2,0),"") -> Таблица связей контрагентов с договором эскроу | D79: t_agr_escrow_cust | E79: =IFERROR(VLOOKUP(D79&J79,'Target columns'!A:J,4,FALSE),"") -> UUID | F79: =IFERROR(VLOOKUP(D79&J79,'Target columns'!A:J,7,FALSE),"") -> Yes | G79: =IFERROR(VLOOKUP(D79&J79,'Target columns'!A:J,8,FALSE),"") -> Yes | H79: =IFERROR(VLOOKUP(D79&J79,'Target columns'!A:J,5,FALSE),"") -> NOT NULL | I79: =IFERROR(VLOOKUP(D79&J79,'Target columns'!A:J,10,FALSE),"") -> Идентификатор договора эскроу | J79: agr_escrow_id | K79: b3080000460002_escrow_legalgk_agreement_actual_dto | L79: =IFERROR(VLOOKUP(UPPER(K79&N79),source_columns[],4,0),"") -> uuid | M79: =IFERROR(VLOOKUP(UPPER(K79&N79),source_columns[],7,0),"") -> Идентификатор договора эскроу | N79: escrowid_uid | S79: depositorlegal_epkid is not null | V79: ="n308000046_"&IFERROR(VLOOKUP(D79,target_tables[],5,0),"<not found>") -> n308000046_agr_escrow_cust | W79: Ключ | AF79: Снимок-история
A80: 700 | B80: Эскроу | C80: =IFERROR(VLOOKUP(D80,'Target tables'!A:B,2,0),"") -> Таблица связей контрагентов с договором эскроу | D80: t_agr_escrow_cust | E80: =IFERROR(VLOOKUP(D80&J80,'Target columns'!A:J,4,FALSE),"") -> UUID | F80: =IFERROR(VLOOKUP(D80&J80,'Target columns'!A:J,7,FALSE),"") -> Yes | G80: =IFERROR(VLOOKUP(D80&J80,'Target columns'!A:J,8,FALSE),"") -> Yes | H80: =IFERROR(VLOOKUP(D80&J80,'Target columns'!A:J,5,FALSE),"") -> NOT NULL | I80: =IFERROR(VLOOKUP(D80&J80,'Target columns'!A:J,10,FALSE),"") -> Идентификатор контрагента | J80: cust_id | K80: b3080000460002_escrow_legalgk_agreement_actual_dto | L80: =IFERROR(VLOOKUP(UPPER(K80&N80),source_columns[],4,0),"") -> uuid | M80: =IFERROR(VLOOKUP(UPPER(K80&N80),source_columns[],7,0),"") -> ИД ЕПК депонента | N80: depositorlegal_epkid_uid | V80: ="n308000046_"&IFERROR(VLOOKUP(D80,target_tables[],5,0),"<not found>") -> n308000046_agr_escrow_cust | W80: -
A81: 710 | B81: Эскроу | C81: =IFERROR(VLOOKUP(D81,'Target tables'!A:B,2,0),"") -> Таблица связей контрагентов с договором эскроу | D81: t_agr_escrow_cust | E81: =IFERROR(VLOOKUP(D81&J81,'Target columns'!A:J,4,FALSE),"") -> DATE | F81: =IFERROR(VLOOKUP(D81&J81,'Target columns'!A:J,7,FALSE),"") -> Yes | G81: =IFERROR(VLOOKUP(D81&J81,'Target columns'!A:J,8,FALSE),"") -> No | H81: =IFERROR(VLOOKUP(D81&J81,'Target columns'!A:J,5,FALSE),"") -> NOT NULL | I81: =IFERROR(VLOOKUP(D81&J81,'Target columns'!A:J,10,FALSE),"") -> Дата начала действия | J81: start_dt | K81: b3080000460002_escrow_legalgk_agreement_actual_dto | L81: =IFERROR(VLOOKUP(UPPER(K81&N81),source_columns[],4,0),"") | M81: =IFERROR(VLOOKUP(UPPER(K81&N81),source_columns[],7,0),"") | N81: cast(sys_date_create_or_update as date) | V81: ="n308000046_"&IFERROR(VLOOKUP(D81,target_tables[],5,0),"<not found>") -> n308000046_agr_escrow_cust | W81: Начало | AJ81: select agr_escrow_cust_type_id from s_grnplm_as_t_didsd_308_db_dwh.t_agr_escrow_cust_type where agr_escrow_cust_type_cd = 'deponent'
A82: 720 | B82: Эскроу | C82: =IFERROR(VLOOKUP(D82,'Target tables'!A:B,2,0),"") -> Таблица связей контрагентов с договором эскроу | D82: t_agr_escrow_cust | E82: =IFERROR(VLOOKUP(D82&J82,'Target columns'!A:J,4,FALSE),"") -> DATE | F82: =IFERROR(VLOOKUP(D82&J82,'Target columns'!A:J,7,FALSE),"") -> No | G82: =IFERROR(VLOOKUP(D82&J82,'Target columns'!A:J,8,FALSE),"") -> No | H82: =IFERROR(VLOOKUP(D82&J82,'Target columns'!A:J,5,FALSE),"") -> NULL | I82: =IFERROR(VLOOKUP(D82&J82,'Target columns'!A:J,10,FALSE),"") -> Дата окончания действия | J82: end_dt | K82: b3080000460002_escrow_legalgk_agreement_actual_dto | L82: =IFERROR(VLOOKUP(UPPER(K82&N82),source_columns[],4,0),"") | M82: =IFERROR(VLOOKUP(UPPER(K82&N82),source_columns[],7,0),"") | N82: cast('9999-12-31' as date) | V82: ="n308000046_"&IFERROR(VLOOKUP(D82,target_tables[],5,0),"<not found>") -> n308000046_agr_escrow_cust | W82: Конец
A83: 730 | B83: Эскроу | C83: =IFERROR(VLOOKUP(D83,'Target tables'!A:B,2,0),"") -> Таблица связей контрагентов с договором эскроу | D83: t_agr_escrow_cust | E83: =IFERROR(VLOOKUP(D83&J83,'Target columns'!A:J,4,FALSE),"") -> UUID | F83: =IFERROR(VLOOKUP(D83&J83,'Target columns'!A:J,7,FALSE),"") -> Yes | G83: =IFERROR(VLOOKUP(D83&J83,'Target columns'!A:J,8,FALSE),"") -> Yes | H83: =IFERROR(VLOOKUP(D83&J83,'Target columns'!A:J,5,FALSE),"") -> NOT NULL | I83: =IFERROR(VLOOKUP(D83&J83,'Target columns'!A:J,10,FALSE),"") -> Роль клиента в договоре - ID | J83: agr_escrow_cust_type_id | K83: b3080000460002_escrow_legalgk_agreement_actual_dto | L83: =IFERROR(VLOOKUP(UPPER(K83&N83),source_columns[],4,0),"") | M83: =IFERROR(VLOOKUP(UPPER(K83&N83),source_columns[],7,0),"") | N83: 00000000-0000-0000-0000-0000fffffc16 -- Депонент | V83: ="n308000046_"&IFERROR(VLOOKUP(D83,target_tables[],5,0),"<not found>") -> n308000046_agr_escrow_cust | W83: Ключ
A84: 740 | B84: Эскроу | C84: =IFERROR(VLOOKUP(D84,'Target tables'!A:B,2,0),"") -> Таблица связей контрагентов с договором эскроу | D84: t_agr_escrow_cust | E84: =IFERROR(VLOOKUP(D84&J84,'Target columns'!A:J,4,FALSE),"") -> UUID | F84: =IFERROR(VLOOKUP(D84&J84,'Target columns'!A:J,7,FALSE),"") -> Yes | G84: =IFERROR(VLOOKUP(D84&J84,'Target columns'!A:J,8,FALSE),"") -> Yes | H84: =IFERROR(VLOOKUP(D84&J84,'Target columns'!A:J,5,FALSE),"") -> NOT NULL | I84: =IFERROR(VLOOKUP(D84&J84,'Target columns'!A:J,10,FALSE),"") -> Идентификатор договора эскроу | J84: agr_escrow_id | K84: b3080000460003_escrow_legalgk_beneficiariesindividual | L84: =IFERROR(VLOOKUP(UPPER(K84&N84),source_columns[],4,0),"") -> uuid | M84: =IFERROR(VLOOKUP(UPPER(K84&N84),source_columns[],7,0),"") -> Идентификатор договора эскроу | N84: escrowid_uid | S84: epkid_i is not null or beneficiariesindividual_uid is not null | V84: ="n308000046_"&IFERROR(VLOOKUP(D84,target_tables[],5,0),"<not found>") -> n308000046_agr_escrow_cust | W84: Ключ | AF84: Снимок-блочная история
A85: 750 | B85: Эскроу | C85: =IFERROR(VLOOKUP(D85,'Target tables'!A:B,2,0),"") -> Таблица связей контрагентов с договором эскроу | D85: t_agr_escrow_cust | E85: =IFERROR(VLOOKUP(D85&J85,'Target columns'!A:J,4,FALSE),"") -> UUID | F85: =IFERROR(VLOOKUP(D85&J85,'Target columns'!A:J,7,FALSE),"") -> Yes | G85: =IFERROR(VLOOKUP(D85&J85,'Target columns'!A:J,8,FALSE),"") -> Yes | H85: =IFERROR(VLOOKUP(D85&J85,'Target columns'!A:J,5,FALSE),"") -> NOT NULL | I85: =IFERROR(VLOOKUP(D85&J85,'Target columns'!A:J,10,FALSE),"") -> Идентификатор контрагента | J85: cust_id | K85: b3080000460003_escrow_legalgk_beneficiariesindividual | L85: =IFERROR(VLOOKUP(UPPER(K85&N85),source_columns[],4,0),"") | M85: =IFERROR(VLOOKUP(UPPER(K85&N85),source_columns[],7,0),"") | N85: coalesce(epkid_i_uid,beneficiariesindividual_uid) | V85: ="n308000046_"&IFERROR(VLOOKUP(D85,target_tables[],5,0),"<not found>") -> n308000046_agr_escrow_cust | W85: Ключ
A86: 760 | B86: Эскроу | C86: =IFERROR(VLOOKUP(D86,'Target tables'!A:B,2,0),"") -> Таблица связей контрагентов с договором эскроу | D86: t_agr_escrow_cust | E86: =IFERROR(VLOOKUP(D86&J86,'Target columns'!A:J,4,FALSE),"") -> DATE | F86: =IFERROR(VLOOKUP(D86&J86,'Target columns'!A:J,7,FALSE),"") -> Yes | G86: =IFERROR(VLOOKUP(D86&J86,'Target columns'!A:J,8,FALSE),"") -> No | H86: =IFERROR(VLOOKUP(D86&J86,'Target columns'!A:J,5,FALSE),"") -> NOT NULL | I86: =IFERROR(VLOOKUP(D86&J86,'Target columns'!A:J,10,FALSE),"") -> Дата начала действия | J86: start_dt | K86: b3080000460003_escrow_legalgk_beneficiariesindividual | L86: =IFERROR(VLOOKUP(UPPER(K86&N86),source_columns[],4,0),"") | M86: =IFERROR(VLOOKUP(UPPER(K86&N86),source_columns[],7,0),"") | N86: cast(sys_date_create_or_update as date) | V86: ="n308000046_"&IFERROR(VLOOKUP(D86,target_tables[],5,0),"<not found>") -> n308000046_agr_escrow_cust | W86: Начало
A87: 770 | B87: Эскроу | C87: =IFERROR(VLOOKUP(D87,'Target tables'!A:B,2,0),"") -> Таблица связей контрагентов с договором эскроу | D87: t_agr_escrow_cust | E87: =IFERROR(VLOOKUP(D87&J87,'Target columns'!A:J,4,FALSE),"") -> DATE | F87: =IFERROR(VLOOKUP(D87&J87,'Target columns'!A:J,7,FALSE),"") -> No | G87: =IFERROR(VLOOKUP(D87&J87,'Target columns'!A:J,8,FALSE),"") -> No | H87: =IFERROR(VLOOKUP(D87&J87,'Target columns'!A:J,5,FALSE),"") -> NULL | I87: =IFERROR(VLOOKUP(D87&J87,'Target columns'!A:J,10,FALSE),"") -> Дата окончания действия | J87: end_dt | K87: b3080000460003_escrow_legalgk_beneficiariesindividual | L87: =IFERROR(VLOOKUP(UPPER(K87&N87),source_columns[],4,0),"") | M87: =IFERROR(VLOOKUP(UPPER(K87&N87),source_columns[],7,0),"") | N87: cast('9999-12-31' as date) | V87: ="n308000046_"&IFERROR(VLOOKUP(D87,target_tables[],5,0),"<not found>") -> n308000046_agr_escrow_cust | W87: Конец | AJ87: select agr_escrow_cust_type_id from s_grnplm_as_t_didsd_308_db_dwh.t_agr_escrow_cust_type where agr_escrow_cust_type_cd = 'beneficiary'
A88: 780 | B88: Эскроу | C88: =IFERROR(VLOOKUP(D88,'Target tables'!A:B,2,0),"") -> Таблица связей контрагентов с договором эскроу | D88: t_agr_escrow_cust | E88: =IFERROR(VLOOKUP(D88&J88,'Target columns'!A:J,4,FALSE),"") -> UUID | F88: =IFERROR(VLOOKUP(D88&J88,'Target columns'!A:J,7,FALSE),"") -> Yes | G88: =IFERROR(VLOOKUP(D88&J88,'Target columns'!A:J,8,FALSE),"") -> Yes | H88: =IFERROR(VLOOKUP(D88&J88,'Target columns'!A:J,5,FALSE),"") -> NOT NULL | I88: =IFERROR(VLOOKUP(D88&J88,'Target columns'!A:J,10,FALSE),"") -> Роль клиента в договоре - ID | J88: agr_escrow_cust_type_id | K88: b3080000460003_escrow_legalgk_beneficiariesindividual | L88: =IFERROR(VLOOKUP(UPPER(K88&N88),source_columns[],4,0),"") | M88: =IFERROR(VLOOKUP(UPPER(K88&N88),source_columns[],7,0),"") | N88: 00000000-0000-0000-0000-0000fffffc17 -- Бенефициар | V88: ="n308000046_"&IFERROR(VLOOKUP(D88,target_tables[],5,0),"<not found>") -> n308000046_agr_escrow_cust | W88: Ключ
A89: 790 | B89: Эскроу | C89: =IFERROR(VLOOKUP(D89,'Target tables'!A:B,2,0),"") -> Таблица связей контрагентов с договором эскроу | D89: t_agr_escrow_cust | E89: =IFERROR(VLOOKUP(D89&J89,'Target columns'!A:J,4,FALSE),"") -> UUID | F89: =IFERROR(VLOOKUP(D89&J89,'Target columns'!A:J,7,FALSE),"") -> Yes | G89: =IFERROR(VLOOKUP(D89&J89,'Target columns'!A:J,8,FALSE),"") -> Yes | H89: =IFERROR(VLOOKUP(D89&J89,'Target columns'!A:J,5,FALSE),"") -> NOT NULL | I89: =IFERROR(VLOOKUP(D89&J89,'Target columns'!A:J,10,FALSE),"") -> Идентификатор договора эскроу | J89: agr_escrow_id | K89: b3080000460004_escrow_legalgk_beneficiarieslegal | L89: =IFERROR(VLOOKUP(UPPER(K89&N89),source_columns[],4,0),"") -> uuid | M89: =IFERROR(VLOOKUP(UPPER(K89&N89),source_columns[],7,0),"") -> Идентификатор договора эскроу | N89: escrowid_uid | S89: epkid_l is not null or beneficiarieslegal_uid is not null | V89: ="n308000046_"&IFERROR(VLOOKUP(D89,target_tables[],5,0),"<not found>") -> n308000046_agr_escrow_cust | W89: Ключ | AF89: Снимок-блочная история
A90: 800 | B90: Эскроу | C90: =IFERROR(VLOOKUP(D90,'Target tables'!A:B,2,0),"") -> Таблица связей контрагентов с договором эскроу | D90: t_agr_escrow_cust | E90: =IFERROR(VLOOKUP(D90&J90,'Target columns'!A:J,4,FALSE),"") -> UUID | F90: =IFERROR(VLOOKUP(D90&J90,'Target columns'!A:J,7,FALSE),"") -> Yes | G90: =IFERROR(VLOOKUP(D90&J90,'Target columns'!A:J,8,FALSE),"") -> Yes | H90: =IFERROR(VLOOKUP(D90&J90,'Target columns'!A:J,5,FALSE),"") -> NOT NULL | I90: =IFERROR(VLOOKUP(D90&J90,'Target columns'!A:J,10,FALSE),"") -> Идентификатор контрагента | J90: cust_id | K90: b3080000460004_escrow_legalgk_beneficiarieslegal | L90: =IFERROR(VLOOKUP(UPPER(K90&N90),source_columns[],4,0),"") | M90: =IFERROR(n89впр(UPPER(K90&N90),source_columns[],7,0),"") | N90: coalesce(epkid_l_uid, beneficiarieslegal_uid) | V90: ="n308000046_"&IFERROR(VLOOKUP(D90,target_tables[],5,0),"<not found>") -> n308000046_agr_escrow_cust | W90: Ключ
A91: 810 | B91: Эскроу | C91: =IFERROR(VLOOKUP(D91,'Target tables'!A:B,2,0),"") -> Таблица связей контрагентов с договором эскроу | D91: t_agr_escrow_cust | E91: =IFERROR(VLOOKUP(D91&J91,'Target columns'!A:J,4,FALSE),"") -> DATE | F91: =IFERROR(VLOOKUP(D91&J91,'Target columns'!A:J,7,FALSE),"") -> Yes | G91: =IFERROR(VLOOKUP(D91&J91,'Target columns'!A:J,8,FALSE),"") -> No | H91: =IFERROR(VLOOKUP(D91&J91,'Target columns'!A:J,5,FALSE),"") -> NOT NULL | I91: =IFERROR(VLOOKUP(D91&J91,'Target columns'!A:J,10,FALSE),"") -> Дата начала действия | J91: start_dt | K91: b3080000460004_escrow_legalgk_beneficiarieslegal | L91: =IFERROR(VLOOKUP(UPPER(K91&N91),source_columns[],4,0),"") | M91: =IFERROR(VLOOKUP(UPPER(K91&N91),source_columns[],7,0),"") | N91: cast(sys_date_create_or_update as date) | V91: ="n308000046_"&IFERROR(VLOOKUP(D91,target_tables[],5,0),"<not found>") -> n308000046_agr_escrow_cust | W91: Начало
A92: 820 | B92: Эскроу | C92: =IFERROR(VLOOKUP(D92,'Target tables'!A:B,2,0),"") -> Таблица связей контрагентов с договором эскроу | D92: t_agr_escrow_cust | E92: =IFERROR(VLOOKUP(D92&J92,'Target columns'!A:J,4,FALSE),"") -> DATE | F92: =IFERROR(VLOOKUP(D92&J92,'Target columns'!A:J,7,FALSE),"") -> No | G92: =IFERROR(VLOOKUP(D92&J92,'Target columns'!A:J,8,FALSE),"") -> No | H92: =IFERROR(VLOOKUP(D92&J92,'Target columns'!A:J,5,FALSE),"") -> NULL | I92: =IFERROR(VLOOKUP(D92&J92,'Target columns'!A:J,10,FALSE),"") -> Дата окончания действия | J92: end_dt | K92: b3080000460004_escrow_legalgk_beneficiarieslegal | L92: =IFERROR(VLOOKUP(UPPER(K92&N92),source_columns[],4,0),"") | M92: =IFERROR(VLOOKUP(UPPER(K92&N92),source_columns[],7,0),"") | N92: cast('9999-12-31' as date) | V92: ="n308000046_"&IFERROR(VLOOKUP(D92,target_tables[],5,0),"<not found>") -> n308000046_agr_escrow_cust | W92: Конец | AJ92: select agr_escrow_cust_type_id from s_grnplm_as_t_didsd_308_db_dwh.t_agr_escrow_cust_type where agr_escrow_cust_type_cd = 'beneficiary'
A93: 830 | B93: Эскроу | C93: =IFERROR(VLOOKUP(D93,'Target tables'!A:B,2,0),"") -> Таблица связей контрагентов с договором эскроу | D93: t_agr_escrow_cust | E93: =IFERROR(VLOOKUP(D93&J93,'Target columns'!A:J,4,FALSE),"") -> UUID | F93: =IFERROR(VLOOKUP(D93&J93,'Target columns'!A:J,7,FALSE),"") -> Yes | G93: =IFERROR(VLOOKUP(D93&J93,'Target columns'!A:J,8,FALSE),"") -> Yes | H93: =IFERROR(VLOOKUP(D93&J93,'Target columns'!A:J,5,FALSE),"") -> NOT NULL | I93: =IFERROR(VLOOKUP(D93&J93,'Target columns'!A:J,10,FALSE),"") -> Роль клиента в договоре - ID | J93: agr_escrow_cust_type_id | K93: b3080000460004_escrow_legalgk_beneficiarieslegal | L93: =IFERROR(VLOOKUP(UPPER(K93&N93),source_columns[],4,0),"") | M93: =IFERROR(VLOOKUP(UPPER(K93&N93),source_columns[],7,0),"") | N93: 00000000-0000-0000-0000-0000fffffc17 -- Бенефициар | V93: ="n308000046_"&IFERROR(VLOOKUP(D93,target_tables[],5,0),"<not found>") -> n308000046_agr_escrow_cust | W93: Ключ
A94: 840 | B94: Эскроу | C94: =IFERROR(VLOOKUP(D94,'Target tables'!A:B,2,0),"") -> Таблица связей договора эскроу со справочником оргструктуры | D94: t_agr_escrow_int_org | E94: =IFERROR(VLOOKUP(D94&J94,'Target columns'!A:J,4,FALSE),"") -> UUID | F94: =IFERROR(VLOOKUP(D94&J94,'Target columns'!A:J,7,FALSE),"") -> Yes | G94: =IFERROR(VLOOKUP(D94&J94,'Target columns'!A:J,8,FALSE),"") -> Yes | H94: =IFERROR(VLOOKUP(D94&J94,'Target columns'!A:J,5,FALSE),"") -> NOT NULL | I94: =IFERROR(VLOOKUP(D94&J94,'Target columns'!A:J,10,FALSE),"") -> Идентификатор договора | J94: agr_escrow_id | K94: b3080000460002_escrow_legalgk_agreement_actual_dto | L94: =IFERROR(VLOOKUP(UPPER(K94&N94),source_columns[],4,0),"") -> uuid | M94: =IFERROR(VLOOKUP(UPPER(K94&N94),source_columns[],7,0),"") -> Идентификатор договора эскроу | N94: escrowid_uid | S94: escrowbankregionaloffice is not null or beneficiaryBankBranch is not null or deponentBankBranch is not null | V94: ="n308000046_"&IFERROR(VLOOKUP(D94,target_tables[],5,0),"<not found>") -> n308000046_agr_escrow_int_org | W94: Ключ | AF94: Снимок-история
A95: 850 | B95: Эскроу | C95: =IFERROR(VLOOKUP(D95,'Target tables'!A:B,2,0),"") -> Таблица связей договора эскроу со справочником оргструктуры | D95: t_agr_escrow_int_org | E95: =IFERROR(VLOOKUP(D95&J95,'Target columns'!A:J,4,FALSE),"") -> UUID | F95: =IFERROR(VLOOKUP(D95&J95,'Target columns'!A:J,7,FALSE),"") -> No | G95: =IFERROR(VLOOKUP(D95&J95,'Target columns'!A:J,8,FALSE),"") -> Yes | H95: =IFERROR(VLOOKUP(D95&J95,'Target columns'!A:J,5,FALSE),"") -> NULL | I95: =IFERROR(VLOOKUP(D95&J95,'Target columns'!A:J,10,FALSE),"") -> Код ВСП ведения договора | J95: int_org_id | K95: b3080000460002_escrow_legalgk_agreement_actual_dto | L95: =IFERROR(VLOOKUP(UPPER(K95&N95),source_columns[],4,0),"") -> uuid | M95: =IFERROR(VLOOKUP(UPPER(K95&N95),source_columns[],7,0),"") -> Терр. Структура по балансу /Договора | N95: escrowbankregionaloffice_uid | V95: ="n308000046_"&IFERROR(VLOOKUP(D95,target_tables[],5,0),"<not found>") -> n308000046_agr_escrow_int_org | W95: - | AJ95: ТБ обязательно должен быть заполнено, иначе функция РДМ не верно расспарсит терр структуру
A96: 860 | B96: Эскроу | C96: =IFERROR(VLOOKUP(D96,'Target tables'!A:B,2,0),"") -> Таблица связей договора эскроу со справочником оргструктуры | D96: t_agr_escrow_int_org | E96: =IFERROR(VLOOKUP(D96&J96,'Target columns'!A:J,4,FALSE),"") -> UUID | F96: =IFERROR(VLOOKUP(D96&J96,'Target columns'!A:J,7,FALSE),"") -> No | G96: =IFERROR(VLOOKUP(D96&J96,'Target columns'!A:J,8,FALSE),"") -> Yes | H96: =IFERROR(VLOOKUP(D96&J96,'Target columns'!A:J,5,FALSE),"") -> NULL | I96: =IFERROR(VLOOKUP(D96&J96,'Target columns'!A:J,10,FALSE),"") -> Код ВСП открытия счета бенефициара | J96: ben_int_org_id | K96: b3080000460002_escrow_legalgk_agreement_actual_dto | L96: =IFERROR(VLOOKUP(UPPER(K96&N96),source_columns[],4,0),"") -> uuid | M96: =IFERROR(VLOOKUP(UPPER(K96&N96),source_columns[],7,0),"") -> Терр структура бенефициара по схеме распределения дохода / отчетность | N96: beneficiaryBank_uid | V96: ="n308000046_"&IFERROR(VLOOKUP(D96,target_tables[],5,0),"<not found>") -> n308000046_agr_escrow_int_org | W96: -
A97: 870 | B97: Эскроу | C97: =IFERROR(VLOOKUP(D97,'Target tables'!A:B,2,0),"") -> Таблица связей договора эскроу со справочником оргструктуры | D97: t_agr_escrow_int_org | E97: =IFERROR(VLOOKUP(D97&J97,'Target columns'!A:J,4,FALSE),"") -> UUID | F97: =IFERROR(VLOOKUP(D97&J97,'Target columns'!A:J,7,FALSE),"") -> No | G97: =IFERROR(VLOOKUP(D97&J97,'Target columns'!A:J,8,FALSE),"") -> Yes | H97: =IFERROR(VLOOKUP(D97&J97,'Target columns'!A:J,5,FALSE),"") -> NULL | I97: =IFERROR(VLOOKUP(D97&J97,'Target columns'!A:J,10,FALSE),"") -> Код ВСП открытия счета депонента | J97: dep_int_org_id | K97: b3080000460002_escrow_legalgk_agreement_actual_dto | L97: =IFERROR(VLOOKUP(UPPER(K97&N97),source_columns[],4,0),"") -> uuid | M97: =IFERROR(VLOOKUP(UPPER(K97&N97),source_columns[],7,0),"") -> Терр структура депонента по схеме распределения дохода / отчетность | N97: deponentBank_uid | V97: ="n308000046_"&IFERROR(VLOOKUP(D97,target_tables[],5,0),"<not found>") -> n308000046_agr_escrow_int_org | W97: -
A98: 880 | B98: Эскроу | C98: =IFERROR(VLOOKUP(D98,'Target tables'!A:B,2,0),"") -> Таблица связей договора эскроу со справочником оргструктуры | D98: t_agr_escrow_int_org | E98: =IFERROR(VLOOKUP(D98&J98,'Target columns'!A:J,4,FALSE),"") -> DATE | F98: =IFERROR(VLOOKUP(D98&J98,'Target columns'!A:J,7,FALSE),"") -> Yes | G98: =IFERROR(VLOOKUP(D98&J98,'Target columns'!A:J,8,FALSE),"") -> No | H98: =IFERROR(VLOOKUP(D98&J98,'Target columns'!A:J,5,FALSE),"") -> NOT NULL | I98: =IFERROR(VLOOKUP(D98&J98,'Target columns'!A:J,10,FALSE),"") -> Дата начала действия связи | J98: start_dt | K98: b3080000460002_escrow_legalgk_agreement_actual_dto | N98: cast(sys_date_create_or_update as date) | V98: ="n308000046_"&IFERROR(VLOOKUP(D98,target_tables[],5,0),"<not found>") -> n308000046_agr_escrow_int_org | W98: Начало
A99: 890 | B99: Эскроу | C99: =IFERROR(VLOOKUP(D99,'Target tables'!A:B,2,0),"") -> Таблица связей договора эскроу со справочником оргструктуры | D99: t_agr_escrow_int_org | E99: =IFERROR(VLOOKUP(D99&J99,'Target columns'!A:J,4,FALSE),"") -> DATE | F99: =IFERROR(VLOOKUP(D99&J99,'Target columns'!A:J,7,FALSE),"") -> No | G99: =IFERROR(VLOOKUP(D99&J99,'Target columns'!A:J,8,FALSE),"") -> No | H99: =IFERROR(VLOOKUP(D99&J99,'Target columns'!A:J,5,FALSE),"") -> NULL | I99: =IFERROR(VLOOKUP(D99&J99,'Target columns'!A:J,10,FALSE),"") -> Дата окончания действия связи | J99: end_dt | K99: b3080000460002_escrow_legalgk_agreement_actual_dto | L99: =IFERROR(VLOOKUP(UPPER(K99&N99),source_columns[],4,0),"") | M99: =IFERROR(VLOOKUP(UPPER(K99&N99),source_columns[],7,0),"") | N99: cast('9999-12-31' as date) | V99: ="n308000046_"&IFERROR(VLOOKUP(D99,target_tables[],5,0),"<not found>") -> n308000046_agr_escrow_int_org | W99: Конец
A100: 790 | B100: Эскроу, ГС, Аккредитив, УПФ | C100: =IFERROR(VLOOKUP(D100,'Target tables'!A:B,2,0),"") -> Тип операции | D100: t_optn_type | E100: =IFERROR(VLOOKUP(D100&J100,'Target columns'!A:J,4,FALSE),"") -> UUID | F100: =IFERROR(VLOOKUP(D100&J100,'Target columns'!A:J,7,FALSE),"") -> Yes | G100: =IFERROR(VLOOKUP(D100&J100,'Target columns'!A:J,8,FALSE),"") -> No | H100: =IFERROR(VLOOKUP(D100&J100,'Target columns'!A:J,5,FALSE),"") -> NOT NULL | I100: =IFERROR(VLOOKUP(D100&J100,'Target columns'!A:J,10,FALSE),"") -> Уникальный идентификатор типа операции | J100: optn_type_id | K100: ETL | L100: =IFERROR(VLOOKUP(UPPER(K100&N100),source_columns[],4,0),"") | M100: =IFERROR(VLOOKUP(UPPER(K100&N100),source_columns[],7,0),"") | N100: processCode_uid | S100: select * from ( select processCode_uid, processCode, row_number() OVER (PARTITION BY processCode ORDER BY sys_date_create_or_update DESC) AS rn from b3080000460006_payments_2_0_posting_dto where processCode is not null and deleted = 'N' ) a where a.rn = 1 | V100: ="n308000046_"&IFERROR(VLOOKUP(D100,target_tables[],5,0),"<not found>") -> n308000046_optn_type | W100: Ключ | AF100: Снимок-снимок
A101: 800 | B101: Эскроу, ГС, Аккредитив, УПФ | C101: =IFERROR(VLOOKUP(D101,'Target tables'!A:B,2,0),"") -> Тип операции | D101: t_optn_type | E101: =IFERROR(VLOOKUP(D101&J101,'Target columns'!A:J,4,FALSE),"") -> TEXT | F101: =IFERROR(VLOOKUP(D101&J101,'Target columns'!A:J,7,FALSE),"") -> No | G101: =IFERROR(VLOOKUP(D101&J101,'Target columns'!A:J,8,FALSE),"") -> No | H101: =IFERROR(VLOOKUP(D101&J101,'Target columns'!A:J,5,FALSE),"") -> NULL | I101: =IFERROR(VLOOKUP(D101&J101,'Target columns'!A:J,10,FALSE),"") -> Код типа операции | J101: optn_type_cd | K101: ETL | L101: =IFERROR(VLOOKUP(UPPER(K101&N101),source_columns[],4,0),"") | M101: Код типа операции | N101: processCode | V101: ="n308000046_"&IFERROR(VLOOKUP(D101,target_tables[],5,0),"<not found>") -> n308000046_optn_type | W101: -
...

Sheet Source columns
D1: =COLUMN() -> 4 | E1: =COLUMN() -> 5 | F1: =COLUMN() -> 6 | G1: =COLUMN() -> 7 | J1: Проверка соответствия типов S2T
A2: Seek | B2: Название таблицы STAGE | C2: Название поля | D2: Тип поля | E2: Первичный ключ | F2: NULL? | G2: Описание поля | H2: Описание таблицы | I2: Опции проекта | J2: Seek | K2: Тип поля
A3: =source_columns[[#This Row],[Название таблицы STAGE]]&source_columns[[#This Row],[Название поля]] -> b3080000460001_escrow_legal214_agreement_actual_dtoescrowId_agreement | B3: b3080000460001_escrow_legal214_agreement_actual_dto | C3: escrowId_agreement | D3: text | E3: YES | F3: NOT NULL | G3: Идентификатор договора эскроу
A4: =source_columns[[#This Row],[Название таблицы STAGE]]&source_columns[[#This Row],[Название поля]] -> b3080000460001_escrow_legal214_agreement_actual_dtoescrowId_agreement_uid | B4: b3080000460001_escrow_legal214_agreement_actual_dto | C4: escrowId_agreement_uid | D4: uuid | E4: YES | F4: NOT NULL | G4: Идентификатор договора эскроу
A5: =source_columns[[#This Row],[Название таблицы STAGE]]&source_columns[[#This Row],[Название поля]] -> b3080000460001_escrow_legal214_agreement_actual_dtoopenDate_agreement | B5: b3080000460001_escrow_legal214_agreement_actual_dto | C5: openDate_agreement | D5: date | E5: NO | F5: NULL | G5: Дата открытия договора эскроу
A6: =source_columns[[#This Row],[Название таблицы STAGE]]&source_columns[[#This Row],[Название поля]] -> b3080000460001_escrow_legal214_agreement_actual_dtocloseDate_agreement | B6: b3080000460001_escrow_legal214_agreement_actual_dto | C6: closeDate_agreement | D6: date | E6: NO | F6: NULL | G6: Дата закрытия договора эскроу
A7: =source_columns[[#This Row],[Название таблицы STAGE]]&source_columns[[#This Row],[Название поля]] -> b3080000460001_escrow_legal214_agreement_actual_dtoreference_agreement | B7: b3080000460001_escrow_legal214_agreement_actual_dto | C7: reference_agreement | D7: text | E7: NO | F7: NULL | G7: Номер договора
A8: =source_columns[[#This Row],[Название таблицы STAGE]]&source_columns[[#This Row],[Название поля]] -> b3080000460001_escrow_legal214_agreement_actual_dtolegalEpkId_beneficiary | B8: b3080000460001_escrow_legal214_agreement_actual_dto | C8: legalEpkId_beneficiary | D8: text | E8: NO | F8: NULL | G8: ЕПК id юр.лица бенефициара
A9: =source_columns[[#This Row],[Название таблицы STAGE]]&source_columns[[#This Row],[Название поля]] -> b3080000460001_escrow_legal214_agreement_actual_dtolegalEpkId_beneficiary_uid | B9: b3080000460001_escrow_legal214_agreement_actual_dto | C9: legalEpkId_beneficiary_uid | D9: uuid | E9: NO | F9: NULL | G9: ЕПК id юр.лица бенефициара
A10: =source_columns[[#This Row],[Название таблицы STAGE]]&source_columns[[#This Row],[Название поля]] -> b3080000460001_escrow_legal214_agreement_actual_dtoestateObject_ExpireDate_agreementObject | B10: b3080000460001_escrow_legal214_agreement_actual_dto | C10: estateObject_ExpireDate_agreementObject | D10: date | E10: NO | F10: NULL | G10: Срок депонирования объекта
A11: =source_columns[[#This Row],[Название таблицы STAGE]]&source_columns[[#This Row],[Название поля]] -> b3080000460001_escrow_legal214_agreement_actual_dtorateSubsidyScheme_agreement | B11: b3080000460001_escrow_legal214_agreement_actual_dto | C11: rateSubsidyScheme_agreement | D11: text | E11: NO | F11: NULL | G11: Схема субсидирования
A12: =source_columns[[#This Row],[Название таблицы STAGE]]&source_columns[[#This Row],[Название поля]] -> b3080000460001_escrow_legal214_agreement_actual_dtorateSubsidyScheme_agreement_uid | B12: b3080000460001_escrow_legal214_agreement_actual_dto | C12: rateSubsidyScheme_agreement_uid | D12: uuid | E12: NO | F12: NULL | G12: Схема субсидирования
A13: =source_columns[[#This Row],[Название таблицы STAGE]]&source_columns[[#This Row],[Название поля]] -> b3080000460001_escrow_legal214_agreement_actual_dtostatus_agreement | B13: b3080000460001_escrow_legal214_agreement_actual_dto | C13: status_agreement | D13: text | E13: NO | F13: NULL | G13: Статус договора эскроу
A14: =source_columns[[#This Row],[Название таблицы STAGE]]&source_columns[[#This Row],[Название поля]] -> b3080000460001_escrow_legal214_agreement_actual_dtolastModifiedDate_agreement | B14: b3080000460001_escrow_legal214_agreement_actual_dto | C14: lastModifiedDate_agreement | D14: date | E14: NO | F14: NULL | G14: Дата и время последнего обновления
... A46: =source_columns[[#This Row],[Название таблицы STAGE]]&source_columns[[#This Row],[Название поля]] -> b3080000460001_escrow_legal214_agreement_actual_dtosys_date_create_or_update | B46: b3080000460001_escrow_legal214_agreement_actual_dto | C46: sys_date_create_or_update | D46: timestamp | E46: NO | F46: NULL | G46: Дата и время последнего изменения
A47: =source_columns[[#This Row],[Название таблицы STAGE]]&source_columns[[#This Row],[Название поля]] -> b3080000460001_escrow_legal214_agreement_actual_dtodeleted | B47: b3080000460001_escrow_legal214_agreement_actual_dto | C47: deleted | D47: text | E47: NO | F47: NULL | G47: Признак удаления | I47: case when deleted = true then 'y' else 'n'
A48: =source_columns[[#This Row],[Название таблицы STAGE]]&source_columns[[#This Row],[Название поля]] -> b3080000460002_escrow_legalgk_agreement_actual_dtobeneficiarybankregionalunit | B48: b3080000460002_escrow_legalgk_agreement_actual_dto | C48: beneficiarybankregionalunit | D48: text | E48: NO | F48: NULL | G48: ОСБ бенефициара по схеме распределения дохода / отчетность
A49: =source_columns[[#This Row],[Название таблицы STAGE]]&source_columns[[#This Row],[Название поля]] -> b3080000460002_escrow_legalgk_agreement_actual_dtobeneficiaryBankBranch | B49: b3080000460002_escrow_legalgk_agreement_actual_dto | C49: beneficiaryBankBranch | D49: text | E49: NO | F49: NULL | G49: ТБ бенефициара по схеме распределения дохода / отчетность
A50: =source_columns[[#This Row],[Название таблицы STAGE]]&source_columns[[#This Row],[Название поля]] -> b3080000460002_escrow_legalgk_agreement_actual_dtobeneficiaryBank_uid | B50: b3080000460002_escrow_legalgk_agreement_actual_dto | C50: beneficiaryBank_uid | D50: uuid | E50: NO | F50: NULL | G50: Терр структура бенефициара по схеме распределения дохода / отчетность | H50: Составной( beneficiaryBankBranch + beneficiarybankregionalunit)
A51: =source_columns[[#This Row],[Название таблицы STAGE]]&source_columns[[#This Row],[Название поля]] -> b3080000460002_escrow_legalgk_agreement_actual_dtodeponentBankRegionalUnit | B51: b3080000460002_escrow_legalgk_agreement_actual_dto | C51: deponentBankRegionalUnit | D51: text | E51: NO | F51: NULL | G51: ОСБ депонента по схеме распределения дохода / отчетность
A52: =source_columns[[#This Row],[Название таблицы STAGE]]&source_columns[[#This Row],[Название поля]] -> b3080000460002_escrow_legalgk_agreement_actual_dtodeponentBankBranch | B52: b3080000460002_escrow_legalgk_agreement_actual_dto | C52: deponentBankBranch | D52: text | E52: NO | F52: NULL | G52: ТБ депонента по схеме распределения дохода / отчетность
A53: =source_columns[[#This Row],[Название таблицы STAGE]]&source_columns[[#This Row],[Название поля]] -> b3080000460002_escrow_legalgk_agreement_actual_dtodeponentBank_uid | B53: b3080000460002_escrow_legalgk_agreement_actual_dto | C53: deponentBank_uid | D53: uuid | E53: NO | F53: NULL | G53: Терр структура депонента по схеме распределения дохода / отчетность | H53: Составной( deponentBankBranch + deponentBankRegionalUnit)
A54: =source_columns[[#This Row],[Название таблицы STAGE]]&source_columns[[#This Row],[Название поля]] -> b3080000460002_escrow_legalgk_agreement_actual_dtoclosedate | B54: b3080000460002_escrow_legalgk_agreement_actual_dto | C54: closedate | D54: date | E54: NO | F54: NULL | G54: Дата закрытия договора эскроу
A55: =source_columns[[#This Row],[Название таблицы STAGE]]&source_columns[[#This Row],[Название поля]] -> b3080000460002_escrow_legalgk_agreement_actual_dtoconclusiondate | B55: b3080000460002_escrow_legalgk_agreement_actual_dto | C55: conclusiondate | D55: date | E55: NO | F55: NULL | G55: Дата открытия договора эскроу
A56: =source_columns[[#This Row],[Название таблицы STAGE]]&source_columns[[#This Row],[Название поля]] -> b3080000460002_escrow_legalgk_agreement_actual_dtodeleted | B56: b3080000460002_escrow_legalgk_agreement_actual_dto | C56: deleted | D56: boolean | E56: NO | F56: NULL | G56: Признак удаления | I56: case when deleted = true then 'Y' else 'N'
A57: =source_columns[[#This Row],[Название таблицы STAGE]]&source_columns[[#This Row],[Название поля]] -> b3080000460002_escrow_legalgk_agreement_actual_dtodepositWithdrawalDate | B57: b3080000460002_escrow_legalgk_agreement_actual_dto | C57: depositWithdrawalDate | D57: date | E57: NO | F57: NULL | G57: Срок депонированной суммы
A58: =source_columns[[#This Row],[Название таблицы STAGE]]&source_columns[[#This Row],[Название поля]] -> b3080000460002_escrow_legalgk_agreement_actual_dtodepositorlegal_creditcontract_date | B58: b3080000460002_escrow_legalgk_agreement_actual_dto | C58: depositorlegal_creditcontract_date | D58: date | E58: NO | F58: NULL | G58: Дата кредитного договора у депонента
A59: =source_columns[[#This Row],[Название таблицы STAGE]]&source_columns[[#This Row],[Название поля]] -> b3080000460002_escrow_legalgk_agreement_actual_dtodepositorlegal_creditcontract_eks | B59: b3080000460002_escrow_legalgk_agreement_actual_dto | C59: depositorlegal_creditcontract_eks | D59: text | E59: NO | F59: NULL | G59: ИД кредитного договора в ЕКС у депонента
A60: =source_columns[[#This Row],[Название таблицы STAGE]]&source_columns[[#This Row],[Название поля]] -> b3080000460002_escrow_legalgk_agreement_actual_dtodepositorlegal_creditcontract_kulid | B60: b3080000460002_escrow_legalgk_agreement_actual_dto | C60: depositorlegal_creditcontract_kulid | D60: text | E60: NO | F60: NULL | G60: ИД ППРБ.КЮЛ у депонента
A61: =source_columns[[#This Row],[Название таблицы STAGE]]&source_columns[[#This Row],[Название поля]] -> b3080000460002_escrow_legalgk_agreement_actual_dtodepositorlegal_creditcontract_kulid_uid | B61: b3080000460002_escrow_legalgk_agreement_actual_dto | C61: depositorlegal_creditcontract_kulid_uid | D61: uuid | E61: NO | F61: NULL | G61: ИД ППРБ.КЮЛ у депонента
A62: =source_columns[[#This Row],[Название таблицы STAGE]]&source_columns[[#This Row],[Название поля]] -> b3080000460002_escrow_legalgk_agreement_actual_dtodepositorlegal_creditcontract_number | B62: b3080000460002_escrow_legalgk_agreement_actual_dto | C62: depositorlegal_creditcontract_number | D62: text | E62: NO | F62: NULL | G62: Номер кредитного договора у депонента
A63: =source_columns[[#This Row],[Название таблицы STAGE]]&source_columns[[#This Row],[Название поля]] -> b3080000460002_escrow_legalgk_agreement_actual_dtodepositorlegal_creditcontract_number_uid | B63: b3080000460002_escrow_legalgk_agreement_actual_dto | C63: depositorlegal_creditcontract_number_uid | D63: uuid | E63: NO | F63: NULL | G63: Номер кредитного договора у депонента
A64: =source_columns[[#This Row],[Название таблицы STAGE]]&source_columns[[#This Row],[Название поля]] -> b3080000460002_escrow_legalgk_agreement_actual_dtodepositorlegal_epkid | B64: b3080000460002_escrow_legalgk_agreement_actual_dto | C64: depositorlegal_epkid | D64: text | E64: NO | F64: NULL | G64: ИД ЕПК депонента
A65: =source_columns[[#This Row],[Название таблицы STAGE]]&source_columns[[#This Row],[Название поля]] -> b3080000460002_escrow_legalgk_agreement_actual_dtodepositorlegal_epkid_uid | B65: b3080000460002_escrow_legalgk_agreement_actual_dto | C65: depositorlegal_epkid_uid | D65: uuid | E65: NO | F65: NULL | G65: ИД ЕПК депонента
A66: =source_columns[[#This Row],[Название таблицы STAGE]]&source_columns[[#This Row],[Название поля]] -> b3080000460002_escrow_legalgk_agreement_actual_dtoescrowamount_currency | B66: b3080000460002_escrow_legalgk_agreement_actual_dto | C66: escrowamount_currency | D66: text | E66: NO | F66: NULL | G66: Валюта договора
A67: =source_columns[[#This Row],[Название таблицы STAGE]]&source_columns[[#This Row],[Название поля]] -> b3080000460002_escrow_legalgk_agreement_actual_dtoescrowamount_currency_uid | B67: b3080000460002_escrow_legalgk_agreement_actual_dto | C67: escrowamount_currency_uid | D67: uuid | E67: NO | F67: NULL | G67: Валюта договора
A68: =source_columns[[#This Row],[Название таблицы STAGE]]&source_columns[[#This Row],[Название поля]] -> b3080000460002_escrow_legalgk_agreement_actual_dtoescrowamount_value | B68: b3080000460002_escrow_legalgk_agreement_actual_dto | C68: escrowamount_value | D68: numeric(38 , 16) | E68: NO | F68: NULL | G68: Сумма договора
... A87: =source_columns[[#This Row],[Название таблицы STAGE]]&source_columns[[#This Row],[Название поля]] -> b3080000460003_escrow_legalgk_beneficiariesindividualdateofbirth | B87: b3080000460003_escrow_legalgk_beneficiariesindividual | C87: dateofbirth | D87: text | E87: NO | F87: NULL | G87: Дата рождения
A88: =source_columns[[#This Row],[Название таблицы STAGE]]&source_columns[[#This Row],[Название поля]] -> b3080000460003_escrow_legalgk_beneficiariesindividualdeleted | B88: b3080000460003_escrow_legalgk_beneficiariesindividual | C88: deleted | D88: boolean | E88: NO | F88: NULL | G88: Признак удаления | I88: case when deleted = true then 'Y' else 'N'
A89: =source_columns[[#This Row],[Название таблицы STAGE]]&source_columns[[#This Row],[Название поля]] -> b3080000460003_escrow_legalgk_beneficiariesindividualepkid_i | B89: b3080000460003_escrow_legalgk_beneficiariesindividual | C89: epkid_i | D89: text | E89: NO | F89: NULL | G89: ИД ЕПК бенефициара ФЛ
A90: =source_columns[[#This Row],[Название таблицы STAGE]]&source_columns[[#This Row],[Название поля]] -> b3080000460003_escrow_legalgk_beneficiariesindividualepkid_i_uid | B90: b3080000460003_escrow_legalgk_beneficiariesindividual | C90: epkid_i_uid | D90: uuid | E90: NO | F90: NULL | G90: ИД ЕПК бенефициара ФЛ
A91: =source_columns[[#This Row],[Название таблицы STAGE]]&source_columns[[#This Row],[Название поля]] -> b3080000460003_escrow_legalgk_beneficiariesindividualescrowid | B91: b3080000460003_escrow_legalgk_beneficiariesindividual | C91: escrowid | D91: text | E91: YES | F91: NULL | G91: Идентификатор договора эскроу
A92: =source_columns[[#This Row],[Название таблицы STAGE]]&source_columns[[#This Row],[Название поля]] -> b3080000460003_escrow_legalgk_beneficiariesindividualescrowid_uid | B92: b3080000460003_escrow_legalgk_beneficiariesindividual | C92: escrowid_uid | D92: uuid | E92: YES | F92: NULL | G92: Идентификатор договора эскроу
A93: =source_columns[[#This Row],[Название таблицы STAGE]]&source_columns[[#This Row],[Название поля]] -> b3080000460003_escrow_legalgk_beneficiariesindividualfirstname | B93: b3080000460003_escrow_legalgk_beneficiariesindividual | C93: firstname | D93: text | E93: NO | F93: NULL | G93: Имя бенефициара ФЛ
A94: =source_columns[[#This Row],[Название таблицы STAGE]]&source_columns[[#This Row],[Название поля]] -> b3080000460003_escrow_legalgk_beneficiariesindividualid | B94: b3080000460003_escrow_legalgk_beneficiariesindividual | C94: id | D94: bigint | E94: NO | F94: NOT NULL | G94: ID записи
A95: =source_columns[[#This Row],[Название таблицы STAGE]]&source_columns[[#This Row],[Название поля]] -> b3080000460003_escrow_legalgk_beneficiariesindividualcase when lastname is not null then 'individual' end | B95: b3080000460003_escrow_legalgk_beneficiariesindividual | C95: case when lastname is not null then 'individual' end | D95: text | E95: NO | F95: NULL | G95: Фамилия бенефициара ФЛ
A96: =source_columns[[#This Row],[Название таблицы STAGE]]&source_columns[[#This Row],[Название поля]] -> b3080000460003_escrow_legalgk_beneficiariesindividualmiddlename | B96: b3080000460003_escrow_legalgk_beneficiariesindividual | C96: middlename | D96: text | E96: NO | F96: NULL | G96: Отчество бенефициара ФЛ
A97: =source_columns[[#This Row],[Название таблицы STAGE]]&source_columns[[#This Row],[Название поля]] -> b3080000460003_escrow_legalgk_beneficiariesindividualbeneficiariesindividual_uid | B97: b3080000460003_escrow_legalgk_beneficiariesindividual | C97: beneficiariesindividual_uid | D97: uuid | E97: NO | F97: NULL | G97: ИД бенефициара ФЛ не клиента банка | H97: Составной( lastname + firstname + middlename+dateofbirth)
A98: =source_columns[[#This Row],[Название таблицы STAGE]]&source_columns[[#This Row],[Название поля]] -> b3080000460003_escrow_legalgk_beneficiariesindividualsys_date_create_or_update | B98: b3080000460003_escrow_legalgk_beneficiariesindividual | C98: sys_date_create_or_update | D98: timestamp | E98: NO | F98: NULL | G98: Дата и время последнего изменения
A99: =source_columns[[#This Row],[Название таблицы STAGE]]&source_columns[[#This Row],[Название поля]] -> b3080000460004_escrow_legalgk_beneficiarieslegalacc_number | B99: b3080000460004_escrow_legalgk_beneficiarieslegal | C99: acc_number | D99: text | E99: NO | F99: NULL | G99: Счет бенефициара ЮЛ
A100: =source_columns[[#This Row],[Название таблицы STAGE]]&source_columns[[#This Row],[Название поля]] -> b3080000460004_escrow_legalgk_beneficiarieslegalcreditcontract_d_l | B100: b3080000460004_escrow_legalgk_beneficiarieslegal | C100: creditcontract_d_l | D100: text | E100: NO | F100: NULL | G100: Номер кредитного договора у бенефициара ЮЛ
A101: =source_columns[[#This Row],[Название таблицы STAGE]]&source_columns[[#This Row],[Название поля]] -> b3080000460004_escrow_legalgk_beneficiarieslegalcreditcontract_d_l_uid | B101: b3080000460004_escrow_legalgk_beneficiarieslegal | C101: creditcontract_d_l_uid | D101: uuid | E101: NO | F101: NULL | G101: Номер кредитного договора у бенефициара ЮЛ
A102: =source_columns[[#This Row],[Название таблицы STAGE]]&source_columns[[#This Row],[Название поля]] -> b3080000460004_escrow_legalgk_beneficiarieslegalcreditcontract_l | B102: b3080000460004_escrow_legalgk_beneficiarieslegal | C102: creditcontract_l | D102: date | E102: NO | F102: NULL | G102: Дата кредитного договора у бенефициара ЮЛ
A103: =source_columns[[#This Row],[Название таблицы STAGE]]&source_columns[[#This Row],[Название поля]] -> b3080000460004_escrow_legalgk_beneficiarieslegalcreditcontract_l_eksid | B103: b3080000460004_escrow_legalgk_beneficiarieslegal | C103: creditcontract_l_eksid | D103: text | E103: NO | F103: NULL | G103: ИД кредитного договора в ЕКС у бенефициара ЮЛ
A104: =source_columns[[#This Row],[Название таблицы STAGE]]&source_columns[[#This Row],[Название поля]] -> b3080000460004_escrow_legalgk_beneficiarieslegalcreditcontract_l_kulid | B104: b3080000460004_escrow_legalgk_beneficiarieslegal | C104: creditcontract_l_kulid | D104: text | E104: NO | F104: NULL | G104: ИД ППРБ.КЮЛ у бенефициара ЮЛ
A105: =source_columns[[#This Row],[Название таблицы STAGE]]&source_columns[[#This Row],[Название поля]] -> b3080000460004_escrow_legalgk_beneficiarieslegalcreditcontract_l_kulid_uid | B105: b3080000460004_escrow_legalgk_beneficiarieslegal | C105: creditcontract_l_kulid_uid | D105: uuid | E105: NO | F105: NULL | G105: ИД ППРБ.КЮЛ у бенефициара ЮЛ
A106: =source_columns[[#This Row],[Название таблицы STAGE]]&source_columns[[#This Row],[Название поля]] -> b3080000460004_escrow_legalgk_beneficiarieslegaldeleted | B106: b3080000460004_escrow_legalgk_beneficiarieslegal | C106: deleted | D106: boolean | E106: NO | F106: NULL | G106: Признак удаления | I106: case when deleted = true then 'Y' else 'N'
A107: =source_columns[[#This Row],[Название таблицы STAGE]]&source_columns[[#This Row],[Название поля]] -> b3080000460004_escrow_legalgk_beneficiarieslegalepkid_l | B107: b3080000460004_escrow_legalgk_beneficiarieslegal | C107: epkid_l | D107: text | E107: NO | F107: NULL | G107: ИД ЕПК бенефициара ЮЛ
A108: =source_columns[[#This Row],[Название таблицы STAGE]]&source_columns[[#This Row],[Название поля]] -> b3080000460004_escrow_legalgk_beneficiarieslegalepkid_l_uid | B108: b3080000460004_escrow_legalgk_beneficiarieslegal | C108: epkid_l_uid | D108: uuid | E108: NO | F108: NULL | G108: ИД ЕПК бенефициара ЮЛ
A109: =source_columns[[#This Row],[Название таблицы STAGE]]&source_columns[[#This Row],[Название поля]] -> b3080000460004_escrow_legalgk_beneficiarieslegalescrowid | B109: b3080000460004_escrow_legalgk_beneficiarieslegal | C109: escrowid | D109: text | E109: YES | F109: NULL | G109: Идентификатор договора эскроу
A110: =source_columns[[#This Row],[Название таблицы STAGE]]&source_columns[[#This Row],[Название поля]] -> b3080000460004_escrow_legalgk_beneficiarieslegalescrowid_uid | B110: b3080000460004_escrow_legalgk_beneficiarieslegal | C110: escrowid_uid | D110: uuid | E110: YES | F110: NULL | G110: Идентификатор договора эскроу
A111: =source_columns[[#This Row],[Название таблицы STAGE]]&source_columns[[#This Row],[Название поля]] -> b3080000460004_escrow_legalgk_beneficiarieslegalid | B111: b3080000460004_escrow_legalgk_beneficiarieslegal | C111: id | D111: bigint | E111: NO | F111: NOT NULL | G111: ID записи
A112: =source_columns[[#This Row],[Название таблицы STAGE]]&source_columns[[#This Row],[Название поля]] -> b3080000460004_escrow_legalgk_beneficiarieslegalname | B112: b3080000460004_escrow_legalgk_beneficiarieslegal | C112: name | D112: text | E112: NO | F112: NULL | G112: Наименование бенефициара ЮЛ
A113: =source_columns[[#This Row],[Название таблицы STAGE]]&source_columns[[#This Row],[Название поля]] -> b3080000460004_escrow_legalgk_beneficiarieslegalbeneficiarieslegal_uid | B113: b3080000460004_escrow_legalgk_beneficiarieslegal | C113: beneficiarieslegal_uid | D113: uuid | E113: NO | F113: NULL | G113: ИД бенефициара ЮЛ не клиента банка | H113: Составной(name + taxid)
A114: =source_columns[[#This Row],[Название таблицы STAGE]]&source_columns[[#This Row],[Название поля]] -> b3080000460004_escrow_legalgk_beneficiarieslegalsys_date_create_or_update | B114: b3080000460004_escrow_legalgk_beneficiarieslegal | C114: sys_date_create_or_update | D114: timestamp | E114: NO | F114: NULL | G114: Дата и время последнего изменения
A115: =source_columns[[#This Row],[Название таблицы STAGE]]&source_columns[[#This Row],[Название поля]] -> b3080000460004_escrow_legalgk_beneficiarieslegaltaxid | B115: b3080000460004_escrow_legalgk_beneficiarieslegal | C115: taxid | D115: text | E115: NO | F115: NULL | G115: ИНН бенефициара ЮЛ
A116: =source_columns[[#This Row],[Название таблицы STAGE]]&source_columns[[#This Row],[Название поля]] -> b3080000460005_escrow_legalgk_tariffscomissioner | B116: b3080000460005_escrow_legalgk_tariffs | C116: comissioner | D116: text | E116: NO | F116: NULL | G116: Код типа плательщика
A117: =source_columns[[#This Row],[Название таблицы STAGE]]&source_columns[[#This Row],[Название поля]] -> b3080000460005_escrow_legalgk_tariffscomissioner_d | B117: b3080000460005_escrow_legalgk_tariffs | C117: comissioner_d | D117: text | E117: NO | F117: NULL | G117: Наименование типа плательщика
A118: =source_columns[[#This Row],[Название таблицы STAGE]]&source_columns[[#This Row],[Название поля]] -> b3080000460005_escrow_legalgk_tariffscomissionerid | B118: b3080000460005_escrow_legalgk_tariffs | C118: comissionerid | D118: text | E118: NO | F118: NULL | G118: ИД ЕПК плательщика
A119: =source_columns[[#This Row],[Название таблицы STAGE]]&source_columns[[#This Row],[Название поля]] -> b3080000460005_escrow_legalgk_tariffscomissionerid_uid | B119: b3080000460005_escrow_legalgk_tariffs | C119: comissionerid_uid | D119: uuid | E119: NO | F119: NULL | G119: ИД ЕПК плательщика
A120: =source_columns[[#This Row],[Название таблицы STAGE]]&source_columns[[#This Row],[Название поля]] -> b3080000460005_escrow_legalgk_tariffsdeleted | B120: b3080000460005_escrow_legalgk_tariffs | C120: deleted | D120: boolean | E120: NO | F120: NULL | G120: Признак удаления | I120: case when deleted = true then 'Y' else 'N'
A121: =source_columns[[#This Row],[Название таблицы STAGE]]&source_columns[[#This Row],[Название поля]] -> b3080000460005_escrow_legalgk_tariffsescrowid | B121: b3080000460005_escrow_legalgk_tariffs | C121: escrowid | D121: text | E121: YES | F121: NULL | G121: Идентификатор договора эскроу
A122: =source_columns[[#This Row],[Название таблицы STAGE]]&source_columns[[#This Row],[Название поля]] -> b3080000460005_escrow_legalgk_tariffsescrowid_uid | B122: b3080000460005_escrow_legalgk_tariffs | C122: escrowid_uid | D122: uuid | E122: YES | F122: NULL | G122: Идентификатор договора эскроу
A123: =source_columns[[#This Row],[Название таблицы STAGE]]&source_columns[[#This Row],[Название поля]] -> b3080000460005_escrow_legalgk_tariffsevent_type_code | B123: b3080000460005_escrow_legalgk_tariffs | C123: event_type_code | D123: text | E123: NO | F123: NULL | G123: Код типа операции
A124: =source_columns[[#This Row],[Название таблицы STAGE]]&source_columns[[#This Row],[Название поля]] -> b3080000460005_escrow_legalgk_tariffsevent_type_code_uid | B124: b3080000460005_escrow_legalgk_tariffs | C124: event_type_code_uid | D124: uuid | E124: NO | F124: NULL | G124: Код типа операции
A125: =source_columns[[#This Row],[Название таблицы STAGE]]&source_columns[[#This Row],[Название поля]] -> b3080000460005_escrow_legalgk_tariffsevent_type_desc | B125: b3080000460005_escrow_legalgk_tariffs | C125: event_type_desc | D125: text | E125: NO | F125: NULL | G125: Наименование типа операции
A126: =source_columns[[#This Row],[Название таблицы STAGE]]&source_columns[[#This Row],[Название поля]] -> b3080000460005_escrow_legalgk_tariffsid | B126: b3080000460005_escrow_legalgk_tariffs | C126: id | D126: bigint | E126: NO | F126: NOT NULL | G126: ID записи
A127: =source_columns[[#This Row],[Название таблицы STAGE]]&source_columns[[#This Row],[Название поля]] -> b3080000460005_escrow_legalgk_tariffsstartdate | B127: b3080000460005_escrow_legalgk_tariffs | C127: startdate | D127: date | E127: NO | F127: NULL | G127: Дата начала действия тарифа
A128: =source_columns[[#This Row],[Название таблицы STAGE]]&source_columns[[#This Row],[Название поля]] -> b3080000460005_escrow_legalgk_tariffssys_date_create_or_update | B128: b3080000460005_escrow_legalgk_tariffs | C128: sys_date_create_or_update | D128: timestamp | E128: NO | F128: NULL | G128: Дата и время последнего изменения
A129: =source_columns[[#This Row],[Название таблицы STAGE]]&source_columns[[#This Row],[Название поля]] -> b3080000460006_payments_2_0_posting_dtoagreementid | B129: b3080000460006_payments_2_0_posting_dto | C129: agreementid | D129: text | E129: NO | F129: NULL | G129: Идентификатор договора
A130: =source_columns[[#This Row],[Название таблицы STAGE]]&source_columns[[#This Row],[Название поля]] -> b3080000460006_payments_2_0_posting_dtoagreementid_uid | B130: b3080000460006_payments_2_0_posting_dto | C130: agreementid_uid | D130: uuid | E130: NO | F130: NULL | G130: Идентификатор договора
A131: =source_columns[[#This Row],[Название таблицы STAGE]]&source_columns[[#This Row],[Название поля]] -> b3080000460006_payments_2_0_posting_dtoagreementreference | B131: b3080000460006_payments_2_0_posting_dto | C131: agreementreference | D131: text | E131: NO | F131: NULL | G131: Номер договора
A132: =source_columns[[#This Row],[Название таблицы STAGE]]&source_columns[[#This Row],[Название поля]] -> b3080000460006_payments_2_0_posting_dtoamount | B132: b3080000460006_payments_2_0_posting_dto | C132: amount | D132: numeric(38 , 16) | E132: NO | F132: NULL | G132: Сумма операции
... A138: =source_columns[[#This Row],[Название таблицы STAGE]]&source_columns[[#This Row],[Название поля]] -> b3080000460006_payments_2_0_posting_dtodatep | B138: b3080000460006_payments_2_0_posting_dto | C138: datep | D138: date | E138: NO | F138: NULL | G138: Дата операции
A139: =source_columns[[#This Row],[Название таблицы STAGE]]&source_columns[[#This Row],[Название поля]] -> b3080000460006_payments_2_0_posting_dtodeleted | B139: b3080000460006_payments_2_0_posting_dto | C139: deleted | D139: boolean | E139: NO | F139: NULL | G139: Признак удаления | I139: case when deleted = true then 'Y' else 'N'
A140: =source_columns[[#This Row],[Название таблицы STAGE]]&source_columns[[#This Row],[Название поля]] -> b3080000460006_payments_2_0_posting_dtoid | B140: b3080000460006_payments_2_0_posting_dto | C140: id | D140: bigint | E140: YES | F140: NOT NULL | G140: ID записи
A141: =source_columns[[#This Row],[Название таблицы STAGE]]&source_columns[[#This Row],[Название поля]] -> b3080000460006_payments_2_0_posting_dtoid_uid | B141: b3080000460006_payments_2_0_posting_dto | C141: id_uid | D141: uuid | E141: YES | F141: NOT NULL | G141: ID операции
A142: =source_columns[[#This Row],[Название таблицы STAGE]]&source_columns[[#This Row],[Название поля]] -> b3080000460006_payments_2_0_posting_dtooperationiddt | B142: b3080000460006_payments_2_0_posting_dto | C142: operationiddt | D142: text | E142: NO | F142: NULL | G142: ИД операции
A143: =source_columns[[#This Row],[Название таблицы STAGE]]&source_columns[[#This Row],[Название поля]] -> b3080000460006_payments_2_0_posting_dtopurpose | B143: b3080000460006_payments_2_0_posting_dto | C143: purpose | D143: text | E143: NO | F143: NULL | G143: Наименование операции
A144: =source_columns[[#This Row],[Название таблицы STAGE]]&source_columns[[#This Row],[Название поля]] -> b3080000460006_payments_2_0_posting_dtoregisteriddt | B144: b3080000460006_payments_2_0_posting_dto | C144: registeriddt | D144: text | E144: NO | F144: NULL | G144: ИД регистра ДТ
A145: =source_columns[[#This Row],[Название таблицы STAGE]]&source_columns[[#This Row],[Название поля]] -> b3080000460006_payments_2_0_posting_dtoserviceid | B145: b3080000460006_payments_2_0_posting_dto | C145: serviceid | D145: text | E145: NO | F145: NULL | G145: ИД сервиса
A146: =source_columns[[#This Row],[Название таблицы STAGE]]&source_columns[[#This Row],[Название поля]] -> b3080000460006_payments_2_0_posting_dtoserviceid_uid | B146: b3080000460006_payments_2_0_posting_dto | C146: serviceid_uid | D146: uuid | E146: NO | F146: NULL | G146: ИД сервиса
A147: =source_columns[[#This Row],[Название таблицы STAGE]]&source_columns[[#This Row],[Название поля]] -> b3080000460006_payments_2_0_posting_dtoprocessCode | B147: b3080000460006_payments_2_0_posting_dto | C147: processCode | D147: text | E147: NO | F147: NULL | G147: Код типа операции
A148: =source_columns[[#This Row],[Название таблицы STAGE]]&source_columns[[#This Row],[Название поля]] -> b3080000460006_payments_2_0_posting_dtoprocessCode_uid | B148: b3080000460006_payments_2_0_posting_dto | C148: processCode_uid | D148: uuid | E148: NO | F148: NULL | G148: Код типа операции
A149: =source_columns[[#This Row],[Название таблицы STAGE]]&source_columns[[#This Row],[Название поля]] -> b3080000460006_payments_2_0_posting_dtosys_date_create_or_update | B149: b3080000460006_payments_2_0_posting_dto | C149: sys_date_create_or_update | D149: timestamp | E149: NO | F149: NULL | G149: Дата и время последнего изменения
A150: =source_columns[[#This Row],[Название таблицы STAGE]]&source_columns[[#This Row],[Название поля]] -> b3080000460007_payments_2_0_account_dtoid | B150: b3080000460007_payments_2_0_account_dto | C150: id | D150: bigint | E150: NO | F150: NULL | G150: ID записи
A151: =source_columns[[#This Row],[Название таблицы STAGE]]&source_columns[[#This Row],[Название поля]] -> b3080000460007_payments_2_0_account_dtosys_date_create_or_update | B151: b3080000460007_payments_2_0_account_dto | C151: sys_date_create_or_update | D151: timestamp | E151: NO | F151: NULL | G151: Дата и время последнего изменения
... A174: =source_columns[[#This Row],[Название таблицы STAGE]]&source_columns[[#This Row],[Название поля]] -> b3080000460008_general_agreement_actual_limitschedulevalue_amnt_limitschedule | B174: b3080000460008_general_agreement_actual_limitschedule | C174: value_amnt_limitschedule | D174: numeric(38 , 16) | E174: NO | F174: NULL | G174: Сумма договора
A175: =source_columns[[#This Row],[Название таблицы STAGE]]&source_columns[[#This Row],[Название поля]] -> b3080000460008_general_agreement_actual_limitscheduledeleted | B175: b3080000460008_general_agreement_actual_limitschedule | C175: deleted | D175: boolean | E175: NO | F175: NULL | G175: Признак удаления | I175: case when deleted = true then 'y' else 'n'
A176: =source_columns[[#This Row],[Название таблицы STAGE]]&source_columns[[#This Row],[Название поля]] -> b3080000460008_general_agreement_actual_limitschedulesys_date_create_or_update | B176: b3080000460008_general_agreement_actual_limitschedule | C176: sys_date_create_or_update | D176: text | E176: NO | F176: NULL | G176: Дата и время последнего изменения
...

Sheet Target tables
D1: =COLUMN() -> 4 | E1: =COLUMN() -> 5
A2: Table Name | B2: Table Entity Definition | C2: Table Entity Note | D2: Table Is In Subject Area Name | E2: Суффикс N-таблицы
A3: t_crncy | B3: Справочник валюты | E3: crncy
A4: t_agr_cred | B4: Кредитный договор | E4: agr_cred
A5: t_registry | B5: Таблица регистров | E5: registry
A6: t_agr_escrow_agr_cred | B6: Таблица связей кредитного договора с договором эскроу | E6: agr_escrow_agr_cred
A7: t_escrow_scheme | B7: Справочник схем субсидирования | E7: escrow_scheme
A8: t_agr_escrow | B8: Договор эскроу | E8: agr_escrow
A9: t_agr_escrow_cust | B9: Таблица связей контрагентов с договором эскроу | E9: agr_escrow_cust
A10: t_agr_escrow_cust_type | B10: Справочник ролей клиента в договоре эскроу | E10: agr_escrow_cust_type
A11: t_cust | B11: Контрагенты | E11: cust
A12: t_int_org | B12: Справочник оргструктуры | E12: int_org
A13: t_agr_escrow_int_org | B13: Таблица связей договора эскроу со справочником оргструктуры | E13: agr_escrow_int_org
A14: t_registry_type | B14: Справочник типов регистра счета | E14: registry_type
... A25: t_optn_fee_type | B25: Тип комиссии по операции | E25: optn_fee_type
A26: t_agr_accred | B26: Договор аккредитива ЮЛ | E26: =SUBSTITUTE(target_tables[[#This Row],[Table Name]],"t_","",1) -> agr_accred
A27: t_agr_accred_fin | B27: Характеристики договора аккредитива ЮЛ | E27: =SUBSTITUTE(target_tables[[#This Row],[Table Name]],"t_","",1) -> agr_accred_fin
A28: t_accred_cover_type | B28: Тип источника формирования покрытия | E28: =SUBSTITUTE(target_tables[[#This Row],[Table Name]],"t_","",1) -> accred_cover_type
A29: t_time_period_type | B29: Тип периода отсрочки платежа | E29: =SUBSTITUTE(target_tables[[#This Row],[Table Name]],"t_","",1) -> time_period_type
A30: t_agr_accred_type | B30: Тип договора аккредитива ЮЛ | E30: =SUBSTITUTE(target_tables[[#This Row],[Table Name]],"t_","",1) -> agr_accred_type
A31: t_accred_income_scheme | B31: Схема распределения доходов | E31: =SUBSTITUTE(target_tables[[#This Row],[Table Name]],"t_","",1) -> accred_income_scheme
A32: t_agr_accred_agr_cred | B32: Связь договора аккредитива ЮЛ и кредитного договора | E32: =SUBSTITUTE(target_tables[[#This Row],[Table Name]],"t_","",1) -> agr_accred_agr_cred
A33: t_agr_accred_bank | B33: Связь договора аккредитива ЮЛ и банка | E33: =SUBSTITUTE(target_tables[[#This Row],[Table Name]],"t_","",1) -> agr_accred_bank
A34: t_agr_accred_bank_type | B34: Тип связи договора аккредитива ЮЛ и банка | E34: =SUBSTITUTE(target_tables[[#This Row],[Table Name]],"t_","",1) -> agr_accred_bank_type
A35: t_agr_accred_contract | B35: Связь договора аккредитива ЮЛ и контракта | E35: =SUBSTITUTE(target_tables[[#This Row],[Table Name]],"t_","",1) -> agr_accred_contract
A36: t_agr_accred_cust | B36: Связь договора аккредитива ЮЛ и контрагента | E36: =SUBSTITUTE(target_tables[[#This Row],[Table Name]],"t_","",1) -> agr_accred_cust
A37: t_agr_accred_cust_type | B37: Тип связи договора аккредитива ЮЛ и контрагента | E37: =SUBSTITUTE(target_tables[[#This Row],[Table Name]],"t_","",1) -> agr_accred_cust_type
... A46: t_registry$gls_clsfctn | B46: Классификационные характеристики регистров | E46: =SUBSTITUTE(target_tables[[#This Row],[Table Name]],"t_","",1) -> registry$gls_clsfctn
A47: t_agr_other | B47: Договора, для которых не созданы собственные agrmnt | E47: agr_other
A48: t_agr_other_cust | B48: Связь договора с контрагентом | E48: agr_other_cust
A49: t_agr_other_int_org | B49: Таблица связей договора эскроу со справочником оргструктуры | E49: agr_other_int_org
A50: t_agr_other_bank | B50: Связь договора и банка | E50: agr_other_bank
A51: t_agr_other_coa | B51: Связь договора и счета | E51: agr_other_coa
A52: t_agr_other_coa_role | B52: Тип связи договора и счета | E52: agr_other_coa_role
A53: t_agr_other_int_org_type | B53: Типа связи договора с терр. структурой | E53: agr_other_int_org_type
A54: t_agr_other_bank_type | B54: Тип связи договора и банка | E54: agr_accred_bank_type
A55: t_agr_other_cust_type | B55: Тип клиента на договоре | E55: agr_other_cust_type
A56: t_agr_other_categ | B56: Типы досье | E56: agr_other_categ
A57: t_agr_scheme | B57: Связь договора со схемами | E57: agr_scheme
A58: t_agr_accred_stts | B58: Статус договора | E58: agr_accred_stts
... A76: t_agr_escrow_schdl_type | B76: Тип графика платежей | E76: agr_escrow_schdl_type

Sheet Target columns
D1: =COLUMN() -> 4 | E1: =COLUMN() -> 5 | F1: =COLUMN() -> 6 | G1: =COLUMN() -> 7 | H1: =COLUMN() -> 8 | I1: =COLUMN() -> 9 | J1: =COLUMN() -> 10
A2: Seek | B2: ColumnTableName | C2: ColumnName | D2: Column Datatype | E2: Column Null Option | F2: Column Physical Only | G2: Column Is PK | H2: Column Is FK | I2: Column Attribute Definition | J2: Column Attribute Note
A3: =target_columns[[#This Row],[ColumnTableName]]&target_columns[[#This Row],[ColumnName]] -> t_crncycrncy_id | B3: t_crncy | C3: crncy_id | D3: UUID | E3: NOT NULL | G3: Yes | H3: No | J3: Идентификатор валюты
A4: =target_columns[[#This Row],[ColumnTableName]]&target_columns[[#This Row],[ColumnName]] -> t_crncyiso_crncy_cd | B4: t_crncy | C4: iso_crncy_cd | D4: TEXT | E4: NULL | G4: No | H4: No | J4: Буквенный код валюты
A5: =target_columns[[#This Row],[ColumnTableName]]&target_columns[[#This Row],[ColumnName]] -> t_agr_credagr_cred_id | B5: t_agr_cred | C5: agr_cred_id | D5: UUID | E5: NOT NULL | G5: Yes | H5: No | J5: ИД кредитного договора с застройщиком
A6: =target_columns[[#This Row],[ColumnTableName]]&target_columns[[#This Row],[ColumnName]] -> t_agr_credsigned_dt | B6: t_agr_cred | C6: signed_dt | D6: DATE | E6: NULL | G6: No | H6: No | J6: Дата подписания договора
A7: =target_columns[[#This Row],[ColumnTableName]]&target_columns[[#This Row],[ColumnName]] -> t_agr_credagr_cred_num | B7: t_agr_cred | C7: agr_cred_num | D7: TEXT | E7: NULL | G7: No | H7: No | J7: Номер договора
A8: =target_columns[[#This Row],[ColumnTableName]]&target_columns[[#This Row],[ColumnName]] -> t_agr_credhost_eks_agrmnt_id | B8: t_agr_cred | C8: host_eks_agrmnt_id | D8: TEXT | E8: NULL | G8: No | H8: No | J8: ID договора в ЕКС
A9: =target_columns[[#This Row],[ColumnTableName]]&target_columns[[#This Row],[ColumnName]] -> t_agr_credhost_agr_cred_id | B9: t_agr_cred | C9: host_agr_cred_id | D9: TEXT | E9: NULL | G9: No | H9: No | J9: ИД договора в системе-источнике ППРБ.КЮЛ
A10: =target_columns[[#This Row],[ColumnTableName]]&target_columns[[#This Row],[ColumnName]] -> t_registryregistry_id | B10: t_registry | C10: registry_id | D10: UUID | E10: NOT NULL | G10: Yes | H10: No | J10: Идентификатор регистра
A11: =target_columns[[#This Row],[ColumnTableName]]&target_columns[[#This Row],[ColumnName]] -> t_registryhost_registry_id | B11: t_registry | C11: host_registry_id | D11: TEXT | E11: NULL | G11: No | H11: No | J11: Идентификатор регистра в системе-источнике
A12: =target_columns[[#This Row],[ColumnTableName]]&target_columns[[#This Row],[ColumnName]] -> t_registryregistry_type_id | B12: t_registry | C12: registry_type_id | D12: UUID | E12: NOT NULL | G12: No | H12: Yes | J12: Тип регистра счета
A13: =target_columns[[#This Row],[ColumnTableName]]&target_columns[[#This Row],[ColumnName]] -> t_registryagr_escrow_id | B13: t_registry | C13: agr_escrow_id | D13: UUID | E13: NULL | G13: No | H13: Yes | J13: Идентификатор договора эскроу
A14: =target_columns[[#This Row],[ColumnTableName]]&target_columns[[#This Row],[ColumnName]] -> t_registryagr_id | B14: t_registry | C14: agr_id | D14: UUID | E14: NULL | G14: No | H14: Yes | J14: Идентификатор договора
... A49: =target_columns[[#This Row],[ColumnTableName]]&target_columns[[#This Row],[ColumnName]] -> t_custhost_epk_cust_id | B49: t_cust | C49: host_epk_cust_id | D49: TEXT | E49: NULL | G49: No | H49: No | J49: Идентификатор контрагента в ЕПК
A50: =B50&C50 -> t_custhost_cust_id | B50: t_cust | C50: host_cust_id | D50: text | E50: NULL | G50: No | H50: No | J50: Идентификатор контрагента в системе-источника
A51: =target_columns[[#This Row],[ColumnTableName]]&target_columns[[#This Row],[ColumnName]] -> t_custind_flag | B51: t_cust | C51: ind_flag | D51: TEXT | E51: NULL | G51: No | H51: No | J51: Физическое лицо
A52: =target_columns[[#This Row],[ColumnTableName]]&target_columns[[#This Row],[ColumnName]] -> t_cust_org_idfncust_id | B52: t_cust_org_idfn | C52: cust_id | D52: UUID | E52: NOT NULL | G52: Yes | H52: No | J52: Идентификатор контрагента
A53: =target_columns[[#This Row],[ColumnTableName]]&target_columns[[#This Row],[ColumnName]] -> t_cust_org_idfnshort_name | B53: t_cust_org_idfn | C53: short_name | D53: TEXT | E53: NULL | G53: No | H53: No | J53: Краткое наименование юр. Лица
A54: =target_columns[[#This Row],[ColumnTableName]]&target_columns[[#This Row],[ColumnName]] -> t_cust_org_idfninn_num | B54: t_cust_org_idfn | C54: inn_num | D54: TEXT | E54: NULL | G54: No | H54: No | J54: ИНН
A55: =target_columns[[#This Row],[ColumnTableName]]&target_columns[[#This Row],[ColumnName]] -> t_int_orgint_org_id | B55: t_int_org | C55: int_org_id | D55: UUID | E55: NOT NULL | G55: Yes | H55: No | J55: Идентификатор оргструктуры
A56: =B56&C56 -> t_int_orgbic_num | B56: t_int_org | C56: bic_num | D56: text | E56: NULL | G56: No | H56: No | J56: БИК
A57: =B57&C57 -> t_int_orgint_org_name | B57: t_int_org | C57: int_org_name | D57: text | E57: NULL | G57: No | H57: No | J57: Наименование подразделения
A58: =target_columns[[#This Row],[ColumnTableName]]&target_columns[[#This Row],[ColumnName]] -> t_int_orgint_org_num | B58: t_int_org | C58: int_org_num | D58: TEXT | E58: NULL | G58: No | H58: No | J58: Номер внутреннего подразделения
A59: =target_columns[[#This Row],[ColumnTableName]]&target_columns[[#This Row],[ColumnName]] -> t_agr_escrow_int_orgagr_escrow_id | B59: t_agr_escrow_int_org | C59: agr_escrow_id | D59: UUID | E59: NOT NULL | G59: Yes | H59: Yes | J59: Идентификатор договора
A60: =target_columns[[#This Row],[ColumnTableName]]&target_columns[[#This Row],[ColumnName]] -> t_agr_escrow_int_orgint_org_id | B60: t_agr_escrow_int_org | C60: int_org_id | D60: UUID | E60: NULL | G60: No | H60: Yes | J60: Код ВСП ведения договора
A61: =target_columns[[#This Row],[ColumnTableName]]&target_columns[[#This Row],[ColumnName]] -> t_agr_escrow_int_orgben_int_org_id | B61: t_agr_escrow_int_org | C61: ben_int_org_id | D61: UUID | E61: NULL | G61: No | H61: Yes | J61: Код ВСП открытия счета бенефициара
A62: =target_columns[[#This Row],[ColumnTableName]]&target_columns[[#This Row],[ColumnName]] -> t_agr_escrow_int_orgdep_int_org_id | B62: t_agr_escrow_int_org | C62: dep_int_org_id | D62: UUID | E62: NULL | G62: No | H62: Yes | J62: Код ВСП открытия счета депонента
A63: =target_columns[[#This Row],[ColumnTableName]]&target_columns[[#This Row],[ColumnName]] -> t_agr_escrow_int_orgstart_dt | B63: t_agr_escrow_int_org | C63: start_dt | D63: DATE | E63: NOT NULL | G63: Yes | H63: No | J63: Дата начала действия связи
A64: =target_columns[[#This Row],[ColumnTableName]]&target_columns[[#This Row],[ColumnName]] -> t_agr_escrow_int_orgend_dt | B64: t_agr_escrow_int_org | C64: end_dt | D64: DATE | E64: NULL | G64: No | H64: No | J64: Дата окончания действия связи
A65: =target_columns[[#This Row],[ColumnTableName]]&target_columns[[#This Row],[ColumnName]] -> t_registry_typeregistry_type_id | B65: t_registry_type | C65: registry_type_id | D65: UUID | E65: NOT NULL | G65: Yes | H65: No | J65: Тип регистра счета
A66: =target_columns[[#This Row],[ColumnTableName]]&target_columns[[#This Row],[ColumnName]] -> t_registry_typeregistry_type_name | B66: t_registry_type | C66: registry_type_name | D66: TEXT | E66: NULL | G66: No | H66: No | J66: Наименование типа регистра счета
A67: =target_columns[[#This Row],[ColumnTableName]]&target_columns[[#This Row],[ColumnName]] -> t_registry_typeregistry_type_cd | B67: t_registry_type | C67: registry_type_cd | D67: TEXT | E67: NULL | G67: No | H67: No | J67: Код типа регистра счета
A68: =target_columns[[#This Row],[ColumnTableName]]&target_columns[[#This Row],[ColumnName]] -> t_optn_typeoptn_type_id | B68: t_optn_type | C68: optn_type_id | D68: UUID | E68: NOT NULL | G68: Yes | H68: No | J68: Уникальный идентификатор типа операции
A69: =target_columns[[#This Row],[ColumnTableName]]&target_columns[[#This Row],[ColumnName]] -> t_optn_typeoptn_type_cd | B69: t_optn_type | C69: optn_type_cd | D69: TEXT | E69: NULL | G69: No | H69: No | J69: Код типа операции
... A77: =target_columns[[#This Row],[ColumnTableName]]&target_columns[[#This Row],[ColumnName]] -> t_optncrncy_id | B77: t_optn | C77: crncy_id | D77: UUID | E77: NULL | G77: No | H77: Yes | J77: Идентификатор валюты
A78: =B78&C78 -> t_optnhost_optn_id | B78: t_optn | C78: host_optn_id | D78: text | E78: NULL | G78: No | H78: No | J78: Идентификатор операции в системе-источнике
A79: =target_columns[[#This Row],[ColumnTableName]]&target_columns[[#This Row],[ColumnName]] -> t_optnbus_srv_id | B79: t_optn | C79: bus_srv_id | D79: UUID | E79: NULL | G79: No | H79: Yes | J79: id сервиса
A80: =target_columns[[#This Row],[ColumnTableName]]&target_columns[[#This Row],[ColumnName]] -> t_optn_fee_typeoptn_fee_type_id | B80: t_optn_fee_type | C80: optn_fee_type_id | D80: UUID | E80: NOT NULL | G80: Yes | H80: No | J80: Уникальный идентификатор типа комиссии по операции
A81: =target_columns[[#This Row],[ColumnTableName]]&target_columns[[#This Row],[ColumnName]] -> t_optn_fee_typeoptn_fee_type_cd | B81: t_optn_fee_type | C81: optn_fee_type_cd | D81: TEXT | E81: NULL | G81: No | H81: No | J81: Код типа комиссии по операции
A82: =target_columns[[#This Row],[ColumnTableName]]&target_columns[[#This Row],[ColumnName]] -> t_optn_fee_typeoptn_fee_type_name | B82: t_optn_fee_type | C82: optn_fee_type_name | D82: TEXT | E82: NULL | G82: No | H82: No | J82: Наименование комиссии по операции
A83: =target_columns[[#This Row],[ColumnTableName]]&target_columns[[#This Row],[ColumnName]] -> t_optn$glsoptn_id | B83: t_optn$gls | C83: optn_id | D83: UUID | E83: NOT NULL | G83: Yes | H83: No | J83: Уникальный идентификатор операции
A84: =target_columns[[#This Row],[ColumnTableName]]&target_columns[[#This Row],[ColumnName]] -> t_optn$glshost_rpfi_appl_id | B84: t_optn$gls | C84: host_rpfi_appl_id | D84: TEXT | E84: NULL | G84: No | H84: No | J84: Идентификатор заявки из РПФИ
A85: =target_columns[[#This Row],[ColumnTableName]]&target_columns[[#This Row],[ColumnName]] -> t_optn$glspayer_ben_cust_id | B85: t_optn$gls | C85: payer_ben_cust_id | D85: UUID | E85: NULL | G85: No | H85: Yes | J85: Плательщик-бенефициар
A86: =target_columns[[#This Row],[ColumnTableName]]&target_columns[[#This Row],[ColumnName]] -> t_optn$glsoptn_fee_type_id | B86: t_optn$gls | C86: optn_fee_type_id | D86: UUID | E86: NULL | G86: No | H86: Yes | J86: Уникальный идентификатор типа комиссии по операции
A87: =target_columns[[#This Row],[ColumnTableName]]&target_columns[[#This Row],[ColumnName]] -> t_optn$glspayer_dep_cust_id | B87: t_optn$gls | C87: payer_dep_cust_id | D87: UUID | E87: NULL | G87: No | H87: Yes | J87: Плательщик-депонент
A88: =B88&C88 -> t_agr_frame_limitagr_id | B88: t_agr_frame_limit | C88: agr_id | D88: UUID | E88: NOT NULL | G88: Yes | H88: Yes | J88: ИД договора
A89: =B89&C89 -> t_agr_frame_limitaccred_limit_amt | B89: t_agr_frame_limit | C89: accred_limit_amt | D89: NUMERIC | E89: NULL | G89: No | H89: No | J89: Сумма лимита на общую сумму аккредитивов
A90: =B90&C90 -> t_agr_frame_limitaccred_limit_crncy_id | B90: t_agr_frame_limit | C90: accred_limit_crncy_id | D90: UUID | E90: NULL | G90: No | H90: Yes | J90: Валюта лимита на общую сумму аккредитивов
A91: =B91&C91 -> t_agr_frame_limitstart_dt | B91: t_agr_frame_limit | C91: start_dt | D91: DATE | E91: NOT NULL | G91: Yes | H91: No | J91: Дата начала действия лимита
A92: =B92&C92 -> t_agr_frame_limitend_dt | B92: t_agr_frame_limit | C92: end_dt | D92: DATE | E92: NULL | G92: No | H92: No | J92: Дата окончания действия лимита
A93: =B93&C93 -> t_schemescheme_id | B93: t_scheme | C93: scheme_id | D93: UUID | E93: NOT NULL | G93: Yes | H93: No | J93: Идентификатор схемы заведения договора
A94: =B94&C94 -> t_schemescheme_cd | B94: t_scheme | C94: scheme_cd | D94: TEXT | E94: NULL | G94: No | H94: No | J94: Код схемы заведения договора
A95: =B95&C95 -> t_schemescheme_name | B95: t_scheme | C95: scheme_name | D95: TEXT | E95: NULL | G95: No | H95: No | J95: Наименование схемы заведения договора
A96: =B96&C96 -> t_schemescheme_categ_id | B96: t_scheme | C96: scheme_categ_id | D96: UUID | E96: NOT NULL | G96: No | H96: Yes | J96: Идентификатор категории схем
A97: =B97&C97 -> t_agr_frameagr_frame_id | B97: t_agr_frame | C97: agr_frame_id | D97: UUID | E97: NOT NULL | G97: Yes | H97: No | J97: Идентификатор договора
A98: =B98&C98 -> t_agr_frameopen_dt | B98: t_agr_frame | C98: open_dt | D98: DATE | E98: NULL | G98: No | H98: No | J98: Дата открытия договора
A99: =B99&C99 -> t_agr_framesigned_dt | B99: t_agr_frame | C99: signed_dt | D99: DATE | E99: NULL | G99: No | H99: No | J99: Дата заключения договора
... A365: =B365&C365 -> t_agr_escrow_schdl_typeagr_escrow_schdl_type_name | B365: t_agr_escrow_schdl_type | C365: agr_escrow_schdl_type_name | D365: TEXT | E365: NULL | G365: No | H365: No | J365: Наименование типа графика платежа
A366: =B366&C366
A367: =B367&C367
A368: =B368&C368
A369: =B369&C369
A370: =B370&C370
A371: =B371&C371
A372: =B372&C372
A373: =B373&C373
A374: =B374&C374
A375: =B375&C375
A376: =B376&C376
A377: =B377&C377
... A481: =B481&C481

Sheet Метаданные для hadoop
A1: Наименование таблицы источника (схема в Haduoop show create table custom_t_processing_308.lcl…таблица) | B1: Поле источника | C1: Тип данных поля источника | D1: JSON путь | E1: NULL? | F1: Наименование таблицы приемника | G1: Наименования атрибута | H1: Тип данных поля приемника
A2: escrow_legal214_agreement_actual | B2: dto | C2: JSONB | D2: agreement.escrowId | E2: NOT NULL | F2: escrow_legal214_agreement_actual_dto | G2: escrowId_agreement | H2: string
A3: escrow_legal214_agreement_actual | B3: dto | C3: JSONB | D3: agreement.openDate | E3: NOT NULL | F3: escrow_legal214_agreement_actual_dto | G3: openDate_agreement | H3: date
A4: escrow_legal214_agreement_actual | B4: dto | C4: JSONB | D4: agreement.closeDate | E4: NULL | F4: escrow_legal214_agreement_actual_dto | G4: closeDate_agreement | H4: date
A5: escrow_legal214_agreement_actual | B5: dto | C5: JSONB | D5: agreement.reference | E5: NOT NULL | F5: escrow_legal214_agreement_actual_dto | G5: reference_agreement | H5: string
A6: escrow_legal214_agreement_actual | B6: dto | C6: JSONB | D6: beneficiary.legalEpkId | E6: NULL | F6: escrow_legal214_agreement_actual_dto | G6: legalEpkId_beneficiary | H6: string
A7: escrow_legal214_agreement_actual | B7: dto | C7: JSONB | D7: agreementObject.estateObjectExpireDate | E7: NOT NULL | F7: escrow_legal214_agreement_actual_dto | G7: estateObject_ExpireDate_agreementObject | H7: date
A8: escrow_legal214_agreement_actual | B8: dto | C8: JSONB | D8: agreementObject.completeEstimateDate | E8: NOT NULL | F8: escrow_legal214_agreement_actual_dto | G8: completeEstimateDate_agreementObject | H8: date
A9: escrow_legal214_agreement_actual | B9: dto | C9: JSONB | D9: agreement.rateSubsidyScheme | E9: NULL | F9: escrow_legal214_agreement_actual_dto | G9: rateSubsidyScheme_agreement | H9: string
A10: escrow_legal214_agreement_actual | B10: dto | C10: JSONB | D10: agreement.status | E10: NOT NULL | F10: escrow_legal214_agreement_actual_dto | G10: status_agreement | H10: string
A11: escrow_legal214_agreement_actual | B11: dto | C11: JSONB | D11: agreement.lastModifiedDate | E11: NOT NULL | F11: escrow_legal214_agreement_actual_dto | G11: lastModifiedDate_agreement | H11: timestamp
A12: escrow_legal214_agreement_actual | B12: dto | C12: JSONB | D12: agreement.parentAgreementId | E12: NULL | F12: escrow_legal214_agreement_actual_dto | G12: parentAgreementId_agreement | H12: string
... A33: escrow_legal214_agreement_actual | B33: dto | C33: JSONB | D33: accountDetails.eksAccountId | E33: NULL | F33: escrow_legal214_agreement_actual_dto | G33: eksAccountId_accountDetails | H33: string
A34: escrow_legal214_agreement_actual | B34: id | C34: BIGINT | E34: NOT NULL | F34: escrow_legal214_agreement_actual_dto | G34: id | H34: BIGINT
A35: escrow_legal214_agreement_actual | B35: sys_date_create_or_update | C35: timestamp | E35: NOT NULL | F35: escrow_legal214_agreement_actual_dto | G35: sys_date_create_or_update | H35: timestamp
A36: escrow_legal214_agreement_actual | B36: deleted | C36: boolean | E36: NOT NULL | F36: escrow_legal214_agreement_actual_dto | G36: deleted | H36: boolean
A37: escrow_legal214_agreement_actual | B37: headers | C37: JSONB | E37: NOT NULL | F37: escrow_legal214_agreement_actual_dto | G37: headers | H37: string
A38: escrow_legal214_agreement_actual | B38: escrow_id | C38: text | E38: NOT NULL | F38: escrow_legal214_agreement_actual_dto | G38: escrow_id | H38: string
A39: escrow_legalgk_agreement_actual | B39: dto | C39: JSONB | D39: agreement.beneficiaryBankRegionalUnit | E39: NULL | F39: escrow_legalgk_agreement_actual_dto | G39: beneficiarybankregionalunit | H39: string
A40: escrow_legalgk_agreement_actual | B40: dto | C40: JSONB | D40: agreement.beneficiaryBankBranch | E40: NULL | F40: escrow_legalgk_agreement_actual_dto | G40: beneficiaryBankBranch | H40: string
A41: escrow_legalgk_agreement_actual | B41: dto | C41: JSONB | D41: agreement.deponentBankRegionalUnit | E41: NULL | F41: escrow_legalgk_agreement_actual_dto | G41: deponentBankRegionalUnit | H41: string
A42: escrow_legalgk_agreement_actual | B42: dto | C42: JSONB | D42: agreement.deponentBankBranch | E42: NULL | F42: escrow_legalgk_agreement_actual_dto | G42: deponentBankBranch | H42: string
A43: escrow_legalgk_agreement_actual | B43: dto | C43: JSONB | D43: accounts.closeDate | E43: NULL | F43: escrow_legalgk_agreement_actual_dto | G43: closedate | H43: date
A44: escrow_legalgk_agreement_actual | B44: dto | C44: JSONB | D44: accounts.conclusionDate | E44: NULL | F44: escrow_legalgk_agreement_actual_dto | G44: conclusiondate | H44: date
A45: escrow_legalgk_agreement_actual | B45: dto | C45: JSONB | D45: depositorLegal.creditContract.date | E45: NULL | F45: escrow_legalgk_agreement_actual_dto | G45: depositorlegal_creditcontract_date | H45: date
A46: escrow_legalgk_agreement_actual | B46: dto | C46: JSONB | D46: depositorLegal.creditContract.crmId | E46: NULL | F46: escrow_legalgk_agreement_actual_dto | G46: depositorlegal_creditcontract_eks | H46: string
A47: escrow_legalgk_agreement_actual | B47: dto | C47: JSONB | D47: depositorLegal.creditContract.contractId | E47: NULL | F47: escrow_legalgk_agreement_actual_dto | G47: depositorlegal_creditcontract_kulid | H47: string
A48: escrow_legalgk_agreement_actual | B48: dto | C48: JSONB | D48: depositorLegal.creditContract.number | E48: NULL | F48: escrow_legalgk_agreement_actual_dto | G48: depositorlegal_creditcontract_number | H48: string
A49: escrow_legalgk_agreement_actual | B49: dto | C49: JSONB | D49: depositorLegal.epkId | E49: NULL | F49: escrow_legalgk_agreement_actual_dto | G49: depositorlegal_epkid | H49: string
A50: escrow_legalgk_agreement_actual | B50: dto | C50: JSONB | D50: agreement.escrowAmount.currency | E50: NOT NULL | F50: escrow_legalgk_agreement_actual_dto | G50: escrowamount_currency | H50: string
... A61: escrow_legalgk_agreement_actual | B61: dto | C61: jsonb | D61: agreement.depositWithdrawalDate | E61: NULL | F61: escrow_legalgk_agreement_actual_dto | G61: depositWithdrawalDate | H61: date
A62: escrow_legalgk_agreement_actual | B62: sys_date_create_or_update | C62: timestamp | E62: NOT NULL | F62: escrow_legalgk_agreement_actual_dto | G62: sys_date_create_or_update | H62: timestamp
A63: escrow_legalgk_agreement_actual | B63: deleted | C63: boolean | E63: NOT NULL | F63: escrow_legalgk_agreement_actual_dto | G63: deleted | H63: boolean
A64: escrow_legalgk_agreement_actual | B64: headers | C64: JSONB | E64: NOT NULL | F64: escrow_legalgk_agreement_actual_dto | G64: headers | H64: string
A65: escrow_legalgk_agreement_actual | B65: escrow_id | C65: text | E65: NOT NULL | F65: escrow_legalgk_agreement_actual_dto | G65: escrow_id | H65: string
A66: escrow_legalgk_agreement_actual | B66: id | C66: BIGINT | E66: NOT NULL | F66: escrow_legalgk_agreement_actual_dto | G66: id | H66: BIGINT
A67: escrow_legalgk_agreement_actual | B67: dto | C67: JSONB | D67: beneficiarysIndividual.creditContract.number | E67: NULL | F67: escrow_legalgk_beneficiariesindividual | G67: creditcontract_d_i | H67: string
A68: escrow_legalgk_agreement_actual | B68: dto | C68: JSONB | D68: beneficiarysIndividual.creditContract.date | E68: NULL | F68: escrow_legalgk_beneficiariesindividual | G68: creditcontract_i | H68: date
A69: escrow_legalgk_agreement_actual | B69: dto | C69: JSONB | D69: beneficiarysIndividual.dateOfBirth | E69: NULL | F69: escrow_legalgk_beneficiariesindividual | G69: dateofbirth | H69: string
A70: escrow_legalgk_agreement_actual | B70: dto | C70: JSONB | D70: beneficiarysIndividual.epkId | E70: NULL | F70: escrow_legalgk_beneficiariesindividual | G70: epkid_i | H70: string
A71: escrow_legalgk_agreement_actual | B71: dto | C71: JSONB | D71: beneficiarysIndividual.firstName | E71: NULL | F71: escrow_legalgk_beneficiariesindividual | G71: firstname | H71: string
A72: escrow_legalgk_agreement_actual | B72: dto | C72: JSONB | D72: beneficiarysIndividual.lastName | E72: NULL | F72: escrow_legalgk_beneficiariesindividual | G72: lastname | H72: string
A73: escrow_legalgk_agreement_actual | B73: dto | C73: JSONB | D73: beneficiarysIndividual.middleName | E73: NULL | F73: escrow_legalgk_beneficiariesindividual | G73: middlename | H73: string
A74: escrow_legalgk_agreement_actual | B74: sys_date_create_or_update | C74: timestamp | E74: NOT NULL | F74: escrow_legalgk_beneficiariesindividual | G74: sys_date_create_or_update | H74: timestamp
A75: escrow_legalgk_agreement_actual | B75: deleted | C75: boolean | E75: NOT NULL | F75: escrow_legalgk_beneficiariesindividual | G75: deleted | H75: boolean
A76: escrow_legalgk_agreement_actual | B76: headers | C76: JSONB | E76: NOT NULL | F76: escrow_legalgk_beneficiariesindividual | G76: headers | H76: string
A77: escrow_legalgk_agreement_actual | B77: escrow_id | C77: text | E77: NOT NULL | F77: escrow_legalgk_beneficiariesindividual | G77: escrowid | H77: string
